{
 "cells": [
  {
   "cell_type": "code",
   "execution_count": 2,
   "metadata": {},
   "outputs": [],
   "source": [
    "import os\n",
    "\n",
    "import cv2\n",
    "import matplotlib.pyplot as plt\n",
    "import numpy as np\n",
    "import pandas as pd\n",
    "import tensorflow as tf\n",
    "\n",
    "from fastestimator.architecture.unet import unet\n",
    "from fastestimator.dataset import cub200\n",
    "from fastestimator.estimator.estimator import Estimator\n",
    "from fastestimator.estimator.trace import Dice\n",
    "from fastestimator.pipeline.dynamic.preprocess import (AbstractPreprocessing,\n",
    "                                                       ImageReader, MatReader,\n",
    "                                                       Resize)\n",
    "from fastestimator.pipeline.pipeline import Pipeline\n",
    "from fastestimator.pipeline.static.preprocess import Minmax, Reshape"
   ]
  },
  {
   "cell_type": "code",
   "execution_count": 3,
   "metadata": {},
   "outputs": [],
   "source": [
    "#os.environ['CUDA_VISIBLE_DEVICES'] = ''\n",
    "pd.set_option('display.max_colwidth', 600)"
   ]
  },
  {
   "cell_type": "code",
   "execution_count": 4,
   "metadata": {},
   "outputs": [],
   "source": [
    "import dis"
   ]
  },
  {
   "cell_type": "markdown",
   "metadata": {},
   "source": [
    "## Download data"
   ]
  },
  {
   "cell_type": "code",
   "execution_count": null,
   "metadata": {},
   "outputs": [],
   "source": [
    "# cub200.load_data('/data/hsiming/Downloads/cub200/data/')"
   ]
  },
  {
   "cell_type": "code",
   "execution_count": 6,
   "metadata": {},
   "outputs": [],
   "source": [
    "csv_path = '/tmp/CUB200/cub200.csv'\n",
    "path = '/tmp/CUB200'"
   ]
  },
  {
   "cell_type": "code",
   "execution_count": 7,
   "metadata": {},
   "outputs": [],
   "source": [
    "class SelectKey(AbstractPreprocessing):\n",
    "    def transform(self, data, feature=None):\n",
    "        data = data['seg']\n",
    "        return data"
   ]
  },
  {
   "cell_type": "code",
   "execution_count": 33,
   "metadata": {},
   "outputs": [],
   "source": [
    "def my_func1(x):\n",
    "    return pow(x, 6)"
   ]
  },
  {
   "cell_type": "code",
   "execution_count": 36,
   "metadata": {},
   "outputs": [
    {
     "name": "stdout",
     "output_type": "stream",
     "text": [
      "  2           0 LOAD_GLOBAL              0 (pow)\n",
      "              2 LOAD_FAST                0 (x)\n",
      "              4 LOAD_CONST               1 (6)\n",
      "              6 CALL_FUNCTION            2\n",
      "              8 RETURN_VALUE\n"
     ]
    }
   ],
   "source": [
    "dis.dis(my_func1)"
   ]
  },
  {
   "cell_type": "code",
   "execution_count": 37,
   "metadata": {
    "scrolled": false
   },
   "outputs": [
    {
     "name": "stdout",
     "output_type": "stream",
     "text": [
      "Disassembly of __init__:\n",
      " 43           0 LOAD_FAST                1 (batch_size)\n",
      "              2 LOAD_FAST                0 (self)\n",
      "              4 STORE_ATTR               0 (batch_size)\n",
      "\n",
      " 44           6 LOAD_FAST                5 (train_data)\n",
      "              8 LOAD_FAST                0 (self)\n",
      "             10 STORE_ATTR               1 (train_data)\n",
      "\n",
      " 45          12 LOAD_FAST                2 (feature_name)\n",
      "             14 LOAD_FAST                0 (self)\n",
      "             16 STORE_ATTR               2 (feature_name)\n",
      "\n",
      " 46          18 LOAD_FAST                3 (transform_train)\n",
      "             20 LOAD_FAST                0 (self)\n",
      "             22 STORE_ATTR               3 (transform_train)\n",
      "\n",
      " 47          24 LOAD_FAST                4 (transform_dataset)\n",
      "             26 LOAD_FAST                0 (self)\n",
      "             28 STORE_ATTR               4 (transform_dataset)\n",
      "\n",
      " 48          30 LOAD_FAST                6 (validation_data)\n",
      "             32 LOAD_FAST                0 (self)\n",
      "             34 STORE_ATTR               5 (validation_data)\n",
      "\n",
      " 49          36 LOAD_FAST                7 (data_filter)\n",
      "             38 LOAD_FAST                0 (self)\n",
      "             40 STORE_ATTR               6 (data_filter)\n",
      "\n",
      " 50          42 LOAD_FAST                8 (padded_batch)\n",
      "             44 LOAD_FAST                0 (self)\n",
      "             46 STORE_ATTR               7 (padded_batch)\n",
      "\n",
      " 51          48 LOAD_FAST                9 (kwargs)\n",
      "             50 LOAD_FAST                0 (self)\n",
      "             52 STORE_ATTR               8 (kwargs)\n",
      "\n",
      " 52          54 LOAD_CONST               1 (1)\n",
      "             56 LOAD_FAST                0 (self)\n",
      "             58 STORE_ATTR               9 (num_process)\n",
      "\n",
      " 53          60 LOAD_CONST               1 (1)\n",
      "             62 LOAD_FAST                0 (self)\n",
      "             64 STORE_ATTR              10 (num_local_process)\n",
      "\n",
      " 54          66 LOAD_CONST               2 (0)\n",
      "             68 LOAD_FAST                0 (self)\n",
      "             70 STORE_ATTR              11 (rank)\n",
      "\n",
      " 55          72 LOAD_CONST               2 (0)\n",
      "             74 LOAD_FAST                0 (self)\n",
      "             76 STORE_ATTR              12 (local_rank)\n",
      "\n",
      " 56          78 LOAD_CONST               0 (None)\n",
      "             80 LOAD_FAST                0 (self)\n",
      "             82 STORE_ATTR              13 (decode_type)\n",
      "\n",
      " 57          84 LOAD_CONST               0 (None)\n",
      "             86 LOAD_FAST                0 (self)\n",
      "             88 STORE_ATTR              14 (feature_shape)\n",
      "\n",
      " 58          90 LOAD_CONST               0 (None)\n",
      "             92 LOAD_FAST                0 (self)\n",
      "             94 STORE_ATTR              15 (compression)\n",
      "             96 LOAD_CONST               0 (None)\n",
      "             98 RETURN_VALUE\n",
      "\n",
      "Disassembly of _get_tfrecord_config:\n",
      " 99           0 LOAD_CLOSURE             0 (data_dir)\n",
      "              2 BUILD_TUPLE              1\n",
      "              4 LOAD_CONST               1 (<code object <listcomp> at 0x7f1f490a0300, file \"/data/hsiming/dev/fastestimator-master/fastestimator/pipeline/pipeline.py\", line 99>)\n",
      "              6 LOAD_CONST               2 ('Pipeline._get_tfrecord_config.<locals>.<listcomp>')\n",
      "              8 MAKE_FUNCTION            8\n",
      "             10 LOAD_GLOBAL              0 (os)\n",
      "             12 LOAD_ATTR                1 (listdir)\n",
      "             14 LOAD_DEREF               0 (data_dir)\n",
      "             16 CALL_FUNCTION            1\n",
      "             18 GET_ITER\n",
      "             20 CALL_FUNCTION            1\n",
      "             22 STORE_FAST               2 (json_files)\n",
      "\n",
      "100          24 LOAD_GLOBAL              2 (len)\n",
      "             26 LOAD_FAST                2 (json_files)\n",
      "             28 CALL_FUNCTION            1\n",
      "             30 LOAD_CONST               3 (0)\n",
      "             32 COMPARE_OP               4 (>)\n",
      "             34 POP_JUMP_IF_TRUE        48\n",
      "             36 LOAD_GLOBAL              3 (AssertionError)\n",
      "             38 LOAD_CONST               4 ('Cannot find .json file in %s')\n",
      "             40 LOAD_DEREF               0 (data_dir)\n",
      "             42 BINARY_MODULO\n",
      "             44 CALL_FUNCTION            1\n",
      "             46 RAISE_VARARGS            1\n",
      "\n",
      "101     >>   48 BUILD_LIST               0\n",
      "             50 BUILD_LIST               0\n",
      "             52 LOAD_CONST               5 (('train', 'eval'))\n",
      "             54 BUILD_CONST_KEY_MAP      2\n",
      "             56 LOAD_FAST                0 (self)\n",
      "             58 STORE_ATTR               4 (file_names)\n",
      "\n",
      "102          60 LOAD_CONST               3 (0)\n",
      "             62 LOAD_CONST               3 (0)\n",
      "             64 LOAD_CONST               5 (('train', 'eval'))\n",
      "             66 BUILD_CONST_KEY_MAP      2\n",
      "             68 LOAD_FAST                0 (self)\n",
      "             70 STORE_ATTR               5 (num_examples)\n",
      "\n",
      "103          72 EXTENDED_ARG             1\n",
      "             74 SETUP_LOOP             260 (to 336)\n",
      "             76 LOAD_FAST                2 (json_files)\n",
      "             78 GET_ITER\n",
      "        >>   80 FOR_ITER               252 (to 334)\n",
      "             82 STORE_FAST               3 (json_file)\n",
      "\n",
      "104          84 LOAD_GLOBAL              6 (json)\n",
      "             86 LOAD_ATTR                7 (load)\n",
      "             88 LOAD_GLOBAL              8 (open)\n",
      "             90 LOAD_FAST                3 (json_file)\n",
      "             92 LOAD_CONST               6 ('r')\n",
      "             94 CALL_FUNCTION            2\n",
      "             96 CALL_FUNCTION            1\n",
      "             98 STORE_FAST               4 (summary)\n",
      "\n",
      "105         100 LOAD_FAST                0 (self)\n",
      "            102 LOAD_ATTR                9 (decode_type)\n",
      "            104 LOAD_CONST               7 (None)\n",
      "            106 COMPARE_OP               8 (is)\n",
      "            108 POP_JUMP_IF_FALSE      140\n",
      "\n",
      "106         110 LOAD_CONST               8 (<code object <dictcomp> at 0x7f1f46cdfae0, file \"/data/hsiming/dev/fastestimator-master/fastestimator/pipeline/pipeline.py\", line 106>)\n",
      "            112 LOAD_CONST               9 ('Pipeline._get_tfrecord_config.<locals>.<dictcomp>')\n",
      "            114 MAKE_FUNCTION            0\n",
      "            116 LOAD_GLOBAL             10 (zip)\n",
      "            118 LOAD_FAST                4 (summary)\n",
      "            120 LOAD_CONST              10 ('feature_name')\n",
      "            122 BINARY_SUBSCR\n",
      "            124 LOAD_FAST                4 (summary)\n",
      "            126 LOAD_CONST              11 ('feature_dtype')\n",
      "            128 BINARY_SUBSCR\n",
      "            130 CALL_FUNCTION            2\n",
      "            132 GET_ITER\n",
      "            134 CALL_FUNCTION            1\n",
      "            136 LOAD_FAST                0 (self)\n",
      "            138 STORE_ATTR               9 (decode_type)\n",
      "\n",
      "107     >>  140 LOAD_FAST                0 (self)\n",
      "            142 LOAD_ATTR               11 (feature_shape)\n",
      "            144 LOAD_CONST               7 (None)\n",
      "            146 COMPARE_OP               8 (is)\n",
      "            148 POP_JUMP_IF_FALSE      198\n",
      "\n",
      "108         150 LOAD_CONST              12 (<code object <dictcomp> at 0x7f1f46ce25d0, file \"/data/hsiming/dev/fastestimator-master/fastestimator/pipeline/pipeline.py\", line 108>)\n",
      "            152 LOAD_CONST               9 ('Pipeline._get_tfrecord_config.<locals>.<dictcomp>')\n",
      "            154 MAKE_FUNCTION            0\n",
      "            156 LOAD_GLOBAL             10 (zip)\n",
      "            158 LOAD_FAST                4 (summary)\n",
      "            160 LOAD_CONST              10 ('feature_name')\n",
      "            162 BINARY_SUBSCR\n",
      "            164 LOAD_FAST                4 (summary)\n",
      "            166 LOAD_CONST              13 ('feature_shape')\n",
      "            168 BINARY_SUBSCR\n",
      "            170 CALL_FUNCTION            2\n",
      "            172 GET_ITER\n",
      "            174 CALL_FUNCTION            1\n",
      "            176 LOAD_FAST                0 (self)\n",
      "            178 STORE_ATTR              11 (feature_shape)\n",
      "\n",
      "109         180 LOAD_CONST              14 ('compression')\n",
      "            182 LOAD_FAST                4 (summary)\n",
      "            184 COMPARE_OP               6 (in)\n",
      "            186 POP_JUMP_IF_FALSE      198\n",
      "\n",
      "110         188 LOAD_FAST                4 (summary)\n",
      "            190 LOAD_CONST              14 ('compression')\n",
      "            192 BINARY_SUBSCR\n",
      "            194 LOAD_FAST                0 (self)\n",
      "            196 STORE_ATTR              12 (compression)\n",
      "\n",
      "111     >>  198 LOAD_CONST              15 ('eval_files')\n",
      "            200 LOAD_FAST                4 (summary)\n",
      "            202 COMPARE_OP               6 (in)\n",
      "            204 EXTENDED_ARG             1\n",
      "            206 POP_JUMP_IF_FALSE      270\n",
      "\n",
      "112         208 LOAD_FAST                0 (self)\n",
      "            210 LOAD_ATTR                4 (file_names)\n",
      "            212 LOAD_CONST              16 ('eval')\n",
      "            214 BINARY_SUBSCR\n",
      "            216 LOAD_ATTR               13 (extend)\n",
      "            218 LOAD_CLOSURE             0 (data_dir)\n",
      "            220 BUILD_TUPLE              1\n",
      "            222 LOAD_CONST              17 (<code object <listcomp> at 0x7f1f46ce26f0, file \"/data/hsiming/dev/fastestimator-master/fastestimator/pipeline/pipeline.py\", line 112>)\n",
      "            224 LOAD_CONST               2 ('Pipeline._get_tfrecord_config.<locals>.<listcomp>')\n",
      "            226 MAKE_FUNCTION            8\n",
      "            228 LOAD_FAST                4 (summary)\n",
      "            230 LOAD_CONST              15 ('eval_files')\n",
      "            232 BINARY_SUBSCR\n",
      "            234 GET_ITER\n",
      "            236 CALL_FUNCTION            1\n",
      "            238 CALL_FUNCTION            1\n",
      "            240 POP_TOP\n",
      "\n",
      "113         242 LOAD_FAST                0 (self)\n",
      "            244 LOAD_ATTR                5 (num_examples)\n",
      "            246 LOAD_CONST              16 ('eval')\n",
      "            248 DUP_TOP_TWO\n",
      "            250 BINARY_SUBSCR\n",
      "            252 LOAD_GLOBAL             14 (np)\n",
      "            254 LOAD_ATTR               15 (sum)\n",
      "            256 LOAD_FAST                4 (summary)\n",
      "            258 LOAD_CONST              18 ('num_eval_examples')\n",
      "            260 BINARY_SUBSCR\n",
      "            262 CALL_FUNCTION            1\n",
      "            264 INPLACE_ADD\n",
      "            266 ROT_THREE\n",
      "            268 STORE_SUBSCR\n",
      "\n",
      "114     >>  270 LOAD_FAST                0 (self)\n",
      "            272 LOAD_ATTR                4 (file_names)\n",
      "            274 LOAD_CONST              19 ('train')\n",
      "            276 BINARY_SUBSCR\n",
      "            278 LOAD_ATTR               13 (extend)\n",
      "            280 LOAD_CLOSURE             0 (data_dir)\n",
      "            282 BUILD_TUPLE              1\n",
      "            284 LOAD_CONST              20 (<code object <listcomp> at 0x7f1f46ce2810, file \"/data/hsiming/dev/fastestimator-master/fastestimator/pipeline/pipeline.py\", line 114>)\n",
      "            286 LOAD_CONST               2 ('Pipeline._get_tfrecord_config.<locals>.<listcomp>')\n",
      "            288 MAKE_FUNCTION            8\n",
      "            290 LOAD_FAST                4 (summary)\n",
      "            292 LOAD_CONST              21 ('train_files')\n",
      "            294 BINARY_SUBSCR\n",
      "            296 GET_ITER\n",
      "            298 CALL_FUNCTION            1\n",
      "            300 CALL_FUNCTION            1\n",
      "            302 POP_TOP\n",
      "\n",
      "115         304 LOAD_FAST                0 (self)\n",
      "            306 LOAD_ATTR                5 (num_examples)\n",
      "            308 LOAD_CONST              19 ('train')\n",
      "            310 DUP_TOP_TWO\n",
      "            312 BINARY_SUBSCR\n",
      "            314 LOAD_GLOBAL             14 (np)\n",
      "            316 LOAD_ATTR               15 (sum)\n",
      "            318 LOAD_FAST                4 (summary)\n",
      "            320 LOAD_CONST              22 ('num_train_examples')\n",
      "            322 BINARY_SUBSCR\n",
      "            324 CALL_FUNCTION            1\n",
      "            326 INPLACE_ADD\n",
      "            328 ROT_THREE\n",
      "            330 STORE_SUBSCR\n",
      "            332 JUMP_ABSOLUTE           80\n",
      "        >>  334 POP_BLOCK\n",
      "\n",
      "116     >>  336 LOAD_GLOBAL             16 (get_features)\n",
      "            338 LOAD_FAST                0 (self)\n",
      "            340 LOAD_ATTR                4 (file_names)\n",
      "            342 LOAD_CONST              19 ('train')\n",
      "            344 BINARY_SUBSCR\n",
      "            346 LOAD_CONST               3 (0)\n",
      "            348 BINARY_SUBSCR\n",
      "            350 LOAD_FAST                0 (self)\n",
      "            352 LOAD_ATTR               12 (compression)\n",
      "            354 LOAD_CONST              23 (('compression',))\n",
      "            356 CALL_FUNCTION_KW         2\n",
      "            358 LOAD_FAST                0 (self)\n",
      "            360 STORE_ATTR              17 (keys_to_features)\n",
      "\n",
      "117         362 LOAD_GLOBAL              2 (len)\n",
      "            364 LOAD_FAST                0 (self)\n",
      "            366 LOAD_ATTR                4 (file_names)\n",
      "            368 LOAD_CONST              19 ('train')\n",
      "            370 BINARY_SUBSCR\n",
      "            372 CALL_FUNCTION            1\n",
      "            374 LOAD_FAST                0 (self)\n",
      "            376 LOAD_ATTR               18 (num_local_process)\n",
      "            378 COMPARE_OP               5 (>=)\n",
      "            380 EXTENDED_ARG             1\n",
      "            382 POP_JUMP_IF_TRUE       392\n",
      "            384 LOAD_GLOBAL              3 (AssertionError)\n",
      "            386 LOAD_CONST              24 ('number of training file per local process should at least be 1')\n",
      "            388 CALL_FUNCTION            1\n",
      "            390 RAISE_VARARGS            1\n",
      "\n",
      "118     >>  392 LOAD_FAST                0 (self)\n",
      "            394 LOAD_ATTR               19 (local_rank)\n",
      "            396 LOAD_CONST               3 (0)\n",
      "            398 COMPARE_OP               2 (==)\n",
      "            400 EXTENDED_ARG             1\n",
      "            402 POP_JUMP_IF_FALSE      434\n",
      "\n",
      "119         404 LOAD_GLOBAL             20 (print)\n",
      "            406 LOAD_CONST              25 ('FastEstimator: Found %d examples for training and %d for validation in %s')\n",
      "            408 LOAD_FAST                0 (self)\n",
      "            410 LOAD_ATTR                5 (num_examples)\n",
      "            412 LOAD_CONST              19 ('train')\n",
      "            414 BINARY_SUBSCR\n",
      "            416 LOAD_FAST                0 (self)\n",
      "            418 LOAD_ATTR                5 (num_examples)\n",
      "            420 LOAD_CONST              16 ('eval')\n",
      "            422 BINARY_SUBSCR\n",
      "            424 LOAD_DEREF               0 (data_dir)\n",
      "            426 BUILD_TUPLE              3\n",
      "            428 BINARY_MODULO\n",
      "            430 CALL_FUNCTION            1\n",
      "            432 POP_TOP\n",
      "        >>  434 LOAD_CONST               7 (None)\n",
      "            436 RETURN_VALUE\n",
      "\n",
      "Disassembly of _input_source:\n",
      "207           0 LOAD_FAST                0 (self)\n",
      "              2 LOAD_ATTR                0 (_input_stream)\n",
      "              4 LOAD_FAST                1 (mode)\n",
      "              6 CALL_FUNCTION            1\n",
      "              8 STORE_FAST               3 (dataset)\n",
      "\n",
      "208          10 SETUP_LOOP              34 (to 46)\n",
      "             12 LOAD_FAST                3 (dataset)\n",
      "             14 LOAD_ATTR                1 (take)\n",
      "             16 LOAD_FAST                2 (num_steps)\n",
      "             18 CALL_FUNCTION            1\n",
      "             20 GET_ITER\n",
      "        >>   22 FOR_ITER                20 (to 44)\n",
      "             24 STORE_FAST               4 (batch_data)\n",
      "\n",
      "209          26 LOAD_FAST                0 (self)\n",
      "             28 LOAD_ATTR                2 (final_transform)\n",
      "             30 LOAD_FAST                4 (batch_data)\n",
      "             32 CALL_FUNCTION            1\n",
      "             34 STORE_FAST               4 (batch_data)\n",
      "\n",
      "210          36 LOAD_FAST                4 (batch_data)\n",
      "             38 YIELD_VALUE\n",
      "             40 POP_TOP\n",
      "             42 JUMP_ABSOLUTE           22\n",
      "        >>   44 POP_BLOCK\n",
      "        >>   46 LOAD_CONST               1 (None)\n",
      "             48 RETURN_VALUE\n",
      "\n",
      "Disassembly of _input_stream:\n",
      "131           0 LOAD_DEREF               2 (self)\n",
      "              2 LOAD_ATTR                0 (file_names)\n",
      "              4 LOAD_DEREF               1 (mode)\n",
      "              6 BINARY_SUBSCR\n",
      "              8 STORE_FAST               2 (filenames)\n",
      "\n",
      "133          10 LOAD_DEREF               1 (mode)\n",
      "             12 LOAD_CONST               1 ('train')\n",
      "             14 COMPARE_OP               2 (==)\n",
      "             16 POP_JUMP_IF_FALSE      120\n",
      "\n",
      "134          18 LOAD_GLOBAL              1 (tf)\n",
      "             20 LOAD_ATTR                2 (data)\n",
      "             22 LOAD_ATTR                3 (Dataset)\n",
      "             24 LOAD_ATTR                4 (from_tensor_slices)\n",
      "             26 LOAD_FAST                2 (filenames)\n",
      "             28 CALL_FUNCTION            1\n",
      "             30 STORE_FAST               3 (dataset)\n",
      "\n",
      "135          32 LOAD_FAST                3 (dataset)\n",
      "             34 LOAD_ATTR                5 (shard)\n",
      "             36 LOAD_DEREF               2 (self)\n",
      "             38 LOAD_ATTR                6 (num_local_process)\n",
      "             40 LOAD_DEREF               2 (self)\n",
      "             42 LOAD_ATTR                7 (local_rank)\n",
      "             44 CALL_FUNCTION            2\n",
      "             46 STORE_FAST               3 (dataset)\n",
      "\n",
      "136          48 LOAD_FAST                3 (dataset)\n",
      "             50 LOAD_ATTR                8 (shuffle)\n",
      "             52 LOAD_GLOBAL              9 (len)\n",
      "             54 LOAD_FAST                2 (filenames)\n",
      "             56 CALL_FUNCTION            1\n",
      "             58 CALL_FUNCTION            1\n",
      "             60 STORE_FAST               3 (dataset)\n",
      "\n",
      "137          62 LOAD_FAST                3 (dataset)\n",
      "             64 LOAD_ATTR               10 (interleave)\n",
      "             66 LOAD_CLOSURE             2 (self)\n",
      "             68 BUILD_TUPLE              1\n",
      "             70 LOAD_CONST               2 (<code object <lambda> at 0x7f1f46ce2b70, file \"/data/hsiming/dev/fastestimator-master/fastestimator/pipeline/pipeline.py\", line 137>)\n",
      "             72 LOAD_CONST               3 ('Pipeline._input_stream.<locals>.<lambda>')\n",
      "             74 MAKE_FUNCTION            8\n",
      "             76 LOAD_DEREF               2 (self)\n",
      "             78 LOAD_ATTR               11 (num_subprocess)\n",
      "             80 LOAD_CONST               4 (2)\n",
      "             82 LOAD_CONST               5 (('cycle_length', 'block_length'))\n",
      "             84 CALL_FUNCTION_KW         3\n",
      "             86 STORE_FAST               3 (dataset)\n",
      "\n",
      "138          88 LOAD_FAST                3 (dataset)\n",
      "             90 LOAD_ATTR                8 (shuffle)\n",
      "             92 LOAD_GLOBAL             12 (min)\n",
      "             94 LOAD_CONST               6 (10000)\n",
      "             96 LOAD_DEREF               2 (self)\n",
      "             98 LOAD_ATTR               13 (num_examples)\n",
      "            100 LOAD_DEREF               1 (mode)\n",
      "            102 BINARY_SUBSCR\n",
      "            104 CALL_FUNCTION            2\n",
      "            106 CALL_FUNCTION            1\n",
      "            108 STORE_FAST               3 (dataset)\n",
      "\n",
      "139         110 LOAD_FAST                3 (dataset)\n",
      "            112 LOAD_ATTR               14 (repeat)\n",
      "            114 CALL_FUNCTION            0\n",
      "            116 STORE_FAST               3 (dataset)\n",
      "            118 JUMP_FORWARD            18 (to 138)\n",
      "\n",
      "141     >>  120 LOAD_GLOBAL              1 (tf)\n",
      "            122 LOAD_ATTR                2 (data)\n",
      "            124 LOAD_ATTR               15 (TFRecordDataset)\n",
      "            126 LOAD_FAST                2 (filenames)\n",
      "            128 LOAD_DEREF               2 (self)\n",
      "            130 LOAD_ATTR               16 (compression)\n",
      "            132 LOAD_CONST               7 (('compression_type',))\n",
      "            134 CALL_FUNCTION_KW         2\n",
      "            136 STORE_FAST               3 (dataset)\n",
      "\n",
      "143     >>  138 LOAD_FAST                3 (dataset)\n",
      "            140 LOAD_ATTR               17 (map)\n",
      "            142 LOAD_CLOSURE             2 (self)\n",
      "            144 BUILD_TUPLE              1\n",
      "            146 LOAD_CONST               8 (<code object <lambda> at 0x7f1f46ce2d20, file \"/data/hsiming/dev/fastestimator-master/fastestimator/pipeline/pipeline.py\", line 143>)\n",
      "            148 LOAD_CONST               3 ('Pipeline._input_stream.<locals>.<lambda>')\n",
      "            150 MAKE_FUNCTION            8\n",
      "            152 LOAD_DEREF               2 (self)\n",
      "            154 LOAD_ATTR               11 (num_subprocess)\n",
      "            156 LOAD_CONST               9 (('num_parallel_calls',))\n",
      "            158 CALL_FUNCTION_KW         2\n",
      "            160 STORE_FAST               3 (dataset)\n",
      "\n",
      "145         162 LOAD_GLOBAL             18 (isinstance)\n",
      "            164 LOAD_DEREF               2 (self)\n",
      "            166 LOAD_ATTR               19 (data_filter)\n",
      "            168 LOAD_GLOBAL             20 (list)\n",
      "            170 CALL_FUNCTION            2\n",
      "            172 EXTENDED_ARG             1\n",
      "            174 POP_JUMP_IF_FALSE      306\n",
      "\n",
      "146         176 LOAD_GLOBAL              9 (len)\n",
      "            178 LOAD_DEREF               2 (self)\n",
      "            180 LOAD_ATTR               19 (data_filter)\n",
      "            182 CALL_FUNCTION            1\n",
      "            184 LOAD_CONST              10 (1)\n",
      "            186 COMPARE_OP               4 (>)\n",
      "            188 POP_JUMP_IF_TRUE       198\n",
      "            190 LOAD_GLOBAL             21 (AssertionError)\n",
      "            192 LOAD_CONST              11 ('must provide at least two data filters for dataset zipping')\n",
      "            194 CALL_FUNCTION            1\n",
      "            196 RAISE_VARARGS            1\n",
      "\n",
      "147     >>  198 BUILD_TUPLE              0\n",
      "            200 STORE_FAST               4 (zip_ds)\n",
      "\n",
      "148         202 SETUP_LOOP              86 (to 290)\n",
      "            204 LOAD_DEREF               2 (self)\n",
      "            206 LOAD_ATTR               19 (data_filter)\n",
      "            208 GET_ITER\n",
      "        >>  210 FOR_ITER                76 (to 288)\n",
      "            212 STORE_DEREF              0 (data_filter)\n",
      "\n",
      "149         214 LOAD_GLOBAL             18 (isinstance)\n",
      "            216 LOAD_DEREF               0 (data_filter)\n",
      "            218 LOAD_GLOBAL             22 (Filter)\n",
      "            220 CALL_FUNCTION            2\n",
      "            222 POP_JUMP_IF_TRUE       232\n",
      "            224 LOAD_GLOBAL             21 (AssertionError)\n",
      "            226 LOAD_CONST              12 ('must provide Filter instance')\n",
      "            228 CALL_FUNCTION            1\n",
      "            230 RAISE_VARARGS            1\n",
      "\n",
      "150     >>  232 LOAD_FAST                3 (dataset)\n",
      "            234 LOAD_ATTR               23 (filter)\n",
      "            236 LOAD_CLOSURE             0 (data_filter)\n",
      "            238 BUILD_TUPLE              1\n",
      "            240 LOAD_CONST              13 (<code object <lambda> at 0x7f1f46ce2f60, file \"/data/hsiming/dev/fastestimator-master/fastestimator/pipeline/pipeline.py\", line 150>)\n",
      "            242 LOAD_CONST               3 ('Pipeline._input_stream.<locals>.<lambda>')\n",
      "            244 MAKE_FUNCTION            8\n",
      "            246 CALL_FUNCTION            1\n",
      "            248 STORE_FAST               5 (ds)\n",
      "\n",
      "151         250 LOAD_FAST                5 (ds)\n",
      "            252 LOAD_ATTR               17 (map)\n",
      "            254 LOAD_CLOSURE             1 (mode)\n",
      "            256 LOAD_CLOSURE             2 (self)\n",
      "            258 BUILD_TUPLE              2\n",
      "            260 LOAD_CONST              14 (<code object <lambda> at 0x7f1f46d05030, file \"/data/hsiming/dev/fastestimator-master/fastestimator/pipeline/pipeline.py\", line 151>)\n",
      "            262 LOAD_CONST               3 ('Pipeline._input_stream.<locals>.<lambda>')\n",
      "            264 MAKE_FUNCTION            8\n",
      "            266 LOAD_DEREF               2 (self)\n",
      "            268 LOAD_ATTR               11 (num_subprocess)\n",
      "            270 LOAD_CONST               9 (('num_parallel_calls',))\n",
      "            272 CALL_FUNCTION_KW         2\n",
      "            274 STORE_FAST               5 (ds)\n",
      "\n",
      "152         276 LOAD_FAST                4 (zip_ds)\n",
      "            278 LOAD_FAST                5 (ds)\n",
      "            280 BUILD_TUPLE              1\n",
      "            282 INPLACE_ADD\n",
      "            284 STORE_FAST               4 (zip_ds)\n",
      "            286 JUMP_ABSOLUTE          210\n",
      "        >>  288 POP_BLOCK\n",
      "\n",
      "153     >>  290 LOAD_GLOBAL              1 (tf)\n",
      "            292 LOAD_ATTR                2 (data)\n",
      "            294 LOAD_ATTR                3 (Dataset)\n",
      "            296 LOAD_ATTR               24 (zip)\n",
      "            298 LOAD_FAST                4 (zip_ds)\n",
      "            300 CALL_FUNCTION            1\n",
      "            302 STORE_FAST               3 (dataset)\n",
      "            304 JUMP_FORWARD            76 (to 382)\n",
      "\n",
      "155     >>  306 LOAD_GLOBAL             18 (isinstance)\n",
      "            308 LOAD_DEREF               2 (self)\n",
      "            310 LOAD_ATTR               19 (data_filter)\n",
      "            312 LOAD_GLOBAL             22 (Filter)\n",
      "            314 CALL_FUNCTION            2\n",
      "            316 EXTENDED_ARG             1\n",
      "            318 POP_JUMP_IF_FALSE      356\n",
      "            320 LOAD_DEREF               2 (self)\n",
      "            322 LOAD_ATTR               19 (data_filter)\n",
      "            324 LOAD_ATTR               25 (mode)\n",
      "            326 LOAD_DEREF               1 (mode)\n",
      "            328 LOAD_CONST              15 ('both')\n",
      "            330 BUILD_LIST               2\n",
      "            332 COMPARE_OP               6 (in)\n",
      "            334 EXTENDED_ARG             1\n",
      "            336 POP_JUMP_IF_FALSE      356\n",
      "\n",
      "156         338 LOAD_FAST                3 (dataset)\n",
      "            340 LOAD_ATTR               23 (filter)\n",
      "            342 LOAD_CLOSURE             2 (self)\n",
      "            344 BUILD_TUPLE              1\n",
      "            346 LOAD_CONST              16 (<code object <lambda> at 0x7f1f46d050c0, file \"/data/hsiming/dev/fastestimator-master/fastestimator/pipeline/pipeline.py\", line 156>)\n",
      "            348 LOAD_CONST               3 ('Pipeline._input_stream.<locals>.<lambda>')\n",
      "            350 MAKE_FUNCTION            8\n",
      "            352 CALL_FUNCTION            1\n",
      "            354 STORE_FAST               3 (dataset)\n",
      "\n",
      "157     >>  356 LOAD_FAST                3 (dataset)\n",
      "            358 LOAD_ATTR               17 (map)\n",
      "            360 LOAD_CLOSURE             1 (mode)\n",
      "            362 LOAD_CLOSURE             2 (self)\n",
      "            364 BUILD_TUPLE              2\n",
      "            366 LOAD_CONST              17 (<code object <lambda> at 0x7f1f46d05150, file \"/data/hsiming/dev/fastestimator-master/fastestimator/pipeline/pipeline.py\", line 157>)\n",
      "            368 LOAD_CONST               3 ('Pipeline._input_stream.<locals>.<lambda>')\n",
      "            370 MAKE_FUNCTION            8\n",
      "            372 LOAD_DEREF               2 (self)\n",
      "            374 LOAD_ATTR               11 (num_subprocess)\n",
      "            376 LOAD_CONST               9 (('num_parallel_calls',))\n",
      "            378 CALL_FUNCTION_KW         2\n",
      "            380 STORE_FAST               3 (dataset)\n",
      "\n",
      "159     >>  382 LOAD_DEREF               2 (self)\n",
      "            384 LOAD_ATTR               26 (padded_batch)\n",
      "            386 EXTENDED_ARG             1\n",
      "            388 POP_JUMP_IF_FALSE      424\n",
      "\n",
      "160         390 LOAD_FAST                3 (dataset)\n",
      "            392 LOAD_ATTR               26 (padded_batch)\n",
      "            394 LOAD_DEREF               2 (self)\n",
      "            396 LOAD_ATTR               27 (batch_size)\n",
      "            398 LOAD_CLOSURE             2 (self)\n",
      "            400 BUILD_TUPLE              1\n",
      "            402 LOAD_CONST              18 (<code object <dictcomp> at 0x7f1f46d051e0, file \"/data/hsiming/dev/fastestimator-master/fastestimator/pipeline/pipeline.py\", line 160>)\n",
      "            404 LOAD_CONST              19 ('Pipeline._input_stream.<locals>.<dictcomp>')\n",
      "            406 MAKE_FUNCTION            8\n",
      "            408 LOAD_DEREF               2 (self)\n",
      "            410 LOAD_ATTR               28 (feature_name)\n",
      "            412 GET_ITER\n",
      "            414 CALL_FUNCTION            1\n",
      "            416 LOAD_CONST              20 (('padded_shapes',))\n",
      "            418 CALL_FUNCTION_KW         2\n",
      "            420 STORE_FAST               3 (dataset)\n",
      "            422 JUMP_FORWARD            12 (to 436)\n",
      "\n",
      "162     >>  424 LOAD_FAST                3 (dataset)\n",
      "            426 LOAD_ATTR               29 (batch)\n",
      "            428 LOAD_DEREF               2 (self)\n",
      "            430 LOAD_ATTR               27 (batch_size)\n",
      "            432 CALL_FUNCTION            1\n",
      "            434 STORE_FAST               3 (dataset)\n",
      "\n",
      "164     >>  436 LOAD_FAST                3 (dataset)\n",
      "            438 LOAD_ATTR               30 (prefetch)\n",
      "            440 LOAD_CONST              10 (1)\n",
      "            442 LOAD_CONST              21 (('buffer_size',))\n",
      "            444 CALL_FUNCTION_KW         1\n",
      "            446 STORE_FAST               3 (dataset)\n",
      "\n",
      "165         448 LOAD_FAST                3 (dataset)\n",
      "            450 RETURN_VALUE\n",
      "\n",
      "Disassembly of _prepare:\n",
      " 70           0 LOAD_FAST                1 (inputs)\n",
      "              2 LOAD_FAST                0 (self)\n",
      "              4 STORE_ATTR               0 (inputs)\n",
      "\n",
      " 71           6 LOAD_GLOBAL              1 (min)\n",
      "              8 LOAD_CONST               1 (8)\n",
      "             10 LOAD_GLOBAL              2 (multiprocessing)\n",
      "             12 LOAD_ATTR                3 (cpu_count)\n",
      "             14 CALL_FUNCTION            0\n",
      "             16 LOAD_FAST                0 (self)\n",
      "             18 LOAD_ATTR                4 (num_local_process)\n",
      "             20 BINARY_FLOOR_DIVIDE\n",
      "             22 CALL_FUNCTION            2\n",
      "             24 LOAD_FAST                0 (self)\n",
      "             26 STORE_ATTR               5 (num_subprocess)\n",
      "\n",
      " 72          28 LOAD_FAST                0 (self)\n",
      "             30 LOAD_ATTR                6 (train_data)\n",
      "             32 POP_JUMP_IF_FALSE      120\n",
      "\n",
      " 73          34 LOAD_GLOBAL              7 (TFRecorder)\n",
      "             36 BUILD_TUPLE              0\n",
      "             38 LOAD_FAST                0 (self)\n",
      "             40 LOAD_ATTR                6 (train_data)\n",
      "\n",
      " 74          42 LOAD_FAST                0 (self)\n",
      "             44 LOAD_ATTR                8 (feature_name)\n",
      "\n",
      " 75          46 LOAD_FAST                0 (self)\n",
      "             48 LOAD_ATTR                9 (transform_dataset)\n",
      "\n",
      " 76          50 LOAD_FAST                0 (self)\n",
      "             52 LOAD_ATTR               10 (validation_data)\n",
      "             54 LOAD_CONST               2 (('train_data', 'feature_name', 'transform_dataset', 'validation_data'))\n",
      "             56 BUILD_CONST_KEY_MAP      4\n",
      "\n",
      " 77          58 LOAD_FAST                0 (self)\n",
      "             60 LOAD_ATTR               11 (kwargs)\n",
      "             62 BUILD_MAP_UNPACK_WITH_CALL     2\n",
      "             64 CALL_FUNCTION_EX         1\n",
      "             66 STORE_FAST               2 (tfrecorder)\n",
      "\n",
      " 78          68 LOAD_FAST                0 (self)\n",
      "             70 LOAD_ATTR               12 (rank)\n",
      "             72 LOAD_FAST                2 (tfrecorder)\n",
      "             74 STORE_ATTR              12 (rank)\n",
      "\n",
      " 79          76 LOAD_FAST                0 (self)\n",
      "             78 LOAD_ATTR               13 (local_rank)\n",
      "             80 LOAD_FAST                2 (tfrecorder)\n",
      "             82 STORE_ATTR              13 (local_rank)\n",
      "\n",
      " 80          84 LOAD_FAST                0 (self)\n",
      "             86 LOAD_ATTR               14 (num_process)\n",
      "             88 LOAD_FAST                2 (tfrecorder)\n",
      "             90 STORE_ATTR              14 (num_process)\n",
      "\n",
      " 81          92 LOAD_FAST                0 (self)\n",
      "             94 LOAD_ATTR                5 (num_subprocess)\n",
      "             96 LOAD_FAST                2 (tfrecorder)\n",
      "             98 STORE_ATTR               5 (num_subprocess)\n",
      "\n",
      " 82         100 LOAD_FAST                0 (self)\n",
      "            102 LOAD_ATTR               15 (edit_feature)\n",
      "            104 LOAD_FAST                2 (tfrecorder)\n",
      "            106 STORE_ATTR              15 (edit_feature)\n",
      "\n",
      " 83         108 LOAD_FAST                2 (tfrecorder)\n",
      "            110 LOAD_ATTR               16 (create_tfrecord)\n",
      "            112 LOAD_FAST                1 (inputs)\n",
      "            114 CALL_FUNCTION            1\n",
      "            116 LOAD_FAST                0 (self)\n",
      "            118 STORE_ATTR               0 (inputs)\n",
      "\n",
      " 84     >>  120 LOAD_FAST                0 (self)\n",
      "            122 LOAD_ATTR               14 (num_process)\n",
      "            124 LOAD_CONST               3 (1)\n",
      "            126 COMPARE_OP               4 (>)\n",
      "            128 POP_JUMP_IF_FALSE      158\n",
      "\n",
      " 85         130 LOAD_CONST               4 (0)\n",
      "            132 LOAD_CONST               5 (None)\n",
      "            134 IMPORT_NAME             17 (horovod.tensorflow.keras)\n",
      "            136 LOAD_ATTR               18 (tensorflow)\n",
      "            138 LOAD_ATTR               19 (keras)\n",
      "            140 STORE_FAST               3 (hvd)\n",
      "\n",
      " 86         142 LOAD_FAST                3 (hvd)\n",
      "            144 LOAD_ATTR               20 (allreduce)\n",
      "            146 LOAD_CONST               4 (0)\n",
      "            148 BUILD_LIST               1\n",
      "            150 LOAD_CONST               6 ('Barrier')\n",
      "            152 LOAD_CONST               7 (('name',))\n",
      "            154 CALL_FUNCTION_KW         2\n",
      "            156 POP_TOP\n",
      "\n",
      " 87     >>  158 LOAD_FAST                0 (self)\n",
      "            160 LOAD_ATTR               21 (_get_tfrecord_config)\n",
      "            162 LOAD_FAST                0 (self)\n",
      "            164 LOAD_ATTR                0 (inputs)\n",
      "            166 CALL_FUNCTION            1\n",
      "            168 POP_TOP\n",
      "            170 LOAD_CONST               5 (None)\n",
      "            172 RETURN_VALUE\n",
      "\n",
      "Disassembly of _preprocess_fn:\n",
      "176           0 BUILD_MAP                0\n",
      "              2 STORE_FAST               3 (preprocessed_data)\n",
      "\n",
      "177           4 BUILD_LIST               0\n",
      "              6 STORE_FAST               4 (randomized_list)\n",
      "\n",
      "178           8 SETUP_LOOP             190 (to 200)\n",
      "             10 LOAD_GLOBAL              0 (range)\n",
      "             12 LOAD_GLOBAL              1 (len)\n",
      "             14 LOAD_FAST                0 (self)\n",
      "             16 LOAD_ATTR                2 (feature_name)\n",
      "             18 CALL_FUNCTION            1\n",
      "             20 CALL_FUNCTION            1\n",
      "             22 GET_ITER\n",
      "        >>   24 FOR_ITER               172 (to 198)\n",
      "             26 STORE_FAST               5 (idx)\n",
      "\n",
      "179          28 LOAD_FAST                0 (self)\n",
      "             30 LOAD_ATTR                3 (transform_train)\n",
      "             32 LOAD_FAST                5 (idx)\n",
      "             34 BINARY_SUBSCR\n",
      "             36 STORE_FAST               6 (transform_list)\n",
      "\n",
      "180          38 LOAD_FAST                0 (self)\n",
      "             40 LOAD_ATTR                2 (feature_name)\n",
      "             42 LOAD_FAST                5 (idx)\n",
      "             44 BINARY_SUBSCR\n",
      "             46 STORE_FAST               7 (feature_name)\n",
      "\n",
      "181          48 LOAD_FAST                1 (decoded_data)\n",
      "             50 LOAD_FAST                7 (feature_name)\n",
      "             52 BINARY_SUBSCR\n",
      "             54 STORE_FAST               8 (preprocess_data)\n",
      "\n",
      "182          56 SETUP_LOOP             130 (to 188)\n",
      "             58 LOAD_FAST                6 (transform_list)\n",
      "             60 GET_ITER\n",
      "        >>   62 FOR_ITER               122 (to 186)\n",
      "             64 STORE_FAST               9 (preprocess_obj)\n",
      "\n",
      "183          66 LOAD_FAST                7 (feature_name)\n",
      "             68 LOAD_FAST                9 (preprocess_obj)\n",
      "             70 STORE_ATTR               2 (feature_name)\n",
      "\n",
      "184          72 LOAD_FAST                1 (decoded_data)\n",
      "             74 LOAD_FAST                9 (preprocess_obj)\n",
      "             76 STORE_ATTR               4 (decoded_data)\n",
      "\n",
      "185          78 LOAD_GLOBAL              5 (isinstance)\n",
      "             80 LOAD_FAST                9 (preprocess_obj)\n",
      "             82 LOAD_GLOBAL              6 (AbstractAugmentation)\n",
      "             84 CALL_FUNCTION            2\n",
      "             86 POP_JUMP_IF_FALSE      174\n",
      "\n",
      "186          88 LOAD_FAST                9 (preprocess_obj)\n",
      "             90 LOAD_ATTR                7 (mode)\n",
      "             92 LOAD_FAST                2 (mode)\n",
      "             94 COMPARE_OP               2 (==)\n",
      "             96 POP_JUMP_IF_TRUE       108\n",
      "             98 LOAD_FAST                9 (preprocess_obj)\n",
      "            100 LOAD_ATTR                7 (mode)\n",
      "            102 LOAD_CONST               1 ('both')\n",
      "            104 COMPARE_OP               2 (==)\n",
      "            106 POP_JUMP_IF_FALSE      184\n",
      "\n",
      "187     >>  108 LOAD_FAST                8 (preprocess_data)\n",
      "            110 LOAD_ATTR                8 (get_shape)\n",
      "            112 CALL_FUNCTION            0\n",
      "            114 LOAD_CONST               2 (0)\n",
      "            116 BINARY_SUBSCR\n",
      "            118 LOAD_FAST                9 (preprocess_obj)\n",
      "            120 STORE_ATTR               9 (height)\n",
      "\n",
      "188         122 LOAD_FAST                8 (preprocess_data)\n",
      "            124 LOAD_ATTR                8 (get_shape)\n",
      "            126 CALL_FUNCTION            0\n",
      "            128 LOAD_CONST               3 (1)\n",
      "            130 BINARY_SUBSCR\n",
      "            132 LOAD_FAST                9 (preprocess_obj)\n",
      "            134 STORE_ATTR              10 (width)\n",
      "\n",
      "189         136 LOAD_FAST                9 (preprocess_obj)\n",
      "            138 LOAD_FAST                4 (randomized_list)\n",
      "            140 COMPARE_OP               7 (not in)\n",
      "            142 POP_JUMP_IF_FALSE      162\n",
      "\n",
      "190         144 LOAD_FAST                9 (preprocess_obj)\n",
      "            146 LOAD_ATTR               11 (setup)\n",
      "            148 CALL_FUNCTION            0\n",
      "            150 POP_TOP\n",
      "\n",
      "191         152 LOAD_FAST                4 (randomized_list)\n",
      "            154 LOAD_ATTR               12 (append)\n",
      "            156 LOAD_FAST                9 (preprocess_obj)\n",
      "            158 CALL_FUNCTION            1\n",
      "            160 POP_TOP\n",
      "\n",
      "192     >>  162 LOAD_FAST                9 (preprocess_obj)\n",
      "            164 LOAD_ATTR               13 (transform)\n",
      "            166 LOAD_FAST                8 (preprocess_data)\n",
      "            168 CALL_FUNCTION            1\n",
      "            170 STORE_FAST               8 (preprocess_data)\n",
      "            172 JUMP_ABSOLUTE           62\n",
      "\n",
      "194     >>  174 LOAD_FAST                9 (preprocess_obj)\n",
      "            176 LOAD_ATTR               13 (transform)\n",
      "            178 LOAD_FAST                8 (preprocess_data)\n",
      "            180 CALL_FUNCTION            1\n",
      "            182 STORE_FAST               8 (preprocess_data)\n",
      "        >>  184 JUMP_ABSOLUTE           62\n",
      "        >>  186 POP_BLOCK\n",
      "\n",
      "195     >>  188 LOAD_FAST                8 (preprocess_data)\n",
      "            190 LOAD_FAST                3 (preprocessed_data)\n",
      "            192 LOAD_FAST                7 (feature_name)\n",
      "            194 STORE_SUBSCR\n",
      "            196 JUMP_ABSOLUTE           24\n",
      "        >>  198 POP_BLOCK\n",
      "\n",
      "196     >>  200 LOAD_FAST                3 (preprocessed_data)\n",
      "            202 RETURN_VALUE\n",
      "\n",
      "Disassembly of benchmark:\n",
      "303           0 LOAD_GLOBAL              0 (min)\n",
      "              2 LOAD_CONST               1 (8)\n",
      "              4 LOAD_GLOBAL              1 (multiprocessing)\n",
      "              6 LOAD_ATTR                2 (cpu_count)\n",
      "              8 CALL_FUNCTION            0\n",
      "             10 LOAD_FAST                0 (self)\n",
      "             12 LOAD_ATTR                3 (num_local_process)\n",
      "             14 BINARY_FLOOR_DIVIDE\n",
      "             16 CALL_FUNCTION            2\n",
      "             18 LOAD_FAST                0 (self)\n",
      "             20 STORE_ATTR               4 (num_subprocess)\n",
      "\n",
      "304          22 LOAD_FAST                0 (self)\n",
      "             24 LOAD_ATTR                5 (train_data)\n",
      "             26 POP_JUMP_IF_FALSE       88\n",
      "\n",
      "305          28 LOAD_GLOBAL              6 (TFRecorder)\n",
      "             30 BUILD_TUPLE              0\n",
      "             32 LOAD_FAST                0 (self)\n",
      "             34 LOAD_ATTR                5 (train_data)\n",
      "\n",
      "306          36 LOAD_FAST                0 (self)\n",
      "             38 LOAD_ATTR                7 (feature_name)\n",
      "\n",
      "307          40 LOAD_FAST                0 (self)\n",
      "             42 LOAD_ATTR                8 (transform_dataset)\n",
      "\n",
      "308          44 LOAD_FAST                0 (self)\n",
      "             46 LOAD_ATTR                9 (validation_data)\n",
      "             48 LOAD_CONST               2 (('train_data', 'feature_name', 'transform_dataset', 'validation_data'))\n",
      "             50 BUILD_CONST_KEY_MAP      4\n",
      "\n",
      "309          52 LOAD_FAST                0 (self)\n",
      "             54 LOAD_ATTR               10 (kwargs)\n",
      "             56 BUILD_MAP_UNPACK_WITH_CALL     2\n",
      "             58 CALL_FUNCTION_EX         1\n",
      "             60 STORE_FAST               5 (tfrecorder)\n",
      "\n",
      "310          62 LOAD_FAST                0 (self)\n",
      "             64 LOAD_ATTR               11 (edit_feature)\n",
      "             66 LOAD_FAST                5 (tfrecorder)\n",
      "             68 STORE_ATTR              11 (edit_feature)\n",
      "\n",
      "311          70 LOAD_FAST                5 (tfrecorder)\n",
      "             72 LOAD_ATTR               12 (create_tfrecord)\n",
      "             74 LOAD_FAST                1 (inputs)\n",
      "             76 CALL_FUNCTION            1\n",
      "             78 POP_TOP\n",
      "\n",
      "312          80 LOAD_FAST                5 (tfrecorder)\n",
      "             82 LOAD_ATTR               13 (save_dir)\n",
      "             84 STORE_FAST               1 (inputs)\n",
      "             86 JUMP_FORWARD            16 (to 104)\n",
      "\n",
      "314     >>   88 LOAD_FAST                1 (inputs)\n",
      "             90 LOAD_CONST               3 (None)\n",
      "             92 COMPARE_OP               9 (is not)\n",
      "             94 POP_JUMP_IF_TRUE       104\n",
      "             96 LOAD_GLOBAL             14 (AssertionError)\n",
      "             98 LOAD_CONST               4 ('Must specify the data path when using existing tfrecords')\n",
      "            100 CALL_FUNCTION            1\n",
      "            102 RAISE_VARARGS            1\n",
      "\n",
      "315     >>  104 LOAD_FAST                0 (self)\n",
      "            106 LOAD_ATTR               15 (_get_tfrecord_config)\n",
      "            108 LOAD_FAST                1 (inputs)\n",
      "            110 CALL_FUNCTION            1\n",
      "            112 POP_TOP\n",
      "\n",
      "316         114 LOAD_FAST                0 (self)\n",
      "            116 LOAD_ATTR               16 (_input_source)\n",
      "            118 LOAD_FAST                2 (mode)\n",
      "            120 LOAD_FAST                3 (num_steps)\n",
      "            122 CALL_FUNCTION            2\n",
      "            124 STORE_FAST               6 (it)\n",
      "\n",
      "317         126 LOAD_GLOBAL             17 (time)\n",
      "            128 LOAD_ATTR               17 (time)\n",
      "            130 CALL_FUNCTION            0\n",
      "            132 STORE_FAST               7 (start)\n",
      "\n",
      "318         134 SETUP_LOOP              86 (to 222)\n",
      "            136 LOAD_GLOBAL             18 (enumerate)\n",
      "            138 LOAD_FAST                6 (it)\n",
      "            140 CALL_FUNCTION            1\n",
      "            142 GET_ITER\n",
      "        >>  144 FOR_ITER                74 (to 220)\n",
      "            146 UNPACK_SEQUENCE          2\n",
      "            148 STORE_FAST               8 (i)\n",
      "            150 STORE_FAST               9 (_)\n",
      "\n",
      "319         152 LOAD_FAST                8 (i)\n",
      "            154 LOAD_FAST                4 (log_interval)\n",
      "            156 BINARY_MODULO\n",
      "            158 LOAD_CONST               5 (0)\n",
      "            160 COMPARE_OP               2 (==)\n",
      "            162 POP_JUMP_IF_FALSE      144\n",
      "            164 LOAD_FAST                8 (i)\n",
      "            166 LOAD_CONST               5 (0)\n",
      "            168 COMPARE_OP               4 (>)\n",
      "            170 POP_JUMP_IF_FALSE      144\n",
      "\n",
      "320         172 LOAD_GLOBAL             17 (time)\n",
      "            174 LOAD_ATTR               17 (time)\n",
      "            176 CALL_FUNCTION            0\n",
      "            178 LOAD_FAST                7 (start)\n",
      "            180 BINARY_SUBTRACT\n",
      "            182 STORE_FAST              10 (duration)\n",
      "\n",
      "321         184 LOAD_FAST                4 (log_interval)\n",
      "            186 LOAD_FAST                0 (self)\n",
      "            188 LOAD_ATTR               19 (batch_size)\n",
      "            190 BINARY_MULTIPLY\n",
      "            192 LOAD_FAST               10 (duration)\n",
      "            194 BINARY_TRUE_DIVIDE\n",
      "            196 STORE_FAST              11 (example_per_sec)\n",
      "\n",
      "322         198 LOAD_GLOBAL             20 (print)\n",
      "            200 LOAD_CONST               6 ('FastEstimator: Pipeline Preprocessing Example/sec %f')\n",
      "            202 LOAD_FAST               11 (example_per_sec)\n",
      "            204 BINARY_MODULO\n",
      "            206 CALL_FUNCTION            1\n",
      "            208 POP_TOP\n",
      "\n",
      "323         210 LOAD_GLOBAL             17 (time)\n",
      "            212 LOAD_ATTR               17 (time)\n",
      "            214 CALL_FUNCTION            0\n",
      "            216 STORE_FAST               7 (start)\n",
      "            218 JUMP_ABSOLUTE          144\n",
      "        >>  220 POP_BLOCK\n",
      "        >>  222 LOAD_CONST               3 (None)\n",
      "            224 RETURN_VALUE\n",
      "\n",
      "Disassembly of edit_feature:\n",
      "235           0 LOAD_FAST                1 (feature)\n",
      "              2 RETURN_VALUE\n",
      "\n",
      "Disassembly of final_transform:\n",
      "222           0 LOAD_FAST                1 (preprocessed_data)\n",
      "              2 RETURN_VALUE\n",
      "\n",
      "Disassembly of read_and_decode:\n",
      "248           0 BUILD_MAP                0\n",
      "              2 STORE_FAST               2 (decoded_data)\n",
      "\n",
      "249           4 LOAD_GLOBAL              0 (tf)\n",
      "              6 LOAD_ATTR                1 (io)\n",
      "              8 LOAD_ATTR                2 (parse_single_example)\n",
      "             10 LOAD_FAST                1 (dataset)\n",
      "             12 LOAD_FAST                0 (self)\n",
      "             14 LOAD_ATTR                3 (keys_to_features)\n",
      "             16 LOAD_CONST               1 (('features',))\n",
      "             18 CALL_FUNCTION_KW         2\n",
      "             20 STORE_FAST               3 (all_data)\n",
      "\n",
      "250          22 SETUP_LOOP             164 (to 188)\n",
      "             24 LOAD_FAST                0 (self)\n",
      "             26 LOAD_ATTR                4 (feature_name)\n",
      "             28 GET_ITER\n",
      "        >>   30 FOR_ITER               154 (to 186)\n",
      "             32 STORE_FAST               4 (feature)\n",
      "\n",
      "251          34 LOAD_FAST                3 (all_data)\n",
      "             36 LOAD_FAST                4 (feature)\n",
      "             38 BINARY_SUBSCR\n",
      "             40 STORE_FAST               5 (data)\n",
      "\n",
      "252          42 LOAD_CONST               2 ('str')\n",
      "             44 LOAD_GLOBAL              5 (str)\n",
      "             46 LOAD_FAST                5 (data)\n",
      "             48 LOAD_ATTR                6 (dtype)\n",
      "             50 CALL_FUNCTION            1\n",
      "             52 COMPARE_OP               6 (in)\n",
      "             54 POP_JUMP_IF_FALSE      112\n",
      "             56 LOAD_CONST               2 ('str')\n",
      "             58 LOAD_FAST                0 (self)\n",
      "             60 LOAD_ATTR                7 (decode_type)\n",
      "             62 LOAD_FAST                4 (feature)\n",
      "             64 BINARY_SUBSCR\n",
      "             66 COMPARE_OP               7 (not in)\n",
      "             68 POP_JUMP_IF_FALSE      112\n",
      "\n",
      "253          70 LOAD_GLOBAL              0 (tf)\n",
      "             72 LOAD_ATTR                1 (io)\n",
      "             74 LOAD_ATTR                8 (decode_raw)\n",
      "             76 LOAD_FAST                5 (data)\n",
      "             78 LOAD_GLOBAL              9 (convert_tf_dtype)\n",
      "             80 LOAD_FAST                0 (self)\n",
      "             82 LOAD_ATTR                7 (decode_type)\n",
      "             84 LOAD_FAST                4 (feature)\n",
      "             86 BINARY_SUBSCR\n",
      "             88 CALL_FUNCTION            1\n",
      "             90 CALL_FUNCTION            2\n",
      "             92 STORE_FAST               5 (data)\n",
      "\n",
      "254          94 LOAD_GLOBAL              0 (tf)\n",
      "             96 LOAD_ATTR               10 (reshape)\n",
      "             98 LOAD_FAST                5 (data)\n",
      "            100 LOAD_FAST                0 (self)\n",
      "            102 LOAD_ATTR               11 (feature_shape)\n",
      "            104 LOAD_FAST                4 (feature)\n",
      "            106 BINARY_SUBSCR\n",
      "            108 CALL_FUNCTION            2\n",
      "            110 STORE_FAST               5 (data)\n",
      "\n",
      "255     >>  112 LOAD_CONST               3 ('int')\n",
      "            114 LOAD_GLOBAL              5 (str)\n",
      "            116 LOAD_FAST                5 (data)\n",
      "            118 LOAD_ATTR                6 (dtype)\n",
      "            120 CALL_FUNCTION            1\n",
      "            122 COMPARE_OP               6 (in)\n",
      "            124 POP_JUMP_IF_FALSE      142\n",
      "\n",
      "256         126 LOAD_GLOBAL              0 (tf)\n",
      "            128 LOAD_ATTR               12 (cast)\n",
      "            130 LOAD_FAST                5 (data)\n",
      "            132 LOAD_GLOBAL              0 (tf)\n",
      "            134 LOAD_ATTR               13 (int32)\n",
      "            136 CALL_FUNCTION            2\n",
      "            138 STORE_FAST               5 (data)\n",
      "            140 JUMP_FORWARD            34 (to 176)\n",
      "\n",
      "257     >>  142 LOAD_FAST                0 (self)\n",
      "            144 LOAD_ATTR                7 (decode_type)\n",
      "            146 LOAD_FAST                4 (feature)\n",
      "            148 BINARY_SUBSCR\n",
      "            150 LOAD_CONST               2 ('str')\n",
      "            152 COMPARE_OP               2 (==)\n",
      "            154 POP_JUMP_IF_FALSE      162\n",
      "\n",
      "258         156 LOAD_FAST                5 (data)\n",
      "            158 STORE_FAST               5 (data)\n",
      "            160 JUMP_FORWARD            14 (to 176)\n",
      "\n",
      "260     >>  162 LOAD_GLOBAL              0 (tf)\n",
      "            164 LOAD_ATTR               12 (cast)\n",
      "            166 LOAD_FAST                5 (data)\n",
      "            168 LOAD_GLOBAL              0 (tf)\n",
      "            170 LOAD_ATTR               14 (float32)\n",
      "            172 CALL_FUNCTION            2\n",
      "            174 STORE_FAST               5 (data)\n",
      "\n",
      "261     >>  176 LOAD_FAST                5 (data)\n",
      "            178 LOAD_FAST                2 (decoded_data)\n",
      "            180 LOAD_FAST                4 (feature)\n",
      "            182 STORE_SUBSCR\n",
      "            184 JUMP_ABSOLUTE           30\n",
      "        >>  186 POP_BLOCK\n",
      "\n",
      "262     >>  188 LOAD_FAST                2 (decoded_data)\n",
      "            190 RETURN_VALUE\n",
      "\n",
      "Disassembly of show_batches:\n",
      "276           0 BUILD_LIST               0\n",
      "              2 STORE_FAST               4 (data)\n",
      "\n",
      "277           4 LOAD_GLOBAL              0 (min)\n",
      "              6 LOAD_CONST               1 (8)\n",
      "              8 LOAD_GLOBAL              1 (multiprocessing)\n",
      "             10 LOAD_ATTR                2 (cpu_count)\n",
      "             12 CALL_FUNCTION            0\n",
      "             14 LOAD_FAST                0 (self)\n",
      "             16 LOAD_ATTR                3 (num_local_process)\n",
      "             18 BINARY_FLOOR_DIVIDE\n",
      "             20 CALL_FUNCTION            2\n",
      "             22 LOAD_FAST                0 (self)\n",
      "             24 STORE_ATTR               4 (num_subprocess)\n",
      "\n",
      "278          26 LOAD_FAST                0 (self)\n",
      "             28 LOAD_ATTR                5 (train_data)\n",
      "             30 POP_JUMP_IF_FALSE       92\n",
      "\n",
      "279          32 LOAD_GLOBAL              6 (TFRecorder)\n",
      "             34 BUILD_TUPLE              0\n",
      "             36 LOAD_FAST                0 (self)\n",
      "             38 LOAD_ATTR                5 (train_data)\n",
      "\n",
      "280          40 LOAD_FAST                0 (self)\n",
      "             42 LOAD_ATTR                7 (feature_name)\n",
      "\n",
      "281          44 LOAD_FAST                0 (self)\n",
      "             46 LOAD_ATTR                8 (transform_dataset)\n",
      "\n",
      "282          48 LOAD_FAST                0 (self)\n",
      "             50 LOAD_ATTR                9 (validation_data)\n",
      "             52 LOAD_CONST               2 (('train_data', 'feature_name', 'transform_dataset', 'validation_data'))\n",
      "             54 BUILD_CONST_KEY_MAP      4\n",
      "\n",
      "283          56 LOAD_FAST                0 (self)\n",
      "             58 LOAD_ATTR               10 (kwargs)\n",
      "             60 BUILD_MAP_UNPACK_WITH_CALL     2\n",
      "             62 CALL_FUNCTION_EX         1\n",
      "             64 STORE_FAST               5 (tfrecorder)\n",
      "\n",
      "284          66 LOAD_FAST                0 (self)\n",
      "             68 LOAD_ATTR               11 (edit_feature)\n",
      "             70 LOAD_FAST                5 (tfrecorder)\n",
      "             72 STORE_ATTR              11 (edit_feature)\n",
      "\n",
      "285          74 LOAD_FAST                5 (tfrecorder)\n",
      "             76 LOAD_ATTR               12 (create_tfrecord)\n",
      "             78 LOAD_FAST                1 (inputs)\n",
      "             80 CALL_FUNCTION            1\n",
      "             82 POP_TOP\n",
      "\n",
      "286          84 LOAD_FAST                5 (tfrecorder)\n",
      "             86 LOAD_ATTR               13 (save_dir)\n",
      "             88 STORE_FAST               1 (inputs)\n",
      "             90 JUMP_FORWARD            16 (to 108)\n",
      "\n",
      "288     >>   92 LOAD_FAST                1 (inputs)\n",
      "             94 LOAD_CONST               3 (None)\n",
      "             96 COMPARE_OP               9 (is not)\n",
      "             98 POP_JUMP_IF_TRUE       108\n",
      "            100 LOAD_GLOBAL             14 (AssertionError)\n",
      "            102 LOAD_CONST               4 ('Must specify the data path when using existing tfrecords')\n",
      "            104 CALL_FUNCTION            1\n",
      "            106 RAISE_VARARGS            1\n",
      "\n",
      "289     >>  108 LOAD_FAST                0 (self)\n",
      "            110 LOAD_ATTR               15 (_get_tfrecord_config)\n",
      "            112 LOAD_FAST                1 (inputs)\n",
      "            114 CALL_FUNCTION            1\n",
      "            116 POP_TOP\n",
      "\n",
      "290         118 LOAD_FAST                0 (self)\n",
      "            120 LOAD_ATTR               16 (_input_source)\n",
      "            122 LOAD_FAST                3 (mode)\n",
      "            124 LOAD_FAST                2 (num_batches)\n",
      "            126 CALL_FUNCTION            2\n",
      "            128 STORE_FAST               6 (dataset)\n",
      "\n",
      "291         130 SETUP_LOOP              30 (to 162)\n",
      "            132 LOAD_GLOBAL             17 (enumerate)\n",
      "            134 LOAD_FAST                6 (dataset)\n",
      "            136 CALL_FUNCTION            1\n",
      "            138 GET_ITER\n",
      "        >>  140 FOR_ITER                18 (to 160)\n",
      "            142 UNPACK_SEQUENCE          2\n",
      "            144 STORE_FAST               7 (i)\n",
      "            146 STORE_FAST               8 (example)\n",
      "\n",
      "292         148 LOAD_FAST                4 (data)\n",
      "            150 LOAD_ATTR               18 (append)\n",
      "            152 LOAD_FAST                8 (example)\n",
      "            154 CALL_FUNCTION            1\n",
      "            156 POP_TOP\n",
      "            158 JUMP_ABSOLUTE          140\n",
      "        >>  160 POP_BLOCK\n",
      "\n",
      "293     >>  162 LOAD_FAST                4 (data)\n",
      "            164 RETURN_VALUE\n",
      "\n"
     ]
    }
   ],
   "source": [
    "dis.dis(Pipeline)"
   ]
  },
  {
   "cell_type": "code",
   "execution_count": 26,
   "metadata": {},
   "outputs": [
    {
     "name": "stdout",
     "output_type": "stream",
     "text": [
      "  1           0 LOAD_CONST               2 (18446744073709551616)\n",
      "              2 RETURN_VALUE\n"
     ]
    }
   ],
   "source": [
    "dis.dis('2**64')"
   ]
  },
  {
   "cell_type": "code",
   "execution_count": 21,
   "metadata": {},
   "outputs": [
    {
     "name": "stdout",
     "output_type": "stream",
     "text": [
      "  1           0 LOAD_NAME                0 (pow)\n",
      "              2 LOAD_CONST               0 (2)\n",
      "              4 LOAD_CONST               1 (63)\n",
      "              6 CALL_FUNCTION            2\n",
      "              8 RETURN_VALUE\n"
     ]
    }
   ],
   "source": [
    "dis.dis('pow(2, 63)')"
   ]
  },
  {
   "cell_type": "code",
   "execution_count": 9,
   "metadata": {},
   "outputs": [],
   "source": [
    "pipeline = Pipeline(\n",
    "        batch_size=64,\n",
    "        feature_name=[\"image\", \"annotation\"],\n",
    "        train_data=csv_path,\n",
    "        validation_data=0.2,\n",
    "        transform_dataset=[\n",
    "            [ImageReader(parent_path=path),\n",
    "             Resize((128, 128), keep_ratio=True)],\n",
    "            [MatReader(parent_path=path), SelectKey(), Resize((128, 128), keep_ratio=True)]\n",
    "        ],\n",
    "        transform_train=[[Reshape((128, 128, 3)), Minmax()], [Reshape((128, 128, 1))]])"
   ]
  },
  {
   "cell_type": "code",
   "execution_count": 10,
   "metadata": {},
   "outputs": [
    {
     "name": "stdout",
     "output_type": "stream",
     "text": [
      "FastEstimator: Saving tfrecord to /tmp/FE_CUB200/tfrecords/\n",
      "FastEstimator: --Converting Eval TFRecords 0.000000%--\n",
      "FastEstimator: --Converting Eval TFRecords 4.966887%--\n",
      "FastEstimator: --Converting Eval TFRecords 9.933775%--\n",
      "FastEstimator: --Converting Eval TFRecords 14.900662%--\n",
      "FastEstimator: --Converting Eval TFRecords 19.867550%--\n",
      "FastEstimator: --Converting Eval TFRecords 24.834437%--\n",
      "FastEstimator: --Converting Eval TFRecords 29.801325%--\n",
      "FastEstimator: --Converting Eval TFRecords 34.768212%--\n",
      "FastEstimator: --Converting Eval TFRecords 39.735099%--\n",
      "FastEstimator: --Converting Eval TFRecords 44.701987%--\n",
      "FastEstimator: --Converting Eval TFRecords 49.668874%--\n",
      "FastEstimator: --Converting Eval TFRecords 54.635762%--\n",
      "FastEstimator: --Converting Eval TFRecords 59.602649%--\n",
      "FastEstimator: --Converting Eval TFRecords 64.569536%--\n",
      "FastEstimator: --Converting Eval TFRecords 69.536424%--\n",
      "FastEstimator: --Converting Eval TFRecords 74.503311%--\n",
      "FastEstimator: --Converting Eval TFRecords 79.470199%--\n",
      "FastEstimator: --Converting Eval TFRecords 84.437086%--\n",
      "FastEstimator: --Converting Eval TFRecords 89.403974%--\n",
      "FastEstimator: --Converting Eval TFRecords 94.370861%--\n",
      "FastEstimator: --Converting Eval TFRecords 99.337748%--\n",
      "FastEstimator: --Converting Train TFRecords 0.000000%--\n",
      "FastEstimator: --Converting Train TFRecords 4.971002%--\n",
      "FastEstimator: --Converting Train TFRecords 9.942005%--\n",
      "FastEstimator: --Converting Train TFRecords 14.913007%--\n",
      "FastEstimator: --Converting Train TFRecords 19.884010%--\n",
      "FastEstimator: --Converting Train TFRecords 24.855012%--\n",
      "FastEstimator: --Converting Train TFRecords 29.826015%--\n",
      "FastEstimator: --Converting Train TFRecords 34.797017%--\n",
      "FastEstimator: --Converting Train TFRecords 39.768020%--\n",
      "FastEstimator: --Converting Train TFRecords 44.739022%--\n",
      "FastEstimator: --Converting Train TFRecords 49.710025%--\n",
      "FastEstimator: --Converting Train TFRecords 54.681027%--\n",
      "FastEstimator: --Converting Train TFRecords 59.652030%--\n",
      "FastEstimator: --Converting Train TFRecords 64.623032%--\n",
      "FastEstimator: --Converting Train TFRecords 69.594035%--\n",
      "FastEstimator: --Converting Train TFRecords 74.565037%--\n",
      "FastEstimator: --Converting Train TFRecords 79.536040%--\n",
      "FastEstimator: --Converting Train TFRecords 84.507042%--\n",
      "FastEstimator: --Converting Train TFRecords 89.478045%--\n",
      "FastEstimator: --Converting Train TFRecords 94.449047%--\n",
      "FastEstimator: --Converting Train TFRecords 99.420050%--\n",
      "FastEstimator: Found 4827 examples for training and 1206 for validation in /tmp/FE_CUB200/tfrecords/\n"
     ]
    },
    {
     "ename": "TypeError",
     "evalue": "don't know how to disassemble list objects",
     "output_type": "error",
     "traceback": [
      "\u001b[0;31m---------------------------------------------------------------------------\u001b[0m",
      "\u001b[0;31mTypeError\u001b[0m                                 Traceback (most recent call last)",
      "\u001b[0;32m<ipython-input-10-e6403b155108>\u001b[0m in \u001b[0;36m<module>\u001b[0;34m\u001b[0m\n\u001b[0;32m----> 1\u001b[0;31m \u001b[0mdis\u001b[0m\u001b[0;34m.\u001b[0m\u001b[0mdis\u001b[0m\u001b[0;34m(\u001b[0m\u001b[0mpipeline\u001b[0m\u001b[0;34m.\u001b[0m\u001b[0mshow_batches\u001b[0m\u001b[0;34m(\u001b[0m\u001b[0minputs\u001b[0m\u001b[0;34m=\u001b[0m\u001b[0;34m'/tmp/FE_CUB200/tfrecords/'\u001b[0m\u001b[0;34m,\u001b[0m \u001b[0mnum_batches\u001b[0m\u001b[0;34m=\u001b[0m\u001b[0;36m10\u001b[0m\u001b[0;34m)\u001b[0m\u001b[0;34m)\u001b[0m\u001b[0;34m\u001b[0m\u001b[0;34m\u001b[0m\u001b[0m\n\u001b[0m",
      "\u001b[0;32m/data/hsiming/virtualenv/tf2.0.0b_py36_hsiming/lib/python3.6/dis.py\u001b[0m in \u001b[0;36mdis\u001b[0;34m(x, file)\u001b[0m\n\u001b[1;32m     65\u001b[0m     \u001b[0;32melse\u001b[0m\u001b[0;34m:\u001b[0m\u001b[0;34m\u001b[0m\u001b[0;34m\u001b[0m\u001b[0m\n\u001b[1;32m     66\u001b[0m         raise TypeError(\"don't know how to disassemble %s objects\" %\n\u001b[0;32m---> 67\u001b[0;31m                         type(x).__name__)\n\u001b[0m\u001b[1;32m     68\u001b[0m \u001b[0;34m\u001b[0m\u001b[0m\n\u001b[1;32m     69\u001b[0m \u001b[0;32mdef\u001b[0m \u001b[0mdistb\u001b[0m\u001b[0;34m(\u001b[0m\u001b[0mtb\u001b[0m\u001b[0;34m=\u001b[0m\u001b[0;32mNone\u001b[0m\u001b[0;34m,\u001b[0m \u001b[0;34m*\u001b[0m\u001b[0;34m,\u001b[0m \u001b[0mfile\u001b[0m\u001b[0;34m=\u001b[0m\u001b[0;32mNone\u001b[0m\u001b[0;34m)\u001b[0m\u001b[0;34m:\u001b[0m\u001b[0;34m\u001b[0m\u001b[0;34m\u001b[0m\u001b[0m\n",
      "\u001b[0;31mTypeError\u001b[0m: don't know how to disassemble list objects"
     ]
    }
   ],
   "source": [
    "dis.dis(pipeline.show_batches(inputs='/tmp/FE_CUB200/tfrecords/', num_batches=10))"
   ]
  },
  {
   "cell_type": "code",
   "execution_count": 13,
   "metadata": {
    "scrolled": false
   },
   "outputs": [
    {
     "name": "stdout",
     "output_type": "stream",
     "text": [
      "FastEstimator: Saving tfrecord to /tmp/FE_CUB200/tfrecords/\n",
      "FastEstimator: --Converting Eval TFRecords 0.000000%--\n",
      "FastEstimator: --Converting Eval TFRecords 4.966887%--\n",
      "FastEstimator: --Converting Eval TFRecords 9.933775%--\n",
      "FastEstimator: --Converting Eval TFRecords 14.900662%--\n",
      "FastEstimator: --Converting Eval TFRecords 19.867550%--\n",
      "FastEstimator: --Converting Eval TFRecords 24.834437%--\n",
      "FastEstimator: --Converting Eval TFRecords 29.801325%--\n",
      "FastEstimator: --Converting Eval TFRecords 34.768212%--\n",
      "FastEstimator: --Converting Eval TFRecords 39.735099%--\n",
      "FastEstimator: --Converting Eval TFRecords 44.701987%--\n",
      "FastEstimator: --Converting Eval TFRecords 49.668874%--\n",
      "FastEstimator: --Converting Eval TFRecords 54.635762%--\n",
      "FastEstimator: --Converting Eval TFRecords 59.602649%--\n",
      "FastEstimator: --Converting Eval TFRecords 64.569536%--\n",
      "FastEstimator: --Converting Eval TFRecords 69.536424%--\n",
      "FastEstimator: --Converting Eval TFRecords 74.503311%--\n",
      "FastEstimator: --Converting Eval TFRecords 79.470199%--\n",
      "FastEstimator: --Converting Eval TFRecords 84.437086%--\n",
      "FastEstimator: --Converting Eval TFRecords 89.403974%--\n",
      "FastEstimator: --Converting Eval TFRecords 94.370861%--\n",
      "FastEstimator: --Converting Eval TFRecords 99.337748%--\n",
      "FastEstimator: --Converting Train TFRecords 0.000000%--\n",
      "FastEstimator: --Converting Train TFRecords 4.971002%--\n",
      "FastEstimator: --Converting Train TFRecords 9.942005%--\n",
      "FastEstimator: --Converting Train TFRecords 14.913007%--\n",
      "FastEstimator: --Converting Train TFRecords 19.884010%--\n",
      "FastEstimator: --Converting Train TFRecords 24.855012%--\n",
      "FastEstimator: --Converting Train TFRecords 29.826015%--\n",
      "FastEstimator: --Converting Train TFRecords 34.797017%--\n",
      "FastEstimator: --Converting Train TFRecords 39.768020%--\n",
      "FastEstimator: --Converting Train TFRecords 44.739022%--\n",
      "FastEstimator: --Converting Train TFRecords 49.710025%--\n",
      "FastEstimator: --Converting Train TFRecords 54.681027%--\n",
      "FastEstimator: --Converting Train TFRecords 59.652030%--\n",
      "FastEstimator: --Converting Train TFRecords 64.623032%--\n",
      "FastEstimator: --Converting Train TFRecords 69.594035%--\n",
      "FastEstimator: --Converting Train TFRecords 74.565037%--\n",
      "FastEstimator: --Converting Train TFRecords 79.536040%--\n",
      "FastEstimator: --Converting Train TFRecords 84.507042%--\n",
      "FastEstimator: --Converting Train TFRecords 89.478045%--\n",
      "FastEstimator: --Converting Train TFRecords 94.449047%--\n",
      "FastEstimator: --Converting Train TFRecords 99.420050%--\n",
      "FastEstimator: Found 4827 examples for training and 1206 for validation in /tmp/FE_CUB200/tfrecords/\n"
     ]
    }
   ],
   "source": [
    "batch_data = pipeline.show_batches(inputs='/tmp/FE_CUB200/tfrecords/', num_batches=10)"
   ]
  },
  {
   "cell_type": "code",
   "execution_count": 18,
   "metadata": {},
   "outputs": [
    {
     "data": {
      "image/png": "iVBORw0KGgoAAAANSUhEUgAAAsYAAAFSCAYAAADxdxl9AAAABHNCSVQICAgIfAhkiAAAAAlwSFlzAAALEgAACxIB0t1+/AAAADh0RVh0U29mdHdhcmUAbWF0cGxvdGxpYiB2ZXJzaW9uMy4xLjAsIGh0dHA6Ly9tYXRwbG90bGliLm9yZy+17YcXAAAgAElEQVR4nOy9adBt2Vke9qw9nXO+4U7drW7NrRHNwswCD9iUBwIxccrGmJgQm7JIGIohlQCpVIWqOLFNOQFcKaeiQGycwiZUwIbEYMAChVkgIQEaQGq11FIP6vFO33DO2cPKj/W8az37frcbqW9f6evb7/Ojv3P32mfttdZe+/Q5z/s+zxtijHA4HA6Hw+FwOJ7rqD7bA3A4HA6Hw+FwOE4D/Iuxw+FwOBwOh8MB/2LscDgcDofD4XAA8C/GDofD4XA4HA4HAP9i7HA4HA6Hw+FwAPAvxg6Hw+FwOBwOB4Cb+MU4hPBXQgh/HEK4J4TwvTfrOg6Hw+G4cfhntsPhcADhZvgYhxBqAB8C8BcB3A/gdwH8rRjjB57xizkcDofjhuCf2Q6Hw5HQ3KR+vwjAPTHGewEghPATAL4GwHU/ZEMIXmXE4XA8m/FYjPGOz/YgbgD+me1wOJ5LeNLP7JuVSvFCAJ+Qf9/PYw6Hw3Er4r7P9gBuEP6Z7XA4nkt40s/sm8UY/4kIIbwVwFs/W9d3OBwOx6cO/8x2OBzPBdysL8YPAHix/PtFPJYRY3wbgLcBHpZzOByOzzL8M9vhcDhw81IpfhfAq0IILwshdAC+DsDP3qRrORwOh+PG4J/ZDofDgZvEGMcYhxDCtwH4BQA1gP8jxvj+m3Eth8PhcNwY/DPb4XA4Em6KXdunPQgPyzkcjmc33h1j/ILP9iA+U/DPbIfD8SzHk35me+U7h8PhcDgcDocD/sXY4XA4HA6Hw+EA4F+MHQ6Hw+FwOBwOAP7F2OFwOBwOh8PhAOBfjB0Oh8PhcDgcDgD+xdjhcDgcDofD4QDgX4wdDofD4XA4HA4A/sXY4XA4HA6Hw+EA4F+MHQ6Hw+FwOBwOAP7F2OFwOBwOh8PhAOBfjB0Oh8PhcDgcDgD+xdjhcDgcDofD4QAANJ/tATwZQgjXORqvPeszMZSbjhivnVeBrsOnet6n0v9Tnf9M4KnG+uniemN9Jvv/TOFmz8P6/0ytzVPN51Pdtw6Hw+FwnCY4Y+xwOBwOh8PhcOAUM8Zf9HlvAgD85b/y5/OxiAkAMI7pb5yUseLrtgYA1KFMrU6no+f7U3t63fH8tq5LV2S4xjieOIYx/Z2kzRixzXYLADjcbnLb8Sa9Ptqu87GDPvLYkM4Zhty2HdNvlRHj/LoARqTzKpkHamPoUlts+9zU1On1VAljx2WpqtR/05WmimvQtGkt6y6caENVfkvFIR0bOfy4LX1N23TNOLb5WL9Nr8ct57aVvrgWw4bzKMuFMfJ+V2U8deRr/pndj3HkMfYp6xt5XpQ1rILNO42vk0WZ6nSBKspe496pYhp/qEvbRKY08PwoUY5+SO+b+jLWiuOZpmn2PgCY7L1y6SmkY7Zbg5KxwdacB6cyx1CnsdZV2ec2J7tOLb+T61DN3gcAaNLmae28Ru/HNWsRT/7mjtBnhs+y3dtB9jnv38jx96PcP95LPdZPaZ/bfa6bMsem7jicMp6Kc6r4MFTyKVjxcyM0aS9U8r4H7/kYAODRTzwoc3I23OFwOG4lOGPscDgcDofD4XDAvxg7HA6Hw+FwOBwATnEqxWDpDIOkDfD1MVMKag1v8zt+4Ps0y2KqLAWj/A6YmHqAiaHQSsLO1wvPM/Q+TRb6lr4Y9+8txUPGPFr/sYR3a/YRppMpGxb9nqaBfUuoNqaQcS/HAscdmBoRx5JKMTW8Tl1yHEaG2XNEfZLQesNQPLeFrDyqJv2rkd9Sk823Tws2DtLG1zIcTD3/MTDNQEPko40/jUHTXiydpNrKOpnQLJxMbbEQ/Nhv7EB5n81H9oelaESu5SAh/5r3WW5fTkEYeX4taxgsReCasaeL29VlHnYa//bQNIvrpAyF+flDlJSQnFcynLi0pRONMo+cqWGbodKmOD8JQBjnz0qU52nL9BJ7Jmt5X35Mx5P3dBo437IV0PMfkecPQ9lEkecPY0lX6pm6FDiBaZT0FWbyNEEmzlSL0fb7IPfPlsL2tgoMoz0fnj7hcDgctyqcMXY4HA6Hw+FwOHCKGePMVwlbFslsLchUDVEYRzKHFam9RsVVlCpVQhNOpLGCsbfKcDX2e0HZWrDf1FcfCovVklXMIqa6LGtrDOIoQjaK4Uzw14lAzQR2A8VL41SuU2c2WVjFfHDLeZV5RzKHqMs6BerKAqnDSdRbgYyjLXklrDjIAA9KtRr9ONn5pcmYaCUJTaC15Rj1fFsf611FaCF3Isyv0aGmM1P22YRsZOTVLixkhrlcuwlp/Y0dDNdhO/VBKd2dFNiBojU7X+/VyL0Z5eK2F4yqLDtBBHkzW7Qo/y0REgCYyLrbLap1+1oXej7HX4f52qdrMgIjR7PG0HSP8gYT5OVDUYV8FsXR5y/OxjUIZWz7YuB9n2biVApKZV0lxMM+Zxsr/RFxrQn+GtvfM6ac16Qib6FM81zvyfMdDofDcSvBGWOHw+FwOBwOhwP+xdjhcDgcDofD4QBwilMpTMSkYVET14zm3StKosBQbDDhkXiZ2qte0gxqhkwDl2DU1AuGZJuqBLYnpjRYuF3TDHI6AsOuteQItEyr2Epcu6E3qnnF1hKcNQFVhZ7zKakUJrQKfQktZ49ehuQruXakj7HG52vzhm0Z3u4lVcVC6zYWTWOxcLvMw/yUTT8VprKdJno1VxLxNvFkw35H6d+6tdk2sczb0ksmTXEwn2BLFxHPXkspyOkGGlo3FV1QYWW6VhUpOpTzG675Vvaaedu25t0bdC/wr9lea/oA0z2CpLZUWdV3Mt0AuV8dv/Wfc0hyU83wv6WLqPjO9pUuhaVGVJP5RGtOAe+fzM3mHbIPsPSVj50Uv5ZMB02luGYecm8HpktsmSql/scYtieuHSfN4QEmSeOouD59LGK9xh6ILODUdAk+A5YCpUbR8+wdh8PhcNyCcMbY4XA4HA6Hw+HAKWaMjS2rhP0pVkpmlyWnR2NrKXCSrkyYV0uFsnFkRSwysioyipkBlv7J/IYsEhIaluNpKMib5DqNiQGFlKorMocxU3bSlzHFxkzLuIztFRbLKoZVZEC3VbFma0xgCLFws8qAW2PEVErEcXE+fV2YOmMhaxHfjdGq7rFKmLDoA8ddy9Sy4Ir9q1AwDyMLqFTQZrZac2YQKCIstX4zVGb7NXPcYvVAmXfF+2W2flWUSIENY/YT0kSKc/GazsNEo7O3ce0qqcp4rShOGV1b6kEZURMiZptBjTbYGIwxVgaYc5MRjVnAyAjJyaFewxjbfrLowYy3TcOy82ciPx6alemzSn8cqzL+mW5npGDQe5s95vKRhutpFn/VjNJlv7KwZtsYyIB38vyZc13P/jth5IMKTx0Oh8NxS8IZY4fD4XA4HA6HA6eYMc45iELSGNtVtWTeei34cI1lGmppm78//cNYKCsMIqyfMXtKuJGuDidJSyAXCyEbK2MemE+qrG3Naxqhp3m4Da/ds6hBFBsrY0ybobxhY+2jFfModFkuHKKsO1m7sSUj1gv7nHN5jUEt4zImbRJ2zQpbtFyoKFUwjK3WYgvGrF+PHZ2yXRvHV5ryCuh4AudrObZ6W4wVjsbMqoUdThZuCMb+c51y8RcAFfPMq0pyjPnXmOJJGGDLjTfaUtlecwFsZG/a8ufUZ5l5yLnbOjnLjc9vkHnM6e1wXSa7nN8Y62qsuzCitt8rYYVt34barP5KX1W2d7P5aIWdk1GAeE3+9CgDG2k9OPamG7hO8R2JCdm+yBZuGiGw3PjZ5kn9jlZopu3KPNitTbuq5CPSk4sdDofjloczxg6Hw+FwOBwOB/yLscPhcDgcDofDAeAUp1JkqEiqMksohkAbsX9iuHXMbxPRkFXeElVOYIjUDk0ajLe0DFH3VV0967eSqnuTpVl0rHomdmq9CbREfGcXbUzspWHn7VwsNIngzFIjxklC/bSvGqyvmVgv/e3k4llEx74mqdJn62QVBWeCxOwKpyFpzrvhtVUcZ6FrSVGp+Ho0OzUVmpkIy4RgYZbHAgDY9lpFjn3kTrSaHEP9XCdNKTCrPFS6JhaLt6py10lHEdQLCjdzmF3mOFlaiQnayjwsXWJW+W4yIdhJwaftSV0nrXSX/q35DHZt3g+xITNbu2qW/mB5A0w3kJyN2lKS5D5YqkVjg6yvl0LCNKSoa2hzO+nhFuzakkJitnaWUmHizjQIS1+RlJMsAuV9n9nb2T2V8/mxZ2Jcvd+W2rLiOdHzJxwOh+M5BWeMHQ6Hw+FwOBwOnGLG2Fg+Zb1MqGOCqCis1ED2y4i3mV2b2ZaJkKbhCUZy6vnZykttnK4RNClbXfe0cjN2UdhIsytrZB51LuJhDFy5esv39iOZYGHZeiu6MJZiBYMRoFYsRJZrMns7+flTU3Q3tcZk67is0ENqG8Qmq8lrrcUsOLmRjN4gFyezrOzoyMW2AgyViuKsLysiIaLDTHPO7N1y+Q72qSyhnW/WfWo7x2urqIrXqqrEBI9yP+x+awTCCmlYpKBWdtTYal4zyCNWk+WcFRCp5gyzbkQTgSqTG1iExBjm+fORYEVDlLW1/TuIAM7GWGUGVeZobLCQvE3DKIsVghH6ecI10ZzZGpLRvY4lYs35VLoPjcm1giuyhwZjvqUv03TaoTDqHDl/ud8V51Y1ad+GRoWVjGrY2qgo15hpFDif7HA4HLcWnDF2OBwOh8PhcDjgX4wdDofD4XA4HA4ApziVwlBVJ8U/OVIuaQbtxHA+q8+JPW8OtbYiHMuCIAZDg1zHIsR1fVKgVeWwvpqlrtlpOn+YhbBT6HemvTM/2zD/dzqRqQG0PR41pSCmFAr1iK2Z7hGuM+aqY6qG3mXmkCw5oii+x9EqgVnVuk7mT1/lSULxK0sbiHZfVHxn/rGSBkChWTVZSkU5vYJ53TKUrSIzpiBUEvI2G2NkgZ16NV+vMlseRJqbrIlVojPPZa1w1pg4rCtvMM9s20/9dar0WXVGFbtZaoDqF626m4XwexXy2XXkBg7DyXB+ufR83jEW7+ye6ztLKbB0AUtBaIrILXTpdV3LMTvP0iXkHrUmWOWxSX5zV0z7GEdJTQqW2sFKj5IS0tg42NdWqs/Zs6KSSOs3mA+1XNu8nVWAWTdzb+pZJcJoYx1PjMt0rZ4+4XA4HLcunDF2OBwOh8PhcDhwihnjLHITViqauM2EZjNWkeydiXmEUzI2bmbjhDm7pmIeY1Fngis7rzJmrPRfT0m0NZm9lIwrj3HG8pIJJG1ZV2K/hg2vYxX8CrbZpk4Y6caEhfFEW8fXjQgFS/k1ssmql+McG1JjlbC9AwWPrVS3y8xctEqBcj9IVg5Cj8aRrLOxinr7YKxfPiBtzYn+TVA3mXBMOjNW2yy9amVhTXiltF8WVHJfCR1pLGojlmFWdc7c/NTSzARvYz0XGqa28UT/JtTMdngyMKsGWDWlMltrEQTem5l7m7H/VrlP19dYdHkGbC/XLefYqEDtZPW8Ikq1vgQmprO2mQDO9ocI2Rg9mBjhqKWa41gv03jIFG9VdEm1aZixz9cIMDUSYaywVrfjsdHum5zf1tcKe5Xyh8PhcDhucThj7HA4HA6Hw+Fw4DQzxsb+aDEEY2+YVxtn1mFm12YMj1Chlhs4Y5KMOT3JGC/q6/mcWc4o2V4pssHUYtQc81iXNitgUEnSc85hZv+NXKbNRRTs36VtaM3KrLCXUzPPma1aYavZsTp6RbYv7KJCX1qqZXapk2IhXTQmrTBvgTZtlbnUCZvcG/MpRT8Gs/nK6d0yVstRNeZYmcp8kuaOthwii0HM6nCY1ZZZjoktnDH+yvLmcfFeLcpj0daL1IXsBbunFqXQsU7XWHq1Mq5o52v+uxWgsEXUlPJrxgcUhjXvTSk0Y8ypvW+ase5m71aOGVtdk01VVrwkHgszy3vfmsWc3o88J2PrZb/z5jS6P7gJig2i5LNzEcYmrX0jg95anr1EM8Y4466zFgEAKrLhtbDhRavA+cteGK04Ctd8mDTK5HA4HM9NxHjzQmb6/9DTgKfNGIcQXhxC+JUQwgdCCO8PIXwHj18IIfxSCOHD/Hv+mRuuw+FwOJ4u/HPb4XA4nho3kkoxAPgvY4yvA/AlAL41hPA6AN8L4O0xxlcBeDv/7XA4HI7PPvxz2+FwOJ4CTzuVIsb4EICH+PpqCOGDAF4I4GsAfDlP+zEA7wDwPZ92/7k6XIlFWxU1y7JQW606C4NoAyUhZjtrXv1qnhqhVbksxNyIEKoxkZBVZtPwLUVekaXmqkpt3mjXNqsqNv89Motuh2uqiql1GPsf5a41rVW8Ywi4mU60hUU531zHIs+vW6k4ZiFy+7cIqECBYf6LrP/KuRFq/Ray9Zl0wbQNS9WoJExvQj47P4wnQyuaOmPWcIHh/xBLNcDIFI9cPe86AjLt3bJ1mgVTW7plbqtZDW8Q0Vpje6aap1SkC/B9o1VQK7DlkWwJxH4ulNN9aOkblaQTRe4tS42YhbemWT5JSUeCiNAkpaBhCkWuzifpIjUszUDGY3khNi59ZK6tEKgpCMEqKfZyaC4u1aylpk3jGQf7DCiomzSGXsR61WAVG5nmpEI7plJUoRyzioitzU0FvmYlaMLEmfju2a++u9mf2w6H49mJm5kq8elc+zSkVTwjOcYhhLsB/CkA7wRwJz98AeCTAO58kve8FcBbn4nrOxwOh+PTw6f7ue2f2Q6H47mAG/5iHELYA/BTAL4zxnhFv+3HGGMI4bo/Q2KMbwPwNvZx8hwr9KDipfoahkfeZSzeRCZRhWCBvF2sCotVU1RVG7urgh2z9BJVXGNCJdp3xVEZab6X3Y/CZg20Yqtm7Pa8qEgrRTmMLWtHsxUrLJuNp1YWmX5roU3nRRHT0WENzULFSGTq6o59nhQF2nwm2R5xoNhtK4IrjjWy6MQkIj+zkVNLts5OIIseoXuFrB+HPwn7aeOpZ4U0aHNGhq8RlnCEWZnZPSsDyz9MhdW3Ih6trYm0RUYNGi10kcdN1lrFk7Zv2dbImCeLBsiijOy/H23MZV9lAl6jDcYUk0et5Jf2xL6mnkUzhIa1OVYzAaPZ4JnlX5lHtmbTwhgmZuS1ZzZ12V6R/5ZrT5xbJ8fWtF2Lk71vFjcBALRmuyeccU0rt1b29JYFdio+R41UbwnoTs6jms8tiFDXLN/sHs3sIm8hv7an87n9J35mOxyOZw0+mwzxaccN2bWFFMf+KQA/HmP8aR5+OITwfLY/H8AjNzZEh8PhcDxT8M9th8PheHI8bcY4JIrhRwF8MMb4P0vTzwL4RgD/kH9/5mldgExgrwzaZGycDVss03I5XJYplvzVYAyXMEM5t9hyCSX30soqzy2ezPrMWE9hWOzFkPJcgzCUNb3c2qn0tR3SsQVZ3n5SVs6KLhhrVhKEjV1DPaPK03xszJJKWXdkDpvCOhuZZn+1+IfN1/Ixx1GYUzLsgxQjGXuy81bed5araScJg22FGOweiZWb5cdm2z1hkwdjQjVtNdcWsTFqNGBe8GFu02fvl5ymbsE50tpLbMssl7nS35DMKQ+ZWRZ223J5mc8etaDGaHM8WeI4TJp5zF7ZpqywWfDZWg6yr4qd4TwXHwACi4Ro+WNjdZtgBTgkysI1rKUwTS7iYUzrzPuNp1xryZcGluaj1ov5uWZERboaLWIR5nsbKHc5SNGTbi/NKfD5mOR5soIpWj4+l5Qvid1l/MyNH2mfN8hExluAYLnpn9sOh+PUwFnhp4cbSaX4MgDfAOAPQwjv5bH/BumD9SdDCN8E4D4AX3tjQ3Q4HA7HMwT/3HY4HI6nwI24Uvw6rqkKK/iKp9uvw+FwOG4O/HPb4XA4nhqntvLdBKsgJpZek4llxhPnV61ZjTF1QcLCI0PAjVqTUThm6QO1nF9XZvEkoh+zycrhXUlBsBg/hXn1Vmyp8v+D9P9FVu2MdllBUh0Yum0YMm+1ut/ElIVKQvHZ78reX65SM5wfZukS6b10sZqFz4u1FSuOyRzNOku3TJag2XAkPSFWZlNXzh95bcttUIuucZjf75l9i3U/qzBndnuWZiFCsMpC/mkeWoUtV4Brl3K+2ZZR0Cf33ZZukmqGJu7KIkU5P1/KsjHEdi4wTWaUHIdoakNL/bmOoG1mmWarca2tH4BQWQU7jk/abIvO9It2KUvH0UKPlaVESBqHPZO8t0Gs+0pqEYWuIqaLtkF03pzvdJ3Hw6pXmlAwapYJ9+SqLilGE+/bSMu+YRBhrH1myHiylWBraS9SRY+Pg+19FdzVeYFOPssOh8PxmYKnSNxc3JD4zuFwOBwOh8PhuFVwahnjzMbNbJzIQpqoSvzBRv6CashEjVLMoyGT28gxKwJgrFRVFcFVXVvRCBlPJuqskIEwrWScIpVvoT0q79say33SLmpJ5m0rNG89caxNalPGeEsLt0bHZe3GegljbAxurYUbrOiHMd+tiA4rK4xBdlyY5ooUaKNk/XSN7ZpYy9kQlfG3ghMjWyf14svvYNvcPmp+HSBbvlmxBrkdhcMzcZnq5mpj/uV+cw2naDZnwrSaTZ8UiLDlNIs53ScTqVmzQJv02mZlJuebYDFHPAZhjK9T9AM5kmJi0DKPPGwea2W/29xUkJevZMLVcJIdVpa+vsZ43YrXpC7snlpfMmKjfLXgiNnN8X2jXHvkc24FfUa1neN9q2Zrzme/ogWj7OlhsuI7ZayVWRxaXZOZLaMVMeGcRXxXUcTqfLHD4bjZeC6xwqehqIfCGWOHw+FwOBwOhwP+xdjhcDgcDofD4QBwilMpTPQyE2ExbD4wJNvWJ7/XWzWuuiuhbxPO1a2Ezym6a+iHWmtI+klF2xJullhuw/D8OFnlrSIMqmp6G2t1NJ5vwd1GUgo6Xrs34dzMBzj9HWZrYqkHPCZir8mqnWnVPaZqoLP1LQOLrBKWq6vFsoYlhUTC4QxJ14OtifrNpmNbCZ8POfWC15xUhMa0hGuuxzewTbyNLWTP+6DiKluojiK5SULlVgWvknUyf2GrrDgMJSWkW9q8y31QP2UAGGfziLNjjaxvb6kk07ZcOxdxZBqL+ETHaZ72MoPdU7m32Wv7mrEAQJ0FhuK5HNM4zOO3knwU66vV/rljW27mfuZLbII53ndZQ4wbjkf2GvfhhOM0FkmFsayHKZ581uw+bGRJakunwUkRYa7AOFvD1Ee1NKFuaYlWXZLvi5K3FFrnERwOxzOP51LaxLMB/knvcDgcDofD4XDgNDPGmUkrMCFTbcI8tVLi30CWUBngxiqaicitIbtpIjxo5Tt2O00qHONfEwuN0mbWVmR5Vfhnvz2qGcOcji3JIK7FFq3iJBuyz52MeU0hUZBqZ5PZorGa3lAVpq4dycqN5fePVZ1rRrOKk5EOZgdH0d50krWNcqxoqliRUAROY7bAOskKj0NiKueiMhNbGgMstGw06yzpi2sWJmPMZR72ey+Tqvr7j0I7uUVbLnHN/hstH0iGUi3csoVXZoeFheXrin/X1xGhVcK0DmRRo7HtqtabTyNdK7O7Nje1crMX16lIx0Nqn5ffS2Fe25RIhzmeHaA8R8vFmTSnnhUb+zKPC4v0hqs8dFyVvo67vTSG5kI+duaO1Nfn3HkXAOCJRz9a5vjEgwCA++5PVYkredZskq3ej/oaCr8t82+4d0a5pbZ4Cy55FEVpvvVt6rObCVdPVid0OBwOx60FZ4wdDofD4XA4HA6cYsbYCjGM4u5v7E+sjCUsbKoxxVawomnETs0snmZpqJZbzFxjLURBNir2wgqPieUcJytycD02ec4cA0DbMc+114IjaU7DNecAwIYsdU3KLihnTvayqgvDlfM8mfvbTq2cziIK6/L7ZyQjGVvacUmurfnAZas1yasdjU2W3NGBjHTNexQ1l5mdbDU3l68DaHsVhfm2HGazQpsl8lrRD2X1rUhK6rMR+7VgxRmM7btOgQxln3PhCp43ouQAW1EOHc4QzDZwXtQinZdOtDz4SfKJp3l9EwBAFVY8Zsz0SZs63bhmmVZVJ+lk22E2rDCzAWQeruxby9M+jGc4r9tz2/rYWOFiPXjx0v0AgO1Rygs+uPRYbvuKv/q304vL6Tqf84ZX5rbPf8trAQAP33sxH/utX/v3AIAP3fP/pettS9swzAvAjKIlyBGFMm2r+ZHzgzVfuWqs2InmxnPvcDu1C3leSXTXZIxDrcV3rIiQ5wM6HI4bh+cWn044Y+xwOBwOh8PhcMC/GDscDofD4XA4HABOcSpFqTxVQuRmgVVNFuY8Kd6y8LFaT1kItJK+snjLdFTXOX+aFWbj+Tn1QELe7MTSMbRSVx3mKR4KE/asRdNjlcCsWp0Kx1qzq1NRIF8OlhqwkSFTYRajriFFfSNTVRoRtDHsbOH6zXWEc2oHFynaytXbJKVga2IvrSLXWtqH2aiJFRbXoGPqwjDTU6Vj41gWyiqs1UV2KednwzI7uYw5+6OVa1vqgf2tJk1VOZnSwtuAgYq/MEjKSdazMfUmit0e134WPgub2bVz5yj3QZei5TFLuahVWMi1NmFao6lGXOvLG9mbuC2dx71w8OgTuW07rtOxi5fzsUuPP5TatimVYm+5l9s+8O6fBwD8rW/5bwEAu+MLctvP/PRPAACO7vntfMys3+LA1BCtgsjFsG0epZyjPRezRJtcndDSLMRGjmuiVRxjbRUR+TlSiXjSxKm8ZBAhX7YGlGt7INThcHw68PSJgtNW8c7gjLHD4XA4HA6Hw4FTzBibBdjc0otsERmxmaUXYUeUZaoy+ypM0jVsnP5CCHyvitymwZgqs0w7OebJ7NSEJa0oxKub4hdV0a6sp8CukV9NJuhqbI6VCqh4u4TR3FBg1/DvKMyYrV0Qfq0lpbnlUtR9mflg7Fg1ZyWBIoabxGrM6LKBArMYdd5pbmNXxGct187s4OJQrt1QrTeQSQxSDMKu2QpbveWUTNRYyx0UHlWHqKQAACAASURBVDr9W6zyMvOthUrI0k6BQivZDMOYjqlwc8oCvvGa6wHTdmsX4tivw7rLOo3sq7a5yZpXtEqLwjpbLZU2i+8komCv7ZC0HU1nAQA73Sofu3wlMcS3nU82ao9cvZrbtps076sHhUXut4epezLRi93S11/8yv8cAPBz//ZnAQAvxj25bX1o6yTCTYpEz9x2BwBgtVes3O578CGe1HP+EgbByaIndm8Cad4g9m3GHqutne1rixrVsqcnRggsOhXkWaviyfvtcDgcjlsLzhg7HA6Hw+FwOBw4xYxxZorjLNE3/TczbtfL9jPbL/VmO5ljjGv6CHody81U1tL6m6zAh+QlGmPFtmpGKVlerdrH2bBYdleuY0VIAvNpWy1iYjZkUgSi3pitHf8tV84ldWVqI5nZyHzXWbldMpqDldWWNRxPdgVYKWWz0RNrvak6yb4aC27lqDsp3DDkHO48+PK+MY21F/bVXLRiHlG5kJUnnoLlpAsjaBeQufVkMiuu11auM5Jtn4R1t/5sTaCFTSYr4mG+c7kpF4epZKxTb4y6lSfWPUd7PrH/M3vBUDUn2mw/jSzo0g/nc9uKPmTH25Mloa9eucxxlTk+8fjDAIBhfZCPLRb0MgsW/Sh9feyePwQAnA+JdT4ey7M2bBPjW58tecdvesWb0zWXuwCARx+9P7ft7iQmer1mkZStPDv8qxEhNFb0xPKutc2sBMshS2i3SEovVm6tPQOM5ujb4lOUinc4HI6ngucWP3vgjLHD4XA4HA6HwwH/YuxwOBwOh8PhcAA4xakUOZNChmjB2Wihz1FC5NFi66ySJuHzLM4RMZKlakzsY1LBzjBLGGC/TBcwmzMV/k1WCc0qx0l6AkPfmuJgIW+zdxtE4GPnmROd2s6ZHVonw9tynoOldoiwK7QMqYutnVUPDJZuIKkUObPBhHCxiKXMRUyDyZY2YAKlqVVrMp6vNnVLplCYsFDEdJaeEM2nTebYUwDXDiq4YpU6s+qaxBZunP/ei0HvJ9NqJp0bK5pZakgt/nm2P+QeTZVV4rO9pvZ5Ng6G8OX+2Z6cZH+YmG7B/rcSbVvktKByrG5YxdHmLSkhgTfp4CDtq24lwj+mbFy59MkyNQoFLw2PAgDe8pJzue0Hvv6vAwB+/Dffl4/9/K+9K42rSykVZ8/fldtuv+1OAMDj938EAHC0Oc5tq7teAQB45Wu/Ih+bDh8HADx2OVXW20plyGaafyzF67yu1KoxH8ybLjeFbG8np1dmY7jm24pA1J6j9jpVLOMptRZyOByOZxNOq02bwRljh8PhcDgcDocDp5oxpqBGxEjG/BlBN2nxBFJtY0eLJy1OYX+F5TX2eOKxaRBeyvRyULaP51kCvbKEo4nW0r8bSbLPoxeGy9i+QHGYFmno2GacZS3DMie2SvqvjVWk2KuqiuipGu32iqArV7PgH2V0zSKvMts5tUxLrJoWF6lMyMciFSpyQ0NhoTDxVWtMOddSfpZlJn5LAdlWGXkWTuklQkCmtLNiLMI45uW8TkGNwD00zDj8NQdIdlH2wkDbuX4qDGg0ap2nVVJAJVB0aOJGvUqkAqwS0WFenkhRnYg6R9rHtc0yH2uqJHyzSIRqTB9+JI1xZ+f2NOZNYcWPDh/hGEr/DffFn79jHwDwta95S277wd9I9/QbhT3/nTueDwC4ejFZuK0WxYLw4kMfAgBsyXzvPO8Vue0tf+7rAQD3fOgjZaz33ZfGuL0EAPjkE5/IbbFJfazqNO/lQkSzHLOyt3m/WiRCFt2eh9n5Wfxac8zSZs9Md1I8WcXTzXI4HI7TBxfdPfvgjLHD4XA4HA6HwwH/YuxwOBwOh8PhcAA4xakU4TrhBxNcNYyVbsQ3d5hSOHwadvhv8dRl+L+qJExtYX+GljcSTm0YGm/E33TMYq2TYqyRfTQm1ArqFWvxdvGizT7BFq4t12lylT6G4jUEHM3XVit78X0N+w9ySxmeh4rc2D4xLWFspCpcXieOr9Y1NHFfmVtkqD8w0l03UqUvH5M0BjvWpjFomoWlGWwZRldxVewpchNF3rJdsS2F8zUto2cahvkYzxpzik2pppavHef+tgCwHbmvVIg4prSSEBYcV0mzAEPxDe9pL9UWrVuttGZ+vLbSnVZNrE9WPxzDvJrh0aXSfVfT//fokCcXUdm2X/N9ZS229Bd+cHMGALC88q7c9kUPfBgA8JHbX5aPra+mPhYdxX2LvdzW96mv2+96EwDg7td+cW5b7iav4vs+8nv52L3veycA4K4XJQHf/t4it+VdZ1o62VdVTqPSSnasVJnPuY6/ueRXZL9u+mOHWRZV+kfYWnpUSeMoWt/r+ac7HA5HgqdPPLvhjLHD4XA4HA6Hw4FTzBibQkZdPeosGKOwqynin2h2V0NirhaDWDANiY1SMV2ACfmMnxL2kuxwlEp5Zu9mFbEGEUlNY2ETAaCKKlDj2IWWGlndrmJfXVvmcbxO4zcrt1bYwoZ2XK2K71pjhcm4idWVjVnFfaOxr2RT40YEdk061rQ2Vy3bZgxaWdfGrK04n6hMttmJLWT8rHhnhdNaFTfaWMkU98pkr1kFcLGTjw0U6VVck0FYQhNe9puJ66BCTKs+J3unIgNMSnAQxt/6GoSttqpzMIZ5xlCSrR5NyCgV+UazeZPKhfke8d+1RBay6E7sx6y64kDhWF/OXywTY7ziHJ84KPfKhHgqQDXR4SNTYozf+s7HcstOnYR2D//hQ/nYbfuJ+R2419742jfnticupwp5m3Ua12/99q/ntgtnE7P8wr1i73aPaUBDmmOj68T9PdQnWZf8eaA0r4nuglU8LJEOI5ZVsDryPpvwtMKq9MVnf+Ten7nCDcbWK+PvcDgcCc4UPzlOu0Wbwhljh8PhcDgcDocDp5gxtnziSosh2LHMEJXzzXKpJuNj+ZPal5JM+c38hTdFZYzJCksObM3c3JG2ZZpjnItAkFVVC62RrGol7GhDJnqoOEYtysGfKsYUh2ohbWu+v7CdCzJt62jFQkpfNX/39NBjNkcys5I7G7bzIiGhkRxrY1GF2TPWfYTZZYmtFot9qHVWWKR+W+bONpoXHO2Ysc/C8LGT0AuDb3VA2H/sxCJvtNxctqldm/0WjJJjbEU/jJ3XfGKSrlrowfaM5T5rvivI6Na5+EdpMx6zkQ1S23s5x0aiIHbNKPfP8sDXR+n8TqzMjg5TwnHkRo+SZ7/cSWx7kH1e12c4ZK7XVJjTJ44vAwDOny0s/Sam122b+vj1P/j90hdzmEfmNcdhndu2u6lwyLnbC2O8aBKLPHJ9KrGkG4aUI20rPkrEw3QCUaue2Ga4RoMAAEbOK09u2oHRivaoxWFlzzfns5Y8+1F7cTgcDsetCGeMHQ6Hw+FwOBwO+Bdjh8PhcDgcDocDwClOpTBLJIncI0azMEvhTROxAUDD0GocKMLbFAutJguajvIxs0Oz/IqoFceouGk1AGvVtRgq1wplJuCbeH6UUHlrgrSgAjDauzGlQrRYGHOoOJ2/EEHbgpXjxlhC3tuBVmNck3qW357e25VoMIba0kpMySjV5BiKtup2cStpFiaGk/QSKzbXViY0E9Ghpa+0Yj9mKQutpcmU7WdZGzYGFTAulgvORiuUMb2Ck5uOxYYsV0JjGstMTJcwivhuisez1kmq+5nvXDuW/gcmRUwmDhs0VWMuMJDlQp+LDso8eI/aRZpjVZeUAssFaTRnaErjsSKAoV/L+RQbMkuklc3QsX9NMap5rGtTikQlItDpcro3h/IctW261jGrTHbVxdIX91HNZ7KXe7tl9cA/vu99pX8TSPYmCizzDnw2TURXS1pNaNL8Z6I4S7WpLKVJ0n0spUWe5dEqEDKVQgs2Vlxf62PaHJb3DS6scTgcc7jg7taDM8YOh8PhcDgcDgdOM2NM9rFWsddoTKOJZQoVasK6KdtliV3bhoIg+WFnFmYm5ItqwTSetPmqcjEOMkkq0MrsJtneUfoyOliUfybkq8hwVXVhNPuJFlJkRLulCO1oD9YLo7mgeMmY4KNBrKooEOyFcZxYoGMwGytht40Nn8i6T0LLtZyH/jq2zRNqu0dqk9XaAuRjpkoM8RrWOv2LY07/6oIUfGDRjLWw7q2x2xQdTlKMxO6tMfe9iKaoG0MUUWAWn7H/TtlhKwoTi0CrMdEW5xhDYWFDJuLTOaPc96WJApXJJVtrBWDUtiwLx+T+HR3ZnrFCLWWf12Maz7ZOzO6yKcI5W+uuLfM4u7uf2ijwbOqyp6eJbHJfxn989SoAoG15b6Jay1HoOdLCri1td77wVQCA8YGP5mOXp2QNV5O5b5eFMa5ofzix/9CVMS9BcW0tv+m5Fia8jSKUzDZ7ch8qzimQAW7kU7A/tg8SFrkJu7kt2Hy9vofD8ZyHM8WfGp5NNm0GZ4wdDofD4XA4HA74F2OHw+FwOBwOhwPAaU6lyCkIEvOurPqaeQOLvylVTladSsV0G1bD60RlM3VMZzCBk6ZS8OW4FcFca6HV+sT50zVeyEHEQpHhWg0tW7R8rE2MJiI0hvNHCvq6UFIplguGq6Wq37ZP5zUM+TdNWa/eBG3TSVFcPZmXq4aDUl9mrRvlfcNAkZjuGKZ9mDewhkwi13qUtISGkfotw9qT2B5Tn4WGfU3i+zxWJoaUEDnX2ESXC8mNOKrmIkhLXQGAPqetaIoHQ/FW+U58omtLDdDqgRzbgvMdK/XNZeU08zNW/Sav03al/0DBW0vRXZC4vvlQ6xrm6o1MDzneFvFdxb3QrlJfnVzH7JQnER2u10lY19JfuquKqPPsbkohOLxyJR/bdKwQyPuwlWvXFcfPmyoZG3j8scfT+KSSZJ4vfZgrWcOJa9Bx/4WF3KsmpXEsZj7XvKdMqdAUnY55D2GQqpdcYqtOOA7lJjUrrvna7qP4iNuG9Qiqw+Fw3LJwxtjhcDgcDofD4cAzwBiH5K30LgAPxBi/OoTwMgA/AeA2AO8G8A0xxu1T9XE9GLOpwqMpV7CjyEZYRasgZhXUQl+ERNsxMcZDU1jkbiJT1xhzLGwk+5+EdTa20uyognismbWaJeOLRgwT2Uu1fjOWuiabpZXpWmMJyS6OIuRrKPaqRazXck7VaBXUylIXRzap0hfmwrdBRYFWTc7s2lDeZ0JEZS9rCpRiz79in2eitbAtc+vJ8i1MtFZGlQVwJnqKcp3JGL2psJ2xN4u8dN4gvWU9YWVrKfM31zm1yCPTb8x0LdXqbE6DRBvqcf57MgrDbMxyZWznIGwv2fxKRHEthW8m7mxkT0cOcjoSBrTb5yvO/1As9UzUx76GqYgC2y5VmusPi8VaXCWGeBhMpCnXpqAwlqmh3fBZITPbiL2bVSqs2RZDGdelJx5O71+U81erxEjH7TAbAwB0exSxcp+HtoyrM7ZXbqA9T/lnvoo9YmK160EjPGSWeclJ2OQ1x2EWhNut7HelwZ/FuFmf2Q7HcwEuurv18Uwwxt8B4IPy738E4AdjjK8EcBHANz0D13A4HA7HMwP/zHY4HI4nwQ0xxiGEFwH4KgD/A4DvDinJ9C8A+Hqe8mMAvh/A//rp903mrZYh0q7MclvVgsnsx+xYr679UyrsMYnlVjb8Zw5vqJVVtCRjKQxBNs7s4IIwe1bUwYYwKTtMJnSUfN1AFnIig6hWca3l/pKNG6Wtox1V0xRGzKzJrNZEJ0xaT7ZZc38t99VI0VrYZGP9it2cFEWwPibJtTX7PDKoQ1/O7yqutbC1EwtDmIVWHTU3l/d76DgGye8eyDALqxjJ+hnR3HTyG49D7fm7r9Mc43GeD67jsJxqZUJHWt410v3E8RvDvJC+QrPL/tO9qjopQjMyX7Up+9Dyn0sRGsm1zcx1sQyz6h3rw0To7e6ckfN5Tfahtn6xZ6EOzUFnAZfA/N7tVArgdJzbJPe7Wa44f+bZh2KRt+3TmnQsBDNWwiZzukGsATe0mVvtkD2vhZHfNStFRmcaeZb5upJ9Ffg82GdGkJCNPcLdouwB0wQE3vdxW/pfsGpN7LgXxjLm5obja5993MzPbIfD4bgVcKOM8Q8B+K9RvkHdBuBSjPYNFvcDeOENXsPhcDgczwz8M9vhcDieAk/7i3EI4asBPBJjfPfTfP9bQwjvCiG86+mOweFwOByfGvwz2+FwOP5k3Ehw8MsA/NUQwn8AYAngDIAfBnAuhNCQgXgRgAeu9+YY49sAvA0AQggnstmDiZHqkyFQi3yGsQh8Rglnpz5FbGO2TFKtzsKuOVqtpdCsMp2kMYyWxsDUiylIKNcEbZa+UUloPVd5K92bGM5CwI2IuTY8ZpkdlQqJOOZWQtJWNa+yVA9JQTDBnC7umG2u5hW+AGBDG7hAi7J6lrLBELakqPRmRcel66Ti2MjQeC02Zya+M3u3OJbzLTUlpzhIZoulXlSiBGvM6s4EarWmqjAMzrSBYStVCrk+fckCQGMpCJbiICkIDViRTdI4Jku1sFQVEetVtp7Niu+XCn5My1DhZuCahSy6lPSgY6btaJrIlMazWDL9YVvSHxZduuaW1Q+jCFDNPm+Qyog9BXxtw/XSFARLM5BnzDjGjukhw0bXydJLWp5T5t1zfXUj7lB81yxSKkVTlcp3zeowzZv7r9JqgOykUh0cn8WaqR2jPDMNN6eJc9ObmYbD5y4upfoj011aS98RT8GPL0vlvmcpbupntsNxq8IFd88tPG3GOMb4fTHGF8UY7wbwdQB+Ocb4nwD4FQB/nad9I4CfueFROhwOh+OG4J/ZDofD8SfjZshJvgfAT4QQ/j6A9wD40afTibGwdaOMMRmqgXZqwkaCzFYkKzfIL7x4HdY2MKVupIhLLdMas+8SErk1GzGywVrwIZDFMjZLf11GslmDiKqaaMUf2KfM2xiugRUvlDGuySaqwG5BVrRj9YxGCD7zjZswo6tnY+6FRa+NDba1nwkfKVqbdU+hFZWPg7C21TYxbVuhfhfcbiMZ00nHakxptpgrTQ2LUnRilxU4NrNWE4I5E762F/pFuVCz5foOx/nYSFbwemx1jgZAowAUedkhsaSLbKuskIZsOiumMokF32SsO6MAlbDPR5s01jNni73bwcFlnp+us7NbxHfbDS3WOI+mW0pbsi0bYrFw64/T62mRzl8Iy2tFL6zQDAA0fBZHCucaOb9Cyzny/EHWvE3j6IV1D7xJO03H04V1J8se+KzNoiZWvAVlXEbAR5xkmHMRIDkWTNTH6E+c5NmcLBKR2nrdiDKMWwzPyGe2w+Fw3Ap4Rr4YxxjfAeAdfH0vgC96Jvp1OBwOxzMP/8x2OByO6+PUGhBluzax2grMITQ7qq1QjpPZkOFkkY1iNSasn7m1kVUcJe+zrawssfSR+2U+quQkW7GBXEpZ+srUpzCHgQyVkYPKiI2ZzTIrt4LOLM1qpbLJ4rH4hRZK2JD161G8+s1abmKecy2zbHaYj9nO814BWV/JMTZmroKV4Rbm1F725f6tycYtWPQidpLbacsEK+MsxVuYT9tUUp6XrGJkLrPmg9fGlFsutuSXVix/3HRi3cec6rEn4y/54za3ICWLa2MfeR+jWI1ZmCGvlzCOC/Y1yFM3tCw5TRZ5K9Zhe4vEBm97ySNujQW2nOGT5b73aOHWS979lvnGjVbsYG7xhnnKw6bsk4rr0ywL6zxx/F1tzL/kmxtTzORftbwze7ujq5fzsch5rPvEZO9JjjGO072tua66voF9TZrXHef3u5Z7ZZ8fjRzLegIrGKP7g8+WfR408WS2mWcbOhzPDXhu8XMTXhLa4XA4HA6Hw+GAfzF2OBwOh8PhcDgAnOJUilJ8ThMa0nCnKoV8NchhYV5zo4qzCmLmfVaODQyDW9S8EXGOBZTbmYgu/e3N+k2tzJiikbMrJPxq45LoPEbmDdQUrQVJjcg155g2UosvlYXltWqbVSGreR21cuvaNI61pH0MDNk3LOXWdnu5LduIMSS/kDWhFgm9zGNr9mNMx5BiZJjY/1LWwlItiqudtPFagbZzTVu25qrZT8e6cqyhEK+2NJZy6Sy6267XvJ6kktj8ZX/0MYXuzfpulPMtZaaS8+2YrVeUp8h0dXasle2bz5c8nyomizVL8zk+kupzTGNopALjEFJKxLBJ5wVIhTmzp6MXnQpEuzbNcavHeH7Y0p5Q7PZqszSTlbVUlp7pDEFSmUwku2hr/i3V+h57/H4AwHpbBI9nd5Og0Hb3eijXWR2lNan3KA4Ubz3TAmpqi4lwTcAYxSKv6jrOpxyrLYWCeyjIc77dcE5WIVHu3+Q8gsPhcNzy8E96h8PhcDgcDocDp5gxtkIEvbBlWxZqsJoD216Y09Gs0sC/0pbtu8QmK1O4xjYV9mtBFq4Sf6bBRGtkNCspGrFcJPaqjSwKoGI6s4+7jlWVrb4K+aKxz4P9FWbMii4EqU4BK15C5rguIiZjj1sV61EktVqlsVahMI5GNjfGaKtVnAmvxLKqpmjNBAqxVjEd11WHShbZRjOJ6Kkje2zCv65dlbaQXi/qcmxBprshlR0mXae01uvpKud8pUx/om1Zr8Ve0iAnMt91JYVEyJzqPcp92dMjzHfFtejMRq5RUSD3iViNDcaoU/i3XBUGv+YNGYQd7Sie29LmTAWSZi03HG3YZblO4PMQGoke0K6trRJ7G4XyNxGrfkAMI23aOC4VYnaVFb5J++rRiw+WvvgM7J25LR9b1umaVZOYXBX5bQ7S3707UqRgRGHRJ1rF1cJkV9cUe9EoyyKk69Sx9G+2boHP1iTPeRfSeUNI1+zVrW06uQccDsetBRfcOZwxdjgcDofD4XA44F+MHQ6Hw+FwOBwOAKc4lcJ8g4+3JSViGCxdguKfWrxoGdbdMKWiUh9jhpGjhO6ztTGvY1XlAGDNEHQv/ZvAbNqmay8WZek2A6u8RasYJ36+FlKXa2edEcVooVeBYXptIrmVhowpUFtOpRJa7BieZ5h3PRbhmIW8W8lnWJm/LMPzbbuQ8xmKDjZnSaVgeoXY5qJldbPKvJebsl4DU2A0jWOk6MyWupJ1qijeapka0YqozEL9bShjbWMSd3WWPiCiQ6vIZ56/ls4CAANNhBtJZ1hPac1CsKpqIjrMKRTSv42Z855EIDqZ9260uapIzKomlrB+x6E9/MRh+veirOHVgwPOWwRwHdNJcqU4qQDHPTaxauLuogjgjhge7A+v5mOtic/o9TupspL9Hq9LpTxLexhrE+uVuW2oiltfvsg+S0/1Mo15uSjzHq0yHlOH1uuS2nL+3IXUv3kvV2W/W0XBoGk+FN+1fF5323L/Vkw9qUWQN3Gfb8xPXIR/didta47qAX7rVr5zOJ7z8BQKh8EZY4fD4XA4HA6HA6eYMTZ2eC0iqfw1ngIfjKrsSsxQpIhuK8IjY22jMm9WWY7U0EYEVI1VchNrK/OJypXjpPLWlgxlMEGfEG9WjUw5YXOfohYNg4iYzMqrIgs5diKumtLtGqDzZlU4Mq1NK8wmK8ytViKqIrO6S/GWcoQN2eelMaEyrkAWshbmdLFO4+nJ9lbqbcXKaaPQbJ0J8kgZV2IHZ6IwE7spk21MYNuosNAEgjxP7veUqyWSdZc1XNvcUPZVJNOdi+3JvbUVqMWurcmVDsn4l1mjH/TeSAcooq/DJ9b52BOXyBSTyY8SPdjfSUK87brYnG026fVqRcGcesXRQrDZpL+PPPbJ3GRM/N658/nY5YuPcT6JFV3tlzU/PqaIsNI1p/CPz90gAtSMYFXxCtNahJUlCrDuE3Ndd4nVHsYyx+02VcjrYmKOa3luzT5ukEU3W8FdRnF2a4mC2GuJCFllysjnaBR+YM09XPEzpm2V+ub+lT3tLJPD4XDcWnDG2OFwOBwOh8PhwClmjK3oRbNb2B/LYe3IEM1yIskqLa0Ixqy3uZVb6osWTzymubCWm6t2ZcFyhJlD2oaydMYgWd5kPxRGsBlTv0d9ydU0+6pDXlsLdlghiSXnup0KA2mM7KRE9mS5uTxH/NRqjrkREjN0xt6l/hfCd9oaLFtjpiUHGFbwoHTW57VIfWotlsD7Ucka2jsry4UVMq7jNSsyx7q+lgu7XMhe4Pkt++/GkpsLrm9v1x6kkAisTdhqstTBKGOpxlIZE6/56ZjnIguhiX0SrB0jEVpk496Pp5xhY4nT3NK1t9vEsC4kD9c27HJVjtlzMR4zgiGs+8A83atXHk99qbsYk+6PD0qOcVNP7P8sAGDdF9a2ozXe2MhNJWPckrXuYznfIimWDx2akhc8Md/80uOP5WPnzyY2+Ogw5STv7+6XyzB/etqwWMhKitzw3jShTG5FVneXLG8nH2vBGPVBH35aLvIeHUvcZIfPU708mXdt99RJYofj1oFHfRzXwhljh8PhcDgcDocD/sXY4XA4HA6Hw+EAcIpTKRaLFMrd339ePrai+CoyLDwTe0WzRaMlluZSMOoa9VjbaRMgoqnIvIRKvMmy6IzpA9p/5HtN+GeheaBU7gsSb58oFLMKbVVXQsW1Vc+jOGzUqng1ryP2YzaBgPS+RsJCiyb1EZvy+8cctqyyXCOV2RoTwFHstpTLTJVV4pNqZw2r+pnAUMZlgscwEzwyZSGnIsg0mCIQKHBSa68zO+lerRZFvLViWoWleAybcu3N1mzRTCxV7sdkQrtY1mSy8D/zappQ0gBMWmdpIwBQT1bBLqGTNTShYMNH63fe+/HcdunwAQDA2f078rGjK1dm146aHcT1XEgqhQnftiMrsx2VfTtOtM/j791qWVJPRqZZbI4P8rFulYRvtYkbhyKYqztLXynVBg+eSCkalqJy56qsYbeTXl8+ZOqQ2CxWC6YmTeU+dCsTFqa0owce/URuu3Db8wEAq6M0nuefK2MwMacK4BZNmkf5PFBbRqYOyTOwMC82HtqdPZsUD25omyiivbbiemrujEdhHY5nHTx9w/9TGgAAIABJREFUwvFUcMbY4XA4HA6Hw+HAKWaMa1KyS7HJMnawmcwCTYpHkGprq7kNGyAFGORXYqCoxiy39BdkTcusKGqywYozjHZ+Ydei9UURzyQWcz292bbCPg9kAlsyerUIiWqyqRXt1JScGmmPNW7LtQcrvMGfOFHspRbG0IoIy6zGzHpqURUW1ohuK44yChMayJJWdZlHJGea9X5qb2dUmgjsxrwGJ3+tG2NslmO7S1kTiqoWTTlmAsGG15y6QrUuKMSz+26sPQDgIPV/EItAsh2tXzLH9UnGsdGJcJrUZ2HVlscoHqfzfvn3/gAAcO5ssUc7GxITevHRB/Ox/fPnAACbo8TkbrcyLtrn9ZPuHUZGeKhpyrVHFoXZXSYh2+HRlTIPjvnMhTKeM3u3AQCOrqZr76xKQZCez8D68uV8bMHCHgsyzPsvOJfb/sM33g4A+Pfv+ggA4N77izBvsqIcTdlrA9ntg8NLAIALF+7KbTssYnK0Tqz4airjsojNVJUoS8UCLSaUFJfBzOov5B5Vwaz++CwLm2xFUrZ8DsdZUQ/7HNGDzjw5HA7HrQRnjB0Oh8PhcDgcDvgXY4fD4XA4HA6HA8ApTqUw79PtUNISulz1ytIZRBzH+P9Ek9+g1csmq4ancX2mS+QUClXmWR/iPRztbfwtMUoqBdMsWvZxLGkZg11H1HrLvZRC0TF3oZIwfU1fWlopW2YBAGBdnRS0Bau6N5o3sIyLofhVJ9XLGM6uTUQoP42q3tacY55pGymgakoI24Zh8i9NRylzkrQEE0Gar7QIqFqmdlj6gHkXA0Bo6Yks92/cshIfd/BShGYtx9hT2BUkHr6/u+IYSlrGepPOs+J5VXXysZhkzatoVeHSda5cLQK433zP+1Jf9Po9ast1zCf53PkiKJ0sDYBiw/649LWlGO5QKt8FPhdW6bCX52OqUttmm/Zt1Zabu7tgFTkR8vXH6byRe2bYaHU4zlWq1Vlv+/tpDf/MG1+U29bMK/mbX/o5AID7PvFwbvuJ96R0ieNNmQeO0lrs7KU0iU5SI6yq30MP3ZfG94Iihmx4b5etCh7TvQ8Um0KrAfK+TfK8Vo35dKcNXs8Ej7y3tlkldajOKTbKJ2jtSIfDcRrhYjvHpwNnjB0Oh8PhcDgcDpxixngkc7MZCss0kvkzNjLUInoi4xjJoA1iPRXI2m6E3RkpuGpY2UuZUyOXVAg1suJb4C/PUQVdZh/H3xlDVAaYldkWhRE7u0wsnFlhVcLMWr+jVJgzdKSPu6qIkUYKsyoy0sMkDCXZ4Wl2m1lNjSJFs44DgIkMo7HvQUVfpqWry0IZaTeNZLnl/DGYIFFs0YzF56EWynyT8bdzxT7PLNBGETwGVkerF7TXqsq8Tdw4DaNduLyPNm1VLYw0OW8jLUdhFxoy+DNxJqMGjzyexGG//0cfKvOmAO7M/gWOoewhY8p3VoWFXW/TuO3IUJU5Tlz0Rtbc9Ism6pzGsk5LCim3jHQEYeuH7THPF0s9+8t1irKG9t4qKGOa9mu3m/bf/rk7c9tiShX1Lj96DwDgwqK870vvSgv7Kx8va2EF+2raBh6KjdyV4zTWJW3eNusiIgTZ3mkqzHfk/etGWviJaHTiM6OP62gRC5urzLHhGpg7n1ZnjNniz1lih+O0wtlhx43CGWOHw+FwOBwOhwOnmDEeRhYk2B7lY5nRCidzgFeRllBkC2th3ioWiKhiyUO9uk7vjZv0t5lVBDFLrNLHltZRY2WsteQ4kkmyNNQAZdnStZumMFyBjHIuxiH2YC29z6aBhSiEyo5k0YdeWEjL07WiHIuSjxnJrlVCe1kKa9ykubXCnOZ8TFrf7Qjzfcil2CgjzfG3XLtp0LxPMq1qqWcMbqHqyrXNrc0Ybc3p5XpulNbnnGwD96OwhMY+k7Xu43XaNHpAxrGQ9JqfHmfvA4CPPZJyZh96KBXsOLN7W5lGTPvpJW98KQDgda9+VW775Z/7NQDAuf1y/qOPpD76KjGn08HVMkdLZ++lWAbXYAz97C8AbDYs8GHWdzLHY1r9xak8T1YkY9Gl52KQedt1JrEstJztO5gDfL49zG1Hlx4DAJxt0jzuuEvs0ZjXfeHVF/KxX33//eyfOdNimXb5arKIG2hLOAz7uc2e/VZyqwOfyTFYNKD0ZSn3G8kbryzv3+wfhSnPz2JlucnSFxwOx2mEs8SOZxLOGDscDofD4XA4HPAvxg6Hw+FwOBwOB4BTnEoRTmYZZMusKqSYt1ZCa6uef9O/Vzt7ua2mqmor4fZzPO8q0yXCcUlPMOEN6hKuPaRIbdim0G8nAp+Gy1hxsFNXxFUdbbgsXA0AO3spFL2zTH+XOyIkYoh4Y1ZaIgC0zIOdtpxfMY1jy7SJldhxBYaPVShYUaxVUbTWih+cFQfraJU2StrEZeZgXJJ1OtikY62F7CX1YklbLbVY23AcB5ybhultxZY8P6hNH9c1xLKux7xmZYLMSubIS5rYL0pqS7RKgUM5vzd7Ov7V9JVhJ/WxGl6Wj93/oX8NAFicSWv9Td/1H+e2P/26LwUAvPfelGbwQ//TP8htK+6/j370g/mYDW1r9mgS1j8+ZNW5qqzFYnEmjfk49T/LAKLAs2P6zlCJuJEWbjN7PqZcjFyn7aakcezvpwp5zbKk5ly6nNIlXnZ72stnxcrshfup46tc1m51Jrfd3aRn7ExbKuW9/T3vTWMc+Cwsyr49u5veu7/DKpZqf8jXlZS3C9lmz/ZaubdTTjVSASb3DFMuRsmkGE10yCUfowofdbEdDsdnC5464biZcMbY4XA4HA6Hw+HAKWaM93aSYGdHilPUJlpj0YRO2OSGzOceCw0YawYgV+dYiKBrJEdpjG4/SaEEWmGFIOzriuza1gosFJppSdpv0aVrm+gNACZac7XCYO8s0uuOc6uFVY2cR9PQQqsXFpYeV50K5shwNVawIwj9FawgiBbSSO1Ljkt/GS3Zx4Js77G4Uu2QIY+8L+m9iQmcuL7K7jfGZIuAseU4los0hu2mMHCtrQHFk70wghMSS90IS78xgSRZwp1FWfOWtmWBLGFTlzE8drjmteV+T3MLvhiKBdriOInnfutX/0U+9vlflVjh7/vm7wMAvOM9D+a2v/nN3woAqA8OOZ0iEK1oL9hWZaG2ZK7t2HpdBG0tBWl1dzYfG/o0l44RCBV1WkUWE7JVwpRbAZGF7M2RwrK+T9fcFZYXgdGGvqzF3jL18eo709/zsVisbfu0ng2jFJMU2Who79aKNeA3fN3fAQD8q5/+t+n928JWHx8me7Y3vvjlAICNzqO2Z0yKvdg17TTZtxZlGkVEB4pLUTHyJM/TwZoixWjVaGTPjSctFB0Ox82Fs8OOzzScMXY4HA6Hw+FwOHCKGeOGea4X7ijWVkbkWeGGCYUJXPArfrS8Y7VgIlNVq+GSFW4ga6v5g90OmbpBmNZF6uOQFlKxFyaUfdWkqoKwcmD/UZZ6MrbTinnID+LIfwy019LiHyFaGetCiQXmkdb0O9tspUAEmTC1GrMcU7PmqiY930ptMz9YmE0jdIPkXJayz7S2EmZvyzFa3i6QHbDQGRs5FtZ2ZLJsMN82yTG2fOCjIHnBzA/d4/2+clgKwSzJtltkQYaAiYz0INe2XOf3f+gTAIDXv6Cw+xeP/gAA8CM/+WP52C//bmJY/8Z/+s3peuPl3LbDoi1Xrj4BAHjpS1+e2x6/kqzS1mLJtmIJ7CtHqc+lRBYC93B/VFjkrk1MsZXMrqTIjZWX7ljGebMuDOcu2d5BfgsvueaHR9xroTCnh30a6+agXPsNr0ylrM8t03kHh6VtXG85H0YbZMwPPpLW59Vf8Jp87MIL35Tm+K9/FgCwFWZ6yxLdLa0H18LUjoG5+pI/bVvStAQ7Uoa7YhTnWCIEx4xU2BZbQ1j9as62j7KnzY5Qbducy3I4nnk4S+z4bMIZY4fD4XA4HA6HA/7F2OFwOBwOh8PhAHCKUym6ZQqZ7q9KtayrDOvWLa2nQrGSqmDh1hQq30j6wGQWYFMJxQ8Mz+aQeqsV4Ci004ppwdIYUphaAz0Wnh9Dx3MlBWFrAjCx3KrS3CoKg47UOsxCvkzVCBLyHxhubrsy1oa5EUOb2vpYwsg9BVGbWPqw9Igdrk8jgqiG1dcGS9WQSY4UqG11POx3YIqHnh+YJqIVArs9CsZ4P47kfsSjo1mfUQWJTC+Jsq52f5f0OeuHMo/YpLaawsUYNP2DW15SQt79O38IADh47GMAgPc+uJvbvu3bvgcA8O3f/g/zsfWVjwIAdldpvZqmpD9MXM/bn/d8AMAnH3k4t1l6wVJUo9s+9bFcpj6CCET7bUoPaZcisGMaSktrtvVxuR87tOrb9iP7LM/HUZ/62pdjVw6TeC4yOWDStBrau+12ZZ1u69LcNrSKw1jSVy7w2pHjm/qSnjDwWa5f+iWlf+7D2+5Iz/fjj9yf2+48nyrdVXwmaxEYWvrRIPfUnoELZ9N5Z6pijRgpNt3pynge7VMqyyGrXmp6UAyWVkILRrkf0e3aHI6bAk+duLWggv9nI5wxdjgcDofD4XA4cIoZY1jhBhHlGCvck03cFZFNBxPAJcbnWFlYvhzFAmxLJnckC1SL/ZoVWdjryrFhorUV+7/Si3CMgrHsIKUCNV67FUbziAUu2oZ9xMJEHRsDSlu4VubRjInRa5QdNcHcwKIcbSnAseG4hqEwgbmNDPO+MIKB4+pYoGQSkR9WaavcfrYw+BsyblcPKdQ6LKxcT+u3/f3C3q1oGTbROqsS1u8ymeV+ncY/CVMHighlK2RmNcLY5NI2ZXmUWcCV+3jh9sSY/twv/U4+tn3s4wCAJS3Q3vwFX53bnmg+BAD41r/9d/Oxf/rP/z4AoD1Oa3JUF+Z0RXHcSEGfivz2yPIudsoaGpMbJ0YDmmKH17aJRd7KXmu5N4213Vnsl3lsj9hHYrwPji/mtrN7dwAALl9+Ih+zn8VrWhU2cp1Ixviuu0pRjre8Ko37jBUSaUrkYmKVDHuu+ljaPucNfxkAsDpzR7k2x7q2MZcWvPq1bwQAjBQRtvLcVrRQnKSyyYJWiksK8zRiU7F4SSXFYfZMPMiiNetRng8y2U0w20BliU2BKpvNmS6H42nBWWLHaYUzxg6Hw+FwOBwOB/yLscPhcDgcDofDAeAGUylCCOcA/AiANyBJr/4ugD8G8H8BuBvAxwB8bYzx4pN08aTY0mT06PgoH9swLG1h8+OjEuZc55D1yPeXNIArFLKNEhWNbLdgzl5XGuuWnrqSSjDRULhmmsQwluDvSNHS1LM3EbvRihVBKtjlCD/DzYOU6jqmH+zjB/SFlYp8S/6MWYhFs1Xb29Jjdb0pYeGtCfP68vunZrWv8xREhVBCzAOFTccMLdddaVuBPrjrkjZgIe7dxcnUiF2G2ZtK1mnDioIMoZn/M1AEZpvtvAodAAxMm9D0islSLyjMq7Xgn91Vzm33fEk3+H9+4V0AgKv3vy8fe9krXgkAeOUXfTEA4Lu++dtz24/+y38JAHj7L/3jMo8+7YXjlmLQcPIxWlNo18iadLupstzBYakYZyk8K4rvFqsi5LtKv2Ot+NdwHwamDcRY0leWXUqhuHLpMQDAzplSMe/w6PH0Qqr67a/S+fEg9XG8vpLbXvSSJB78G1/6qnzs7lXaF8cbe57KPbJ0mungEgdT0kXe+4H3AgD+7Gu/uIx1mdbirpfcnebflOf8hXffBQB49AqrB4rAsLdnS9IrAtc/e5FLKlOo0vnTVI4N3CsjKyOaPzEABO6nTWViW6mwF28N8d3N/Nx2OJ4MnjrheLbgRhnjHwbw72KMrwHwZgAfBPC9AN4eY3wVgLfz3w6Hw+E4HfDPbYfD4XgSPG3GOIRwFsCfBfCfAUCMcQtgG0L4GgBfztN+DMA7AHzPp9u/WZMNQ2HEtkZQ8dhaWEUYm8y/B1tljNOxRV0YUCMyK1qfHQjD3DXp94IyzI1VxKJzlPZ1cJUsHplE/V1sDFQtAjgr5LWIxjgWVtX4qYaqvSNls/iLeyFMbqD4aq9J1PSZqKLDdKGjhVTpY1W+jqzaJBXKjo11Jsu52CtCsMbEVPJTKpBVa3l+XxcrsMCttduWY0NI49iuDzhvEVXxpXGDys2Ng1Uhk/PJAB6t+Q7pazC7riGxkB9/X2FoH/6jXwUA7JwrFRW//4d+II3nMAnNvvW7vzu3HTz8SQDAohH7OFZK66rEuI5bEWJO6Zr7+2R+xTrs8DAxsra/ACDSGrBhhcT1YamiZ6vxile9NB+5+6Wpety735lY2IOrRUw3DmmegWMdhO28+0UvSf2Ljdp0RKb4MDHTf+87//vc1lxM/d8+fCwfW5PNH4YkkBzH0v/EZ3FaJSb4SJSSn/vnvjK9kGfGnu977n0/AOCvfeGX57ZIpr/fTev02FEhLmtuwF7YaouSHHE4S/25z0iNmgeZMNIiPCq83SWLvOJ1RO+ZxbXPZubrZn9uOxyKZ/Oz4nju4kYY45cBeBTAPwshvCeE8CMhhF0Ad8YYH+I5nwRw5/XeHEJ4awjhXSGEd93AGBwOh8PxqeNpf277Z7bD4Xgu4EZyjBsAnwfg22OM7wwh/DCuCb/FGGPQigXztrcBeBsAXO+cifmCW2Hjjum7tukTM7YvRTmMTRyYe9gL5big7dNiUdi7s3uJyVyQra2kuMEYaYsmhRhuv/N2AMCZ3cQE9nKBh55ILN/HH0x5nP2mWKaNtHYySzcAuHAhMbE7beqzF7uow6uJcVw0tKaT3MiptmIepQDFGFNfK9q21VLgIzCfdH+n5K2GKd3ywNzUoSrnXz5I6zqR5RayGpvR8oPLeMzqzuje7SZKW5pTpYw3meVA1rqqC+tXDantLIuAqLXelcOU1zyJnVhgrumS7Hkjhl8PP5Duw2tekljS3/79n8ltO89LTPE//6c/no/9j//bPwMAPPLRewEA8eql3NaRJmzFmmxL9r8/TgzwGcnlPV4P/JuY+EtPPJTbmjbN6fyZ2/OxkbZjI4tlrC6UPfpPfuBHAQCLRdmH//uP/FR6MaU998pXvzK3bY5oP7ZJfT3+RMkZfvd7fhcAcHX7eD72BRz2V70q2ai1H/xXpS+y2o8K17oKaX+0VVrzYVPygiNDMCP3F85/Tm4L9mxV5ePmw59Ia/1lr/tcAMC2kn3CiJDt1Uk+pWwPWO4wAKxpEWe55VvNXbfnryrP60WzFeQl94TBt1IigfnErTxPksb+bMbT/tz+kz6zHQ6DM8WOZzNuhDG+H8D9McZ38t//N9IH7sMhhOcDAP8+cmNDdDgcDsczBP/cdjgcjqfA0/5iHGP8JIBPhBCMGvoKAB8A8LMAvpHHvhHAz1zn7Q6Hw+H4DMM/tx0Oh+OpcaOV774dwI+H5Pl1L4C/g/Rl+ydDCN8E4D4AX/t0Op5oYXZVxHemhjvXpmGf3ZHKWxQaPbpm6FtCsy2rWe3sFiHYHtMRQrZDk6Xgz4Xz50uI/M7zKdx8B/sYJf1hwTSGY6Z9XLpcgq4TUwJ29kqIvKpS+sOWgqWNpCCYHVxNYVMjKSEVrdkWe0XE1PHaHVMigsiFFqt0nb1lSaXoKTJcX6WN1VAuYCK3I4am2+Oy9h3TVoamXDsy3Jzt1ET4t6SocaiKvdsOBWZNncbViYjwwtk0/itXeb5EahumXqy3pa+rh8mSbGLWysVHS9vBpfsAAL/x2IcBAG/4wj+V2174os8HAPxX3/8P8rHjqym9oKXYbWjK/Vub/Zik4ayYmhM5xicultSLg6P0+nm3Pw8AsCv3/fz5dOzKUUlBWO0k8eSb3/w6AMDf+5Zvy21WgVGtyd7whlcDAB77RJrb1cslXWJznNb//R/8bQDAq1/24tz2NW88DwB400telI91vEeHh2kRF1W53xd4ry4dlP4Xe/scTtpjsZY9zb6wuhsA8KLXlzU/e3ea2+Gm3KOBAsydjs+CVt1j+tCGKRi1VLk7x/VcxnJt0wBeOk7zuCqiQNtG2215XiOr4e2c6diniAIPmLZzyOdDrBTnstpnNW7a57bD4XA823FDX4xjjO8F8AXXafqKG+nX4XA4HDcH/rntcDgcT44bZYxvGiayPpP4JXVkfvfIMjXCDKFObM6FRWq7Kk2m+enaMt26SUxQQ9unjTBDFQV5i1VhDm+/kBjm/YnHgrBfO4nhenCHRTC2heGaKNJbqHgrFwLhtYcyyYGsVEPPqefvl2yXC3ekogn7dRFvneWaBNqExVBYv71zyTqrlqIRPdnpR7s0j4O+iMN6ziMsU9uxWNhNR4mNW67K3Fqu4dndNO9z3bncFilC0yIQ5oplup1dYZhXZGTP3p7W+UgCBbWteSU3tUvs6yMPJOb4p97xC7nphc9PbS97eSpO8ejFcp37H/h1AMBeLBZuVkxmOyTbMr1Xk7HDwhZevJgs0partF63nSsC/r0d7s02sat1Vezwjo7JWg4iztyma/Us7LLZlDk2C7L7x1LYpE/3+dwqrdcH3v+R3HaeDOhfe9MLAQB/+vVln4Cs63JZip0cUSC4rFvOX/bhkNrOnT2Tjz3+6MMAgNVeiqSs12UeFQWJbftAOueOrynXbtNYF7E8fxcvU6jK/aE5XQMZ4y3XqZHCGp0JOCWi0FIWd4ZFay4elHFFRmDu3FnmY3vn0x67cCE9T+f3y5qABXA+9sDHAACXHyyMOVxv5nA8KVxw5wgh/MknPQvgJaEdDofD4XA4HA6cZsaYJR4qKfUw8RepFTCItZQ6ZqGEBWnJsNBKFOn8RVt+zdzG9rNkp4apUJSXyKZeWJUiEKsxHdtn4Y2tFBdZkfncb1kYZFXYqWlBOy4tEEGmeyAju1qU8zsyzBeWidU6vyi36DzL6IZabNGY72mFD3YWpSjH/m56HYUBvUqLtV0yoS957ctz22v27uAY0riM1QOAhx5mTq/Yu53fS0z0HbQra4IUF1km9nXYFsaUjmyoaCNXMr6BhjnbRgrvt5KnzdzisS55ohMtuf7xL/4SAOAtX/yFua0lc/2Bj94DAPiu/+Lrc9vb/11ijO/7ZMkLrsmy92QmN+syj8ssr/wCWr8BwGrB+9Cl+3B0UKIHS9r5HV5Ndmpn9sssL12iFd9uyY+98kRin3/vD1NBjVf8+nty22/+3m8CAF7zylfkY+/7vd8HAHz+ixPL+U1/6bW57badNG7Lrw9SVMa2zKYvY634XAwsqdzKmvcslLPWEuCLtGc2R7Srq8Ui7yDd01d/4V9K5555QW4bmD/8KBlnAHj/H6R5rpjLLI8yJlrEHbHM9JmmPAMtn9dKrBSNUG74GbArz8yKp+0uy7HnMfpz+21p33aNPH+L1Pa8c2kPPf78sk9+652/AWDOijhL5niuw58Bx60GZ4wdDofD4XA4HA74F2OHw+FwOBwOhwPAKU6lCAzPzMM0ZguW/o5BqryxelVkGLauRWjHOO2yLX2tWAlrbz+dF3u1eEr9diK2iRRmDV3q63gs9lIHDKV3fQonn6lL+odZbh3KNI4pOGqZ9tFLda2uTv3uL9Kxc4vStrdKnXR7JV1ivU3j6TdXOf8SPt9sWMFvlEpgtHM7t5/mu9orIe+a6RXLlqkhIjjrthTThdLXmf0Uit7l+na1hOKblFLQ3V4EeSva31V1Cl33xyVMvaYtWFxbOkDpa9uneYwlqo9/8nPvBgD8hbf8mXT+qlQDfP/HfhUA8J1v/RYAwL/5+V/ObZceTuH8h+7/eD4WaIc20K7t5S8vVduWu6nfuippA1fWFwEAe3Wa26YvYq86ptSJDdM/jseSNnGwTe8bgoi9KPpsKBL7F//Lf5dbuiEJBM/dW8ST/9Eb0v3aX6W1bOUZqJius6HtXtkJALhfG7E+MwuztmG1QbHu64f0XAxiS3j1iBaKLEXXvaDYwb2MNnIvfs2X8P0lHWWzTakqv/Ibv1TGykttaLEWahFtmAiQaT8bEV12fB6qUCzWbAkqpjQFsZ3bW6b7ce5csV68/bYkltzfTcd6Ed4u+HwjpD2625Vnba9Le8FDxw6HPweOgltFdGdwxtjhcDgcDofD4cApZowrs2Wq9WA6dkAG8XxbWDwT4FitjKoROycT5MmxjnZXS7Kk6ErblgK75aL0f5lWW8ZsHh0WUdkltm042H7Ugh2pr1id/HU9kRHr2vL75HlnEkP1kjPp1pw/J0VJLiSmq+/LbVs/kVjIekjXXm/Lgm3I9i0W5dom+FtTjbVciOUWrGCHHZEiGybomgqrGDaJmQtLrmErlnc8pkzuIiSGzoSC3UJ+ZVLw1x9dtgPlfRSF/dZHi8Xa574hsbrbntZel/8ot33e678cAPD//uIvAgA+/uEP57aJe0dFcbff/lIAwEMP3gsAePzxy7lthxZgV6TQxR6LTGxYqKMVsdfhxVRJt6Go7HWvf3Vu+7bv+D8BAB97qMzjbT/4jwAABx/+NwCAr3z93bntNa9IhTEqEcXtdenaFQvTSGAEw8YKYlCcKlGNjsesOAcAdCwAM9EOb5pK4ZGJlO4wlGcAbRIdvuz1bwYA3PmGYntb7SWLvJ7RgKYqA/ujD6WCI+FSEXO+4Cwt3FhMRZnvLffdcsnxdaWvK8fpuVuL4DFQzHq4TmO2AiEA0HOv9VIo5+ohIykNIxHV/8/emwZbdl3nYeuMd7733TcPPWNuzCAIzpNIiqQoUZasMaZEK1YUqzxUUokrTlUqcimpSlyRK3YcW4wcuiRFtChZI0VSFESQ4ggQBEBiBrrR0+vuN493OvM5+bHWPms9NEgB3QD50L2+KlY/nH3uPns6j+9+6/vW4vtdY66N8DlByOxzlolOFAqFQnFVQhljhUKhUCgUCoUC9A9jhUKhUCgUCoUCAPaxlMLkHL5lnEPxHbpmioMtxxyKN14fmyQRtTqbnrr093/F5lC/TzKMnPKW+iKCo7wNAAAgAElEQVSRapukDXkmpQT4rJDCsELNAN1ZzHE7RiHd85sbZdvWFprichEqLj1O9Mj5cc6jeriLhq6JJj67Ocb5c6s+5c/t8LisBs5jcWUJAACGAYd7a2To6olctFt9DJc7FOq2XSERqJEpjIxQ28N+2bZDoetcGC4yCnlbxjBYE4YokmX0RSgayqp8ZHbLuC2KsQ/PwX1zhUbgudMobVhf4/E8exHvX155EAAAjs7eULZ1erj+zzz9GM2Lz9D0POYEXl09X167eAHzHXe7WAltU+xfu3UA5ypyArcauEc3XI/3//RP/5Oy7dMPYD7ihx7+IwAAOPHk42Xbf/V37gEAgANjLGe49zCOZ/KH34rPE/KgBuXTBmFqLKy9l7JUrK/J801bJNRBYJGZMRPVIgcjMj/S2fZdNvnt0hqu52w+e/8voOwj93Gfrdql719R4Dqtr7O5MVp7CgAAbpwUshrKA141kikh24EGylxiqkCZWvw5j+QfZ3oXy2vBCNczJ+lQKkyzPhn5rBFLhlLAczSgQdvC4OqThMSKTSVC/p0Rk2lW8xgrrlXoeVcYXG2GOwlljBUKhUKhUCgUCtjHjLFPhpijwjg2R4adjCrFzUc8/Bd6yAjlHrZ1q8xejjeRVZOscGrh/QXgfTGTeJCba6FgmRI0TAVUxcttMJNWkHkJyBBVEWahnJ4ZJcw8GdbPpIayLWYJc2IA4wyvhTF/zvOR6WqIlGnTdTLYLaCxbZAdLttsMqZtrq+U19Z2kMkbDIa0Dltl2y6l1UrJYDfcZTY5CnAc0n8U57hoFQcZvk6fzV51Sp/XF96trQLXtSDKPMqZyY4DZIXrPvb1wP0PlW3PPHcGAABCwaY6Dvb1/ne8DQAAzp3iOT7z/MMAAHDkEBrfNleXy7aVpecBAKDZYBZylJkIAe73zES7bBvvzOLnNi/wPKi/jW1kLb/1q79QtvX7eN+BSRzr0ZnJsm3hbmSHZ7qcrm1qDFnagIyMhahqGNJBaYrqjzX6Lrs9xLX2xfq6YOhkOh+C3Emor1hsoEfpx0YhnqskZkZ+bA7HOn/zB8prVsX0hR3bsTCn9jANnlfgNUcwxrd0F3DMBZvvihGeuzjGCAafcgCbzr55JQPgcTkeDmJmslte27Cw380tnFso2H1jNu3FvBgNSnEIdL5z4Jc/o98LdaryVxMmwhEZ/5Q1U1wr0LOuuBahjLFCoVAoFAqFQgH7mDG2KD2YazPD5VJOthoVZAhE6qkukbaJhczuTVNcWGKaGCvLFanMcmToDCM7ipntDKk4g5VzAQqSF4Kpj5CLohxxhuOw8+KSNps0s37OnJhJ02bSTAUB60S3iL2KiL1seutlm+Uhu+i6gkUukHGr2Thft2AmOyYNr+0ye54SEx9YtPURr2FviAzaMEhoDNxm9NZ5xs+uUQ6sCu1RI5Apt0inLFjCxRyZ1moVGcGGYCjHidH700eRaTyzxkz2Wh8ZwKbDDP56n4plDJFNnmgc4XHVkHXeWj8HAACdNq9JrYIp7za2uX+j13WJrY0Dfi3+81/+Ls57xKnMDhw6BgAACbGd803+fjkxMwUAAMcOzeF/d3jtW23aP5/v75EG1vNN2jJRjMWkEbN4PH06pxals8tD3qOEUgMGpIv1K6xdT6ncRyI0yWZ7LaKC8+ljZRt0MP3azLHbyksB7b1DGvTd3ho/O8TxDLYwNZ67w20h6cV3I17DbIjjSIgpj3OhVysomkEp7xyPU+tZVIjHF/dPTSIr73fwfR2MOB1eRGe5R+cFAGCHUgI6NP9M8NUH57CAyhzp+WNZMIfCSlJZp3ya4mqDssSKax3KGCsUCoVCoVAoFKB/GCsUCoVCoVAoFACwj6UUGckSdmL+270WY8jeIYnAVsqh+10Kc+aAMojdXW6bbGNarVaT01HVbPw5IcNZOxVSCuo/qHIf/T6G/Z0eyg2CiEPxXg1DsRGgRKBIOTRrMkGFIjoVRvisIjIyEX52bPLA7ZDBaZMNcAcOoiRgoc3B3Jqp6kcV0eKU7zfyh5EwI/kkYxijgHCRcyg+pNi6kYZEyaVSiliYCANKaWXm6It0bRWa2raQIEBO1fwodV3H57D+//XFRwEAoG+h1CEc8Jp4QKbAgvs/vmDMVziuMGDznUN6lzJlXCzMWCQz+NZjT5bXNvu4Zi1aG6fGoXuHxjo2faC81h2jZ2doXnM9XqcjU2iCnJ6dAACAiRqf37pJh5fzeIxUyKU1l+Y7g6EwgZoiexmlwSuERCcmqUNOEoyKx1IKU85QymoKn87A+BtwrjNcpa8zhfKEjeVz5bXaJMoMYpIa5eKdOX3mCQAASLY2aJxszLMtlEbs7nBFwR5VwQtJjpMBv2tzTVzDWZJz2C1OvZhmKJOYzHlu4x2UEXlVlK+AqODnZCih6IvUgyeWcD0fP43XUp/7n6Yz4NN74RX8HPY0qphCcXVAZROKV4qrOU2bgTLGCoVCoVAoFAoF7GPGOCSTzXN9Tum1HhETRrTZIGNWqk8mslGC9xcJf25IacEOTnGxjIkGslIupQBzbGbS6mSYq1U5pVfDRrYvqCNbGAnWbzgisx6lc+o6zKRVPWI7RcqtyDIGO/y2nhXcVxHgtYSYWUE+w/kA2a9EFPhotnDcbiOl+XBfOTFbOzvMImcjMtYlIf3LbGdARq6Q/g1kDi3DaIprplDJ0jrOf1hlZtMhxi0TbK1JoZdWcFx/+G02SZ0f4d5WHTRQ5QmzydUKts10+HtcTINzbZzPWJNZv2dPIRv5zBksrmFbvLdVov08waYePngQAADaTTRcJSJFXmwKj4ivkFGAjGS9SWvv8ms03sBz0iQCtBDP9onJlkU5zD6YohmSaR0McH0cYQ5zAKMGeW4MknwWCipsYRFzHPSZJe0PMMKR8NGExhhGUioVTGFXX+WUdNkGMac3fbi8FoQ4nl4P/1088XTZtriIJkio4Vo4HrMKAUUN4iGfD7uB+3XsEL6HVpPX8PgMpoqbGEfWul0R5jtjcBVREDvH98636R2wuc0hRmzX5fFUbXo2sfq7I2arRzu4QMMB7lFvyAZc38Y1kYSJEm6K1yOUKVa8UlwLTLGBMsYKhUKhUCgUCgXoH8YKhUKhUCgUCgUA7GMpRU6hnu0Rh3w2BhiypzSqkGRM7ReU/9VIEJaW2Ojz3Gk0EB2aer68dmQa881OttHg02xwtTOfql7ZouqVbeOzPKog5oucyC2qgheQcSdpszwhzeo0LpFvlsx9JkKeinzBCeW1jQP8N4lZbgAUNrd3eE162yRZsM/jOrgc+u1TtzsifB6nuE5hgRdHETeOAgxBZ1QdzbOFgYr+DVNR+o6GQQoXiMR+QIR9+SKkXuR44+997TsAANA0ZikAyEPcr6LaonnzPOapUlwgjHwPfRtlEsMA5QKew1KKegX3o9vGUPyRhdmyrd1EeUytwdXn5sbx5+vm8Qw89uzpsm1zF59Zdfk7ZEj6ljA0kgg+CyYnbkwhfycUkp4Cf26KqokBSUKcgqogivy8HhnrsoylAQOSEFQrONZGm2UGRUJmywif0x/yekVkcuvOX19e68wfwTHsYtW63ojH2rntvdgmZCImV/HGKTRKDoYbZRvQPhuFUVv4/u49jmOdnp7mvlLa5xGuRW2MJSdTZLqb7uA7aol85TlJpBxHVJ6kPMw2HUhbHEOnQGOexa83NFKU2tghvZsZV9E73cO2nIyx0pz6zW/h/RqFVryeoLIJheKVQRljhUKhUCgUCoUC9jFjbJjToTBhATGZKTFo6R7jEdJEFjFvscUsXm8bry2eXy2vPeY8AwAAk2T6GauJ9E+UHmpyjFnFVg1NQq0GpnlrtZmCqpIZ0KfqZZWcv2/khRmzrHxX7LmWJKK61gh/diI0zGWCJQ0p1ViYMWvbS5FpCwD/DXNmmEdk5AoEkxvSzwkxiKLQGsR0zTZrKaoOlixczmtuKvwV9P0qFexamuJ93376ZHnNIdNTjcxUachV8eoeMrkWGbzWV5bKthdOI5vcJQYRAKDVQuPU3Lyp1sZjnewiA/iuNx8FAIBbrmeWNKfUeLas4EdscOEhCzkzO1O2QYqM9MUVNjBubOA5OruCrHaWiRRoxJxaYP7lvU1C/Hk35D1q1nHepshdWvA8AmP8c5i5d4iSjYkVzkXbaEjXIjSj1WduKdtmjn4EAAB8SoUGABBewJR1u3Supu76ibJtQKn1oi1OS7hx6hEAAKg5ON9bFw7zvI/h/T1i8A+NsdHu1nmc3NgYP3sE+L5d6OM7VnPHy7ZmBdfEd/CcWBUR8ohMWjt+v1MgxpiqPro+M9MFVZmsFvwO1BMco13F9coyfglub+K5Cnbw/Fkuv+cTxGRrsjbFfoWyw4pXE9eS4U5CGWOFQqFQKBQKhQL2MWNsvqjkQtKaGf0tpdOKcmaSTGoy2+h2U/7mbLjB2OYCHz0qILG4hqxfErBesp5gWrRmhdm+GSrUMDdORTbmxsq2iSlkmdotkwJOFCSgYcQxf/OKaFIZsbeRYC9HIRWlCHB8Jg0dAEBMBURiUehi1+hdSbccFszUWaQRdprMhvsObvl4Fcc44XFKuvUQ2emVETKOliAfPGLiA0ukDrMp3RylmLu4wrrggjTD05OT5bVBREz5wBRJGZZthvyPIpzH9DyzkXOkH87Eftd9nFunhXObGeOjfN99xwEA4OhhTMNWEQUcTHGGRKSR81NKJ+ZgXw1RCMalNH6dSWa3zy3jnDrjyByvrSyXbcMespFhhvvQj3mOE11kH9tjvCZGUpzTvHcGnGKt2yVNK/D4g4hYeqMDHzKTHQbIgHYXbgIAgNk3cqq1vIJnc/3kl8trF09jUY7mzcgmX9ziOd5wE+qyZxvM0i837gIAgJVl1LM3xbpWSNc9TnnqZuvrZdtYnVK4ifBEldjgaVrrIBTMBEUekhzZahOZAADwyGDg2BPltcLCs7Ad4BpWgHXXVRfHmAJHnjKKVNRMv5koCDKitHkUBar7/K4xeaKsnOIHB2WFFa81rlWm2EAZY4VCoVAoFAqFAvQPY4VCoVAoFAqFAgD2sZSiSma42TkOmQ5JXpCYymEcYYWUwpsppZwahBx2D3bx50IYxybaaNCarGN4e3vIqaqoOBzYouLY+Q0M654+i6ac7jpLL6baGP7ujGNYuFbjUHyYYmeNLhuPal0MU59cXMP5cCQXLDIeFT6OyxOl5uY87COx2HAVUUqvlNbCE+Hq627HSn/33XC8vDbexpD32hqO//EnTvGzE+zEd0z4WHxvcnDtqi7Pzc5xbzYGiwAA0G5w28jC/VtZWyyvGV+ZqRRn2RyKN3m+2i2UGRSiGqAJXU9VObwzN47revQoSi4OHr2ubOuO496mlCKvt8vyBJvmFAcs++hMouSiWkcDWC7MkzFtTuGzdCaKUSYwM4+fy0ZsULNIkmPO6liTpSqmAl8asLwiKqvg4T422nxOTKG4IuP7jfPLIinFUKTzm7nzgwAA4E/guPpCojM89xQAADz3nW/wvG/E+wc03/fexJUhxzuUSs/n8afkSRxEZDrcZdkOkLTFJwOj67EEI0hojMLMGdCBHVApvlSkZUyB+qdx9S0+C9XqGP3L6RiDHMfYS/BzE6k4V1ThsBCV8vo9vK9Ha14V71OaYr9pjnPbiHgNTRVHDWQrXmuoXELx/ca1Lp+QUMZYoVAoFAqFQqGA/cwYk4Ftps1GpbRBBQ/ov9t1TqXUrBEbRwxtmjMNO9FApurEOU7XdgularpzAtnF9apYiu48/lsw8/SZh9Co9PTTTwMAQKXO3ymCIfZ/8EZkUBdmFsq2U2vILt583cHy2mwHWc6ojizew49ySrOFiSN4Tx3ZVydc4TkGyGI1BCMd0bwLhwx9TH7B4XE0YU21mHWf9Cm1XAfX6UyXU9KdXkXTYX8bDV31MWb98hBZuY2tc+U1v4JM5tLFswDABRYAALa3cNySPY+JHfXJtNUS+zekggp5jvsyywQt3HAQmVwvY1bfpfxxfgUZwY11No5tbSEjWKUiLCPJ0PaQ0bVr/GxrHRnNikeGq7F5fjhRtGnK5q2UGPXVDeyrH/FZcIl1ziI8f47P87eokMvmOrPVrTFiNDMca7/PrKrJOJgJI2lCbK3bxHM7ftfPlm0hHeFhD1nPaJvnvbWBkQ5v9s18f4D7/RP33IHzavGzBwWy7G7A5s8KMfAzNXwnI4+jJj6lBqxUcL5j3tGyLSpwzIOAWd7IRmZ5FJE5LuSxJjt4dhxile1pPr9JDdciF6kaRzSPjEyzlSa/a7mDe7O5wu/YzgpGMaoujqHe5sNWrTg0ZrzWt5lpHgljq0LxakHZYYVif0EZY4VCoVAoFAqFAvYxYxxT0YvtAWsoK6RNdejfJGUGxzCOBq0Wl4xtkv7x1ln+Zm6ye1kkoZzsMjtaHUOGyrZZX/mTH0KGcf46LBaRXGD2K3NQY/qOg8jizY6zVnP1BmSg4jpTudMdZBVjKiG9GzGDOE0s4SCmwiAVThflEksdiHRwN8/iuN5wO7LDF3q8JucXsd+tgSiGkOFntyit2E6f7w9yZC9rLWT71i+eKducGjJ6G2s81nB0AscaYR81j49TvYNa2SxkxrHTQRYuCvH+3Y2zZdvReXx2m0ocNyo8xzVi+wqLdeNDSq3WHuA+THa57PPGNo7RdkhDWuO1b9ZQO1tN+HzkVEZ8g0Trbsh7e8NRFNa2Il7D5XVcl+UtjEBMjHFp67E69ptHeCZGmxfLtoRSjRWifPXmJrLzvkvpBl1mxUN6PXPBxHcpjV3RRFb7wsXvlG21Jp67R5/Ba++8656y7S763N23st48dZEFt6kIiVvwOgXWkO7h8dSbOO6Y0qFVRzxvj4q2eFRGvT/iNHJZQtq1Ot/fINY993AMg0CkZOviPIZDXMOuxe9h08VzZYuCHYmN52JuBj9X9zhdW0Bp8IaW+F1h4RhjB89mUxSmsUMq5U331KocUTEFRBSKVwplhRX7FaotvhTKGCsUCoVCoVAoFKB/GCsUCoVCoVAoFACwj6UUxkD1xAsvlNc8F8Ov9TqGXetVDkk36g26B/97IhKmryp+bjtkI808yRIiG0PyYxkb8xYoVVguTGsTBRqOru9i2zeW1sq2JrmkQgfbgkKYmGIM0xZdrj5nVbDfo+N430cO31C2tfsocVil1G+tQ7eXbYWLn3MzkX6sllNfaDi6cZKf/ef9JwEA4OTieV6LGMPOf/1tNBE6W5yOKqFKYDmVY1tZZqNdOEJ5QZbw/Z0OhpnnJg/g+DJe34Sq1KUZS2HuuAVD6R/7sV8GAIB+wGMtaB63k3FxGzj0vUH7NtcWqft6eO2pE88AAMD5RX5OZwp/ftM8ymPGO2yuWoxx7Z5eEen5qP+MJB6OyAO4PUQTXWuS06jdcDNKTb72ia8DAMDOATZ6LkyjxCHeRSPY2XOcrm6ihet1+123lteqLdy3wkEZw/oS71WFZCW7Qzam9ei8tmI8vwf9mbINyGj2znuwQt1NU/wOHJlGyU014XMb0tk0VSOtgOdhd/BFargsUYkofVpA36fDnENwFarsGKS4vlWR6rCwcT3HfTY8OjVa4z4Z80TauTa9ywePoTSiUu3ymDOUaIxWWe7SGcN5dhq4vp6Q4dgu3neww5IkL6X+YjKuConE0uA8jRnHOsxYvlOhFJIgI48aIVd8D6iEQrFfoRKK7w5ljBUKhUKhUCgUCrhCxtiyrP8WAH4ZkDd5EgB+CQDmAOBTADABAI8CwC8Ue6s1vCxsD5B5OvvC2fKaYyPD5ZEhrVlhpsdy8W/8GrHD9SobdjxKwVQVRrbtcTLYFcjsjcdLZdvRMfysu8CGvEr7ZgAAWNxBVm0g2OekQFbp1Aayilsxpw5bo0Ijh8d5bpaD7Nh2gsagGEQ6sSYVKqF5gM0s22wX51vxmUEbUIqqlApkxILCOrOIbNmffeqPy2utSeyvXUOmcnmH08EVQ1zzjc1lAACo1pnlbreQdfWrzJzaFo01JhOXtV62vfttbwMAgM4BHuu73nwb9uVN43PO85rbNrK1/RjH3JlgI9jMNLL1acCmqsxHRjIiE9Z6zKnDGhbu0aiPzKEvSJsiQWa6YTOjebiJr0Hawn2fFUVMzmfY16JgcjvEbv/qL34UAACeXL7A/Y+wbTfCPV7eYRY2n8Tz1Jx/S3ltchLXtdLAdU1t/hb/M++6E/s4y8++uIJrvEaEel8YC7v0431UVKTZ5O+9g92zAACwvc1s+IDYLCKfYXrhAPcFh2lCbD4bZnjWdqmgyfIqR1lG1EnNw39vn2EDao3GWIjUZ40M+x2l2NZu87t8YB7H0TLva8qRhd0U5zYCfraX42c9MszJtIHGsAt8bKEdY7RgGOD5jkWBj0efw7M/WEWm/+Cd15dtlk3jeZ2TgK/l7+1rGcoOKxRXBy6bMbYsawEA/ikA3FsUxW2Adeh+DgD+JQD8n0VRXA8A2wDwD16NgSoUCoXiyqC/txUKheJ740qlFC4A1CzLcgGgDgDLAPBDAPBH1P47APB3rvAZCoVCoXj1oL+3FQqF4rvgsqUURVFctCzrNwBgEQACALgfMAS3UxSFSQx6AQAWvksX3xMZmcQ21jkPrONhGNhIKHYtzqkLLobGaz5JKDwOGZuqXBPCTDfaJklEjDFpO2Gz14lxDIm5Sxwa89vYbiVmyWQeVXzWyQ2UAVR2uS/XwT6Om9A0ALgB9jHooeTC8tkI5q9RKD7Gue1WzpZtRQ0lCAsuzyMf4bz/+8/8AQAAfP0v/rpsu34e5R/jM9eV17a3cT1XLzxCHfAcXQpdHzh8BMdis3QhJtNaf8gykY/9yBsBAOCOg2hGe0ONI6+5h3v0AKeIBSdGWYVH/do+m6RmeyRpaWGI3K/xmN0qShBS2CqvPbOC4wgcXLt2myUnwS6ened3KJfuDks2NgNsm22xqWySwvhdko5kNhuujnl4rReyNGeWlr/TwP2YqXCltd//6qdosvi59/zQj5RtJ88+T3PjvlZHVIHwiYcAAOAD99xdtvVTMtZ1WY5xegVlN7ccRcPmjYdZstCmCo8+Hf0iZUObHeDPvR2WnKxexDVfDPAsJx5LjcwKeB7nIw4jPDtzAZ5Nae5b2yB5RYjnMRiwOc7xUApTS/naqILPbFrYR52XBOoZVbFM8Hv7YMiyibV1HPPSBTYRRmN4yJIUP+e3eR4+VT8sXF6nagfX1U5wPFbMvytuIKnRjoNn5h7hbfxCmUdb/toUB/x1gNf69/a1ApVNKF6PUMPdy8OVSCm6APDjAHAUAOYBoAEAH3wFn/8Vy7IesSzrkcsdg0KhUChePq7k97b+zlYoFNcCrsR89z4AOFMUxToAgGVZfwIAbwOAMcuyXGIfDgDAxZf6cFEUvwUAv0WfveTr9yhEZqzX3y6v+cQUm7sdh5ke8r+BFePnYtmjjf8xElXellyqLJdim++zAaefYGeOz4y0ZaNJzae0WtU6m5JcMoDVqZKd4/D3jZhMXtUGX1taQPbuzDIyYUecW8q2DR+vndkkNnnIY9i6gOzo//bkp8tr2TL25VeRvZyY4PRu5xfRFNbrs8Gu20YX4NQEphUDm8dlEwsSBMgSfvhDzLL9w5/7ZwAAMBjwOn3p5LP4A21I0BBV+jJkEA8E/A11o4fGMWNc7Ik0ZMfvvA9/IIY2GjG76Bb4sxfx/be1cNzDA2jUaqbMZB+YQEr3QoTrdWqNmelb7kMK8F23MDMbUJW67bNY0e6OiqiEVkN2+zt9XqczW3g+2g6u0+SR+bKt8QiOPyQmf3WVqwe+4c43AwBAHjEj/fuf/DgAAPz4h38CPz/BFOWffOlPcS0E83vHzfcCAMDCYXST1RqC1SfTYUTDr7XYPOrUkZmtFjy367dwfdZDNE/2+nzWZuo47uaI3xmb1snzcfxewuZMlyo1RsTyroo5rq9gX7ZMydbAc9ihF7XV5nf54hCfGVM0INs6y3Ps4TMPdNhNt3D9EZxvB6MAWcZ9BUNkyKses/o1Sp24liODn5zjlJDX1fEMNw6iUXTqGFcPtPLP0w9s3HwdGvEu+/f23/Y7+/UIZX5fG7wUM/ly1vp7MZq6V4rvF65EY7wIAG+2LKtu4Wl+LwA8AwBfAoCfons+BgB/fmVDVCgUCsWrBP29rVAoFN8DV6Ix/qZlWX8EAI8BCu2+DcgmfBYAPmVZ1v9K1z5xWf1nyGylIlWTTTriUYhMku8yQ2n7OJXEwfsFpwMZUWiRSOnlOzR126QcY/YrCpCZbIhCAUGKDFiQ5Xs/D5w+ruVQerAmCyazDPvf2WSt5ngHC2fUGsjiBZPM4vVGyKZ+5ynUOK6vPFW2ddv4TLfBrOLSDjKlg9Wv4djTiOdI4+9OzpXXOk3U+faIia46zOy96013AADAO9/9dgAAuLnLbGSxdRoAAC4kfG1iGhnJx547CQAAa8ushR2ziV3MeV1XC2Sub7gHmdNjhzkV1uYI78vH8N9dwXLXtzFdWbvNDGhaR43t/BDPwlaV2eSdHj67SRGFW2+8sWy7bg6lk3WbGf+MUqTtWpiqa63KazJ3DJnlO1whgj17FgAAnn4GGfmdKo/1rjd+CAAAHn8U2cU4Z+0zWDjWd9zOmvK3/ca/AQCAsKBCM7OcMu0np/8xji9n1jZN8WS3E4ws5ENmO+0cz1HWwT3KbT6/PlGbWz6/GY/2kcFd6uHnqhFruB0Px9i0+DwNqKhGQbr5usfRgy1iitcGuOZ+wn29+zpk8Dsuj+ebLyAheTHBtXdXeI6tCUxhd6iFURAr4TXcTfEdHolz2Kc0fhZV97EdXt8m/RwBF8WBGNdgmqITYZN/x/iHsTiKTQVzEkfkeSOm+PVc3+O1/r29H6FM46uHK9GoXqm+Vdnk7w3VD796uKI8xkVR/BoA/NqLLp8GgPuupF+FQqFQvDbQ35th7ZAAACAASURBVNsKhULx3aGV7xQKhUKhUCgUCrhCxvi1BPnZwLL4b3cTLclyDGmGKacHqxrDm4//OjmHR02QJROOvMjGEHGFTHd5znKGiMLVuQjP5NRfHFKFtoTD7QV9druCodmJLof8bRuvbQ7YROhdxMlVyDiVJFz1a7CLkouJGoadxyYny7blZQwj909+o7yWpjiesS7eN15lmUVMbVnGYx0NMez/1je/CQAALBFuD6sYBv/GI98BAIAlhyuuzRTY16mxN5TXnOZxAAA4v4amumdFBbh2get7hDPLwXvfgtXwigKfuTNi+YM1hWsyneIH8pD3/dwijrk2x6aqiXlc16UUQ/JPXTxbtrXI8Fd4+O8BYQrc3sE+eiFLW3ZpT7dWMAXYDR4POqE1dGyWhDRJOpNRSsB+wHIDB/CcvP04mra+fYbXcPciygsePc0mtH70VwAAMNVBCcXRGksdJjpHAAAgTliyEEV4jp5ew2fOdvl83HIcpSk5Vd3bCU6Xbec3TwEAgLXFazh3GJ95/Q0otennvB9HuihVcT2WEpybw2QEE02UOAxEprJxeu9ay1gxbnogjHwuSiHSQgicPJRLvLCC86k4vL7TFVzDg7MozZmq8hlt+JgiMGrz/RWqehkAPtMOWDJVqaPJz/NZeuHQmY+oWl/oC5kMpRmsURq58wPeq63I7LOGbV8P0PD65UFD8vsDug8/OChjrFAoFAqFQqFQwD5mjB36m91zeYgFFaPIYqSqCpsZKJdYIzDFAQRjnJBxroiZOTWGq5zStXku95WTIc8WbHWNCgVk9G+a8f2FSQ+V4rgGI2aZWk1ssyL+9jfKcE6bW8hajjeY+R7vINu8NUCmcvfJR8Vz8L4JYdAy7FVgUlwJk9HKEhqz3vNBLjJRbyHDOEiwL9dh2i8McL5RiuPbjtn01HKRQettMBtnTz4GAADvuBfNbTd0fqhs++TnvwAAAEOX+z/fI6a4h+m7esL4N7uFLGR94iyuQ8Br/601NH3lCbO8PzqOLN9bpsm09qY3lW2ff/hJvD/Cz90jClFUCpz337zART9OnsM51UdoZOxeeJznbUyAE0fKa0Pa+nfchanxBgHv96iPrPPxWUzBN3kjF6L43J/dDwAAy0tsNFtZRZb9+EewGIsX8f3btNTNLpsnJ4ghzmnfbSbDYYciHVUyvk3YPO/eNLLJ1gIzpwcDfEc2+3g2ZyxhAg0xFZ9XHyuv3XU9miZHRMSlfU5FV+zgmZyrYONqn7N9RTvIIvdHvN/+DO73ZI5rfiBk1r05g3s6t4B9OhWepAc4/mHKc9sZISu/S8VFbJGSruai2TR1RKrGZWSp17bQNLqyeKpsO3ILMuT3TOA70KlyX1kPGemieD3b7xQKhrKSCsWlUMZYoVAoFAqFQqEA/cNYoVAoFAqFQqEAgH0spaD0v5CkwuFDUR9jqrBF5bs8ofzFFQqnigiRRdKLIBN90Y8J5SaNEl4K18EPZwnfH7togHKNBCPjEGpKuY0tymNc8zj0G0R4bWuLc912ahgqnp7CcHIY8feT8xcwvNuhSmWTs7Nl2+Y6hnKHohrggTkMrZ89hbKJm265qWx783s+jPfH3P9wC/ug6cBkZ7xsS2xcT9vC8Y2EaW+HjEdDUb2sS3lsiwDnu2rxuGIL12RpwDKR3Wcw9J6TUdK2WO4SuzjvY1MYyt4VEpreOkoDLqzyulbcJwAAYKpFJrweSwS2dsmElaJ569SFs2WbCzie4S4b2pYHGM4/UsG1fijltn/0xo/i8yrd8toXH/1LAAA4S2bI1S02uXXbKPHY8nCOMwffUrZ15lHisbPB6xSRvGd7G89T0+f1stf+BgAAzi1z1bbZ69DUN0GmzCRk6Ux/A+cdNTFX80bKz+nQgfdrR8prtTF89piD92U9Pu9bJNtxXDaSDi0056UkQagtscGu6KBcYptMdO9+z0fLNqDc4r0T3ywvVXq4l969KJc4scNyhie28YzdO4Zr7voi53SOeYmX11jSA2s4j2mqhidzn5/ZwTF6uyxH+dozX8X5nMZ53zPF5ypdxbO2U8PzngiDLwiDrmJ/Qg13Lw9Xm4RCzudqOQMvNY+rbd/2K5QxVigUCoVCoVAoYB8zxiZVWpayyc1yyhxuALDX9pJTKijzl740yKQW3lkIxscY65LEsL38HFOtDgRblLrIljWpWpY091WJ3W015gEAIAqYxfNtZL/mptkwl1jIIq9cQAbVFwaqVg0Nb8ubaA6bn2DG7o33YQqtQZ+/zzz+zMMAAFDr4udWN5lJ2x2g+cxvcR8OGZNaDWQ2/YJTYcW0vlaN0ryJ+fvEDteqnB7MIRPhV76FZrVKhVNoBUNcnyJnVt8uzDVk+JKI+98MkbUd9vDfyuR1ZduOhYzhSBi0Hn0MTWomjV4kGHwTPTAH5MGTXJEvInY/FBXdPnjHBwAAoJfiHi+t81k4cebbAADg1ZlFvngO2c0nt08AAMAg4v1emEFmcm0HjYI9mysXBsSU15ucnq8zQZUIyZz5rSfPlm3DRayQuFUsl9eu28Ixvvs9H6S+mMlOic0Phjhfz2fjXG+A4/ErbGD0TdXHBM9aq36kbKuMUcq6hM+HBfjzLkVg0m1ORTeW4NnfaSBDu51y6reCIiJPXDxZXpsmpvv6if8SAAC6dY5cvK9DZybH82Fb/Gsq93C+sxVe1z89jeNvNPCcBAnv34jY/xT4/tPPIbt9awv34ebx42Vbf4Tvz/3f/CMAAAgDngdn5bs6GKnXO64WZvC1wrXKLpp5X43nw8zpWt3b7xeUMVYoFAqFQqFQKGAfM8YWfTMqBPuTW8gkuS5+W3LF3/UO6WMzG6/5BbdZOf6c5oJ9Lr9NUl/yyyV9NkiYVQRiJu0KLtn89A1lUxgjM1sQa11rsCayXseCG8tLJ8prLqXFatRRF3vh4mLZdvPNyIi9/653AwBAnDNT+eW/+nMAAJgYZ71klea7O0QGLhYM+6hGuuhdZmajBBm9ThMZ47UN1j6PdZAlDFvENAqGfUgFTdw6z82ySCdaxTF068xeesTS12pMh1tUJKOW4pqvD1mjOrSx35NDZCWbFo85ITbYtVhHPIyR+YyIvczF3prqMA5FBVZ3mTF2SCM+CDl91xdOYMGUyYPI/N9+40LZ9uB3kOXcXGW97jZFBCr0pf0jh3iOcweR+fyTx/FzJy+s87N9/MD77ri7vLa8vAoAAEYqHBachmye9PKzfATgM99EnW6zhn3deitX8a2PYWTANvr5WO47rt326RfKazcdxv1qdu7EOY6YTe5TxMKvMjPhFMiseu2j2HYrF//IbPz5pgFGLnaXt8q2la2zAADQGfHZiVIczye//Os472eZ0b33Te8FAIDuDN5//XGOUsDEj+L9NkcUgI7dkydwbtEOv7fGhxCM+FoW496fjHChPl1jJjslH8LBW/H9njzEkZ7Pfu4BAACwQOgZlT3+vuNqZAKvFMogXlt4ue+AnovLgzLGCoVCoVAoFAoF6B/GCoVCoVAoFAoFAOxjKUUOGEYuLCF/oL/jbcDwqOPw3/U+SRxckhbEAacaG6bGTMb9OxRiSAu8L82lLIPkGHU2Hs3MHMF+KRVUnHL/7TZKD+oNlE0sLrE0Ith5HgAAaiKicX4Zw9Q33YiV0z7y4z9WtnkNDEV/9i8+DwAA/V2uLuZ5aBZa2V7lzsjQllJqOVusSZ3SrrV9NnudodRkdoqxeytgScGoj5KQrSre7zuNsm07wjD7RJtDy3WSgvhjeP9IrK/r4x75wgC20UNZwcYqmrZmu4f4A5lFfaCBbNBj6UKD5BvNCQ7dg43PLixKdyZS2MUxhs1jMg+6IuyU03odu43lEqmL998+ianQ7jx2S9mWbH4dAACeHl4or412ScZB0oMvbrJcYm4L1/fZJRzXIOL1nT+IEpjHzjxSXnNW8dk57V97msf1FMkq3n7bveW1f/zBWwEA4P/+xL/AcX31s2Xbh/7ePwUAgLFZrESYCYNolqCcpC3WfNhDE2G1wBRoG+efLNtcByvlVWos28mpWuLOCGUS9pD7d0Ps/9ziHwIAwEzOshdviHvTmWL5w3O7+MxzF/B8bKxxSjr48oMAADBZx3tObr2/bLr+DnyfBvR5AIBffCsaEc/fhOM6+e3PlW1Pb+N9N15/Bz/7Au7l6e/gu/XUaa7SNzaJZ+1ukkBN27wfg4iMeFr47vsGlU1cCg2PvzxcjSncXileybz1XDGUMVYoFAqFQqFQKGAfM8a2Mc/ZnO6L/FxQEBMmU6ZFZA6rVykdV8SMUkLFKbJMMGiUtiyhlFWezd+spsax0ENuMWMaB8iW1epotFqY5hRo20P8prVITOBYi1NPPf48mu7e+sZ3ltfe+6G3AwCAS6nPPvfZz5dt6+vI4sURzkd+4ytTk0VskgJqN6xqq85jDjOct0mFBgBg5Xj/iBj5rsUp1rIA16QXIHOcp2ygGsbIlg13mB1t+fisjQYyxpZg2I/No0HLtZlZb7nIIlp0//omm55MJjaX0uGNVZlxXMtwHLsivZsx9413cN6dLq/5bri3OEMSM5U9SvBctHNmcvMRzvfTn/00AADc732a5000eCaKkQQj3O8KjXHi2BvLtvEpZFgPTuEevW2CmdAD1yFjWrWZwf/M/cj4xts4xyzkNaz7OKeTF3bLa9VNTM/3cx/6ewAAED71IM/7Sfy5NoYsp19lU6A/jgzoQBjslgbIwH/+wS8CAMC5xbWyrVZFNnV8jPvoTKE5c3UX9/S+2dvKtnAbWdidDv5KuXGeTYELDXyf7n/ub8prX3sG994rcAzNY7eWbcsF7s1qBdd+UhR2OfA8mvQW1zlq8tTSWQAAuGsCU8bdc+Tmsm26ieOqB2zATCycx4kUxxDEHJXqkcny/JmHAADgepsjEQepaIst3klh+VRcIa5VVu9vgzJ5iu8HtKAIQxljhUKhUCgUCoUC9jFjbFGqrT06ISpAkRDbm0oGkdicaIjXwlimZ6JUay6zfjYVnjDpnCZbXHrZtpEJTUZcuGFyAlmm5jQyb+dPiTLAB7Ft8SymPjv6XtZSfuAD7wMAgN6Qx/p7/xmLB2QBspceiCIKlMqtoHLMOTBjDsT2gtBDW8Ssx1TCN8p4S02hkjjkZ1tUGtim70RBwMx6SIx0jTTWI7GGpuCKHzD7ujFAhrE+xPWyWoLdP4Aa1TRjtm+nXANkhYNtTteWDHG+mykymhcd3vd2C3XNtstMa4NKL7tUmGV3xGsShchud+rY5yhkXi8kdvDkGV7zYQ/H5Tk4R6fCrPuxQ5i2a3GZdeN2E/t48/G7AABgLmJt7sYA53bbGPYxEGWZl5eQbd9NmEW//W6MJAzWkRVePH+Wn0Ni1qrPKdxGCWqwzy3hOk3f+I6y7fl11MpuPYW6aHfEZ+HITZhqrd3ilHqmEvntt3wEAADuvYn3Iy1w/NNdfvbGNhYaOf00pi17On2ibJueOwwAAM0urtfEwl1l29o2rs+7ruexHuwcAQCAG6ffhGM+82dl25OUJvDuQ9iH6/Jeffb+/wAAAGdOsOb7Dh/Zdvc+XNeVLp+dIze/G+cjtPdvOIca/8EW7mlcF6XG+7iud9AWBVv8nPUVLLiivOari2udKb5WWTnF/od8N6+lc6qMsUKhUCgUCoVCAfqHsUKhUCgUCoVCAQD7WEqRAYb1C8He+w4ON6PUVoXFofuMZBXbFIqPYw5XF2TUykVnlRqGZyc6mC6qWudUYCeefRwAACan2uW1QwfQHORQ6H5bmNxyMsr99M/9FAAA7I742Y88hMYmUxUPAKAISSZBqoTQYmMQ0LxtC8ud2TaPOaNUY54IC6dAJr0Uw8GZmHdI6bV8m0PFcbq30l8oKuWBZZ6N9xvZBQBAmqEhaijS1CU5pUNzcTzjHhvN0gQfEAqpRm+E82zUOvRslkacOPdtnBs9u97gEH62gxXNWlNseIyGOG5rMEZz5ZBPncx9S2tUiVBII0KSJ6QbSzxvMulFZPzbPcf7sbGGYXq5fy7Jdp46g1KCr2+wIdFuoPzmoz/6d3GuFZYBFA7tQ4/NdIWH/WbUv21zmbszZ5/DMQvJ0NQcSnksSod38gIbGGdbeF4vrqDcYneL5R+daVxz35WyHdzLI4fRrDcasYExJuNpf+fZ8trk8CLN7WfxflFRcHuIMoMq4Nw2d7jC3sZjaGa0o+ny2tzdmBqvX0WpycwtHyjbsg38rE1nwKrxmH/q5/8XAACoVIQsis7pZ7+JadreefBOHleM/S80ry+vtW/DNZx46N8CAMBb7vnZss2q4Rl+6pG/BACAee/Gsm3mMKZ8yx98BhRXDpVQXDuhaYXi9QRljBUKhUKhUCgUCtjHjLGBZBWMYcz1kUHKcmbxUioQEVGatj1sBBn5QBQLMcUfVneQEbS2mPU7fBRTbt11nFNOJcSsnllFA9Ib7mOG65N//K8AAOCJJx/FCy4vq10QA1gw65cVhsFGxs4pBPNtGGPzsVywCvRjIVKHGda5INNeljLjyB/gKzYZ6xIagy2MfCZDXqWCzGmSCPMd3RcXzCJ7GRkkafzBaFC2LV1Ec+LYOBeUyGgNkgL3rzvGxSPGm2hgXKM0XIMh91Undj7JmK0ebyM7uk5sam/ILGxOxzqjwi6WZNiJWR7vMvtcpfkW6QZ+3uWiJMEI12CizaY1m1LcPXcSWVJfGAWPH8JUYRvraACMW7zvL5zE1H1ff+pxHmuOc1pbxXM4DNkAN9rBn993F7Od73rH/wwAAGOzmA6vXuG0dheWMdXf5PRRGifP+5FvYlq4Z5/8QnltdvYYjsF6CwAAODJ4UMFxDXNm7iuHsNDGIMaozKk1nsfXvn4/AADMTOJe2VWOwDz80Fexf7tVXvsnU3fjsxtobnvkK/+xbDvVw7U78m5k3T/y9g+WbYmP+3dx+7Hy2vA8npVkFyMFn1v+Ztl29gy+k5UaTy6xME1iK0MGePuB3y/bdgBZfXuA83/Dhz5atuUVE0kR7wzwu6j47lB2WNlhheL1AmWMFQqFQqFQKBQK0D+MFQqFQqFQKBQKAACw9kOIy7KsSwbR7GDoukXVtgAAalRpzCeTVJrIXMUY+kyMOcx9qb/5+TEeyR0cMqZJWYbnk2TDY4nD1g5Wj6sAVXlzWLKQkTHNoip9nsdmN67Wx/1nYKQUJGcQs0+plpbvkvmuEPl5Scbgie8zSUYSCtJU2GIpXQoLuzUea55h/x5pNVJZu4vMfY0Khs8Dsb5GJuE4vCYNyitsTHhhxPd7NQwd3nbj3eW1mKQs41UMqS/usAHOGuGz19YwF/SFJc4fG5GJsOLxPObnMW9uq4VjDYMh92VMmbSwQcLyj4Dum2hwWD+nfW76eK7W+yxnGKP7LJ/XtdZA85ZHkpaJuWNl23QL+5htYp8vrHCFtkeefBrvbx4or3VaOKcYaL99PjtmzYX3DH7lY78AAAB33/pWvEecq3iEc8tJcvKlr/xO2fatr34HAAB++Sd+qbx2aBuv/UEPz+8Pv/8nyzarinm9u2MsObFtfGcGIclWMl7XiAynTzyGlfmm5tiIefONt+MYHvvr8toXv4q5kI/dhKbWj/3Y3y3bfvNT/wkAACoVlGO8/Q1s0rz9ZgpJZzPlteFfYN7mjRx/Z/y70xfLtipJmWod7uOeu28CAIAXHkNj4Uev47zj39hGs94Tq2iiPH7nfNn2qY//ewAAeOALD5XXxO/PR4uiuBeuEbzU7+yXwn74/5fvN1Q2sT9wLZ691xJX4bn+rr+zlTFWKBQKhUKhUChgP5vviB3NU/7WZ9jg0kCWc5sxwWREZFiZSI9GKc+aFWaNPGK/Rpnpk78NxUN89rBgQ5dNqd4KMnLlhTDAUZtLjDGINHIJmas8V1Swo7E59Mw8EwZDYogz+nZmCebbpypy1h5DIiKleYQpm70aFWJCq2yg2h2gOXEU47/SSJTRWB27Qn1zm+vhNVcwxsbbFxEjm8a8JimNf3l9rbzW7GA6sLSJBq25LjN1UQPXOomxr8UVZv2KBNcrTHhPTy9imrJD82g0AyZaoUbp1MzaNSxuNKNvtzkV3yl61o45V+LsmLU+Nscmws1tnFNIKdZuO3p72Xb/1zHNV40Y+XHBTI9TOrUg5xR2Yx6eyTjA5+z22ARaIab/v/uH/2N5LQ5wnTY2ccyf/fwflm3PnzsPAABpjGfbF6nicg8Z1v/w2/+6vPb29/wwAAD8/H/xzwAA4Nd/42fKtg+9878GAICFeWZMQ5Mmkc65JSo2Tk6ioc2w9UXKbPJXvo6Gv+kxTpv37rdhFbyQPJZ/9tf/qWzr1LHfUYKs7cOPs+nyyRfo/Uu4ouDSM9ieORhtsETKu0oTWecP3H1zee2WG48AAEAjw7X81tc+X7YdPoqp3t50E67Xn77AUY11Sv+nPNRL41pl6K5CJu11jWv1HCpePShjrFAoFAqFQqFQwD5mjHNiTgtRZCLPkI1KEiqQIXW7ObGVuWGO+Vu8S98gQ1mcgvShGWls8z0pmPBaCiL1GTHEFrVZMkuTYZvNI8W4CsMvifstSqMVky7YlV9w6WfDUEvW1nQf2bwmLnGgCQgm19xH881SXgujEc5Sw37xww3znZCmd08iKlrXSKRMy6hgRUKMdy72qlnBYg4Xl5f52WuoG97dpLRoINcJ1/osMcHJkFlVh/YyF0xAnuB4traRYZ2e4dRvaYZtFdoX15dsPd0jGP8aMcp90ug2qxxZiALUTee2SA1In62RHnh57WzZlpBWmuTX4NSYJY12t2lcPI8R6YgzWvPxJrP7d9+J+uzzLzxdXvv4//dbAAAwOY0p5Tzg+8e7uOZOFeedCXbfa+M4atNvK689t4P7tfXHvwcAADML7yvbLAsn8MUHHymvdceQ8T916gwAAPz9n39X2XagTdTvnXjPH32WU6bVWsgAv/GOt5fXshj9AuPzN9AA+2Vb7+I3AADAPoXj+9wp1nyfX8d1GorogdPCsc518dnj4uv+cB1Z9MmnWd/cqaFuOnoUGWa3yT6Gjz/4FAAA/Kt/8RsAAPCLovjOX96PBURseQ5BcS1B2WHFtYRr9bwrY6xQKBQKhUKhUID+YaxQKBQKhUKhUADAPpZSgAlXispvBZmdnBzD7pkIaRYU3rYptlm4MtyJIeVcpB+LKUTgWy49hoOixsDniKpw5kdjsCtEhCE3Mg5zTbQ5ZOhKc5YZQCkTweekQs7gkGHMmNxsEcowmdts+QD6rJlvxWYZQJrhfAchh6l9G9OJZWRulKGSgtKu5bS+ljAMZmRIK1IOYdsufrZdw3D+TsRz3N0yEgphaswoDL7bp//m+42yIaWUb1JdUo5RXHQpiD0kKUIeC3kJVSgr5RIp7+MoRIlGp8EV43Kah9kPmabOpTUYBSztCCOUkxipys42p2SLKXVfHmKfF1fZRNisoRFvY5cNiVYP5RULkyiNWN9g893x69AM98lPc2U2j6QsY1WUA+yICoGT4yglWFxC+UAiDuncOJrjZDW87W1MQbi+jv9Wm1zx74F1lDM06tXy2kafUhZSpcA/eeBk2Va1aE1Iq7IjsgDaBZ7Jcxu8Tt/82rdw/j6mWrt1iisLvvFeNGVW7sExf/jIStn2ma/i59ZObZXXsj6a6E6dwofOTHOKuXe++b0AAPDnZ06X15K/QXlEmKCxUChnoD2Pe/SvP/GbeE8gJB59ktXI8KIafa4JXKshZcUPDt/rzL2UwfDlnNHvZUzUM85QxlihUCgUCoVCoYB9zBibIhiC4CpTQVlU/MIRqdwMA5rQ/U4h/+Y39/E1mxhHx8ElSAV7abx0hTBJecQsW5SuzRaum8IwzDS+qqCgyAcGccSMoxmrQ+MphBEsoxR0ps8k5zaX+nfEN7s0pXkQO2iKjAAAVB1kRYuM7x9BbCaH9wtGNy/ImFdQCjvB+sXEouYiRV4eoVnN7Iftclq0jNjUXNiTzDfSLKN9yPj4pWlo7sL5OJeaCaXVKaO1M6y+iSYAAKR0X8M1hWCEyY++McfSvOUZBj+np/CaNBrIZA5HnAYvIla7SgVB+oNe2Vah4i4mPZ9vcUqzQYRz9G2+NqJ1PbuGDGghIgtRiKazUyefK6/NNjDl2/oaMtFLa1wI5eD0AgAAXEfp484uPV+2uS72u7HO7GtI5yI0BVSGzI7OL2ABlVSMv4hxzc7uIOMdnWbG+Ngsmh9jjwrnOPw5F/As/NUD3xbXsJ3qoMBdP/yWsu3wAhb9eOirmPquO8999amQz39zjPfo0DvQNPil55EJfuYcp1j76jcwFdvaRlheW5hFk+LhCWTIlxM2lFZa5vcB/pvl/C43aG7ynSmu8eRtV0tqLGXLFD9IvNLzd7nnVc/5y4MyxgqFQqFQKBQKBegfxgqFQqFQKBQKBQDsYymFQb7HhYX/4VL+3FyEnTm8SVIEEeK0jCxDfA9wTHUsk/c4lyH/F//ARi7buPD2GHAoFE/jsx1us0nakOe81FlAxjcThhRfTxyqyJeZ3MAFz9Ehk1iWCElBZkx0JLNw+Tk+SRykYQ7MZ0mjIk2HFskXIqpaVvNYzuBSaDwuWFJgNsfISjyPJ5JSzmlH5IJ2AaUHRi4wCjm8bbbLKrUzQrJBe7MnDER6F1py2BxylcK2R0auyDIdlG0e9SEjwK5LVf1ICmKJZ/eHKJPoCxlHQYbKCR+fc2J1sWxrUXVFI3EBX3yO9kPuqZHmFJT7OhXr++DDD2OfPhsFV7fRrHeobcxqvN9ff/jLAAAw2UGDWlVUPFyhcTVs3qN2q0NjpnzM6xtl27NPolxidna8vJZTecFJqgK4IyodbpMJ0PNwj/0Gn52tHspEag2W2uwMUL6wuYxn4F/+H79btnke5lzuzqLUoZAGzhFKSf6fLT471ilcp2GMz3THeN476yhh+p/ef2d5baGD8pW5IyQ5cdhgd291rwAAIABJREFU+Ouf+AwAAEzMoNziwgobBneGIY3n6pAPvBrYY97dB7IKDRUrXk/Q87o/oYyxQqFQKBQKhUIBL4MxtizrPwLAjwLAWlEUt9G1cQD4AwA4AgBnAeBniqLYtvDrz78BgB8BgBEA/P2iKB67nIE5YAxtwgBHLG9GBrIMpPmOfr600BxYxIrKNGcZueISY7gSrKJtX2roMp8tyKBm29LIZ8ZxaVoxc6niMetnug3iAX3eefHtzIALY15KTG4MclzmA7ReMsVaaSaTqeiyPQ+yX8KQaNHcZHU/Y2ireMwAOzkxrI5hxdnEZIyIsn+TBi81Vf32rJN5GN0v22xTBVCuk6lESMx3IqruUSW7gK5VPGYEE2JkExGKMExxndLOFRlP3FTNG5DREADApTMQxcggNoXRzDDFeRHQtESFvSYZ08QamgqHUYjGsYbHZq8HH3sI+xfMb7WObOqFFUyHl4l5+I5J/4fPqdS4r7OnMV3ZWLNdXpumFG5L68iKjvo8x+1dNP6FiWD1KfKws4NtzQozwEvLZCilqox2zOM6eN1R7LPHqeUaFq7B7E1Y+a4KnbJtZQ0NgsEWPu/cMpsbZ2dncShiT8fH8Vo9xXnbNV5fi/bv88+fKq95K7gWP/fPjwMAQKXG6fm6bZzT5ioy5pOtybJtkfbt0mSJ+w8/qN/brxasMrKj6aUUrwwv5+y80r5eCpfbv57b/Y+Xwxj/NgB88EXX/jkAPFAUxQ0A8AD9NwDAhwDgBvrfrwDAb746w1QoFArFK8Bvg/7eVigUileMv5UxLoriK5ZlHXnR5R8HgHfTz78DAH8DAP8DXf/dAr9KPWRZ1phlWXNFUSzDKwb+zZ6JfG2GYSzZXcHsmZRnL/Udzi72puMCYEbWoW99opYH5HRtTyEN+tF829vDPtO1hBjdNGadqOuQzleynfSjbdLPiTmW33YNY55LxhUZtIq8v0whRf8tCqIYplj271FzROyuZHTN4tmG2RVsvW1SzDmN8lpKfVSpD8tnFs+kt8tEsQyTQs980Y4l604MokXPlEUUzMoVYm6GpU/NJcHMjojdTYnRrDlSK00/C931ZBXHfZGGs90TBVGIFQeRGjClYiomxV+n3irbeiN8dmyKhUQ8f6+KUQNZ0MVMMyGNsQvMwgYjZJELJuIhpH2oU7qzTEQUOmNY2GJ9bY3GJ94Gui0JeTxPPPMUAAC068jWyqiJ0a7nYp3SNKJx4foMt3lgLu39kFKzxSNui09iHxEVMwEAOHoc2doTTz8OAAANh89Cc3IGAACWzuM8xif5zJ19ClO+zd56fXlt5QKmrgtjeg+TUdk2Nz4BAAAvFMzqH77phwEA4N/+v8jIJ31mxX/6V38MAAC2t3H+3/jKw2Wb0ey/HvCD+L39WjBhyq4pLhd6dhSXi8vVGM+IX5orADBDPy8AwHlx3wW6dgksy/oVy7IesSzrkcscg0KhUChePq7o97b+zlYoFNcCrjgrRVEUhWVZr1hsUxTFbwHAbwEAXM7nFQqFQnF5uJzf2/o7W6FQXAu43D+MV02ozbKsOQBYo+sXAeCguO8AXXvFMGnEHGE0y0yKrtyYykSon0xnHt2TibB7QRIHGZ7PSpkBSRZSKY0gWYYM51OFPLfUVPBYnXJcZKSSpj1jGIw5tFxWViOJQ5rx/SadWBlaF6nfciMdsfmakQZYmVkTkTKN5ujKkBKlYCsiHE8h08EZmQGljDMGOgCAkFKsZVJeQWti+uxW2WCYevjsUISwRwGZuyiaXxFV+kLXpC2jOQpjg6nqlwo3oDHwmeEUQgYQpFTJjeZRr/L8h9SvKzLYXdjCEP8wRMNcASKdWob75/sscbBo/dvjSLiFAUsvEpI/uD6lgBP7npCsxBXSjmYNZRjmDIRCelEYY10hziFdGxb4HCmdGY7IzEnvQhCwpCCiqnuOkCy0qAKfXcFrg102xwGl/cvE2alSWrNGDfe5OsH7bfbr4jKZAkXaucEAzXq2SP8X7mJ6vYRS5fkO/yoKh7gfkYP7EFzklGnX33ETAACkIz4fa0PaL6rgNx2wNGJpgFXw5q87xNdOn6fxk1yrzebGT378iwAAMHczEqaFx/sel2f/dfs34Wv+e1uhuFbwUlINNYteHbhcKcWnAeBj9PPHAODPxfVftBBvBoDdy9MXKxQKheJVhv7eVigUir8FLydd2+8DGjYmLcu6AAC/BgD/OwD8oWVZ/wAAzgHAz9DtnwNM+fMCYNqfX7rskRFb6bmccsqkSCsZ1sK+pM23iYFzmTUaZMjaucJ8l+cmpYtJX8bf5jwygkmGyzYFMYhx80XKrTgxrOBeFhMAIKOxpiCLbCDDZcyAtmSyTcEOGleeS9Ya2StPmIBcGldGxTWsjNlOm769OoKNM2vnkzkuEc4uY+Ty6VjYgqn0DGMu1nyUIAPsV3A8Xp3ZYZeGMRTGJmPIIzIVeqlgqwtiKIn5tW1mHI2HzJbGQs5rR/fL4i24Thn1vzHcKdtsSuWWCFYYiMHNiKWXfaVUvaQu9rsgE+RUFwtQPLHG8kzf92gM2Eci3jCTSc8WrMIoQZY6odRvts0fMMUyokyY3GjvLUoLF2ecYs2yuzQdnFsk2GeXGOA45v1IaECDvol48Fg9sjz2trnohzGSDqmPXBj/xqhYiFnDoM9sdZnMUNxfp7Rz7QbdX+U137qwDgAA/QH2Mb8wX7atLZ7DsQvWdkSMdHfhAAAAbIR8DpvE+A5DLgDjtHC+gxGuyebmUtnWzvD+/gu4LxNTbKwc9vt7J7SP8QP7va1QXMNQVvjqwMvJSvHz36XpvS9xbwEA/+hKB6VQKBSKy4f+3lYoFIrLw74tCW1Y1FqVU4C5xKYNcmSsLFumX0OGK7WRJStkAQcj1RSaVlNlw5RSLmRpZMM+e4IBJQ2sQ6ynK/S3rEnGPjOR4sowoYIsE0U8iOUVFLPREZvh76k8TSynLTTGNjFipYZZiGNMLY8sl6wwdpwRg10RbHJMDLbRSRVifRNixc0cAVjfmmaXFv/Iidn0hd6zKPDnkMhgT+xH/qLSyEUhijQQC16ItHNlCrfCFGiRNB6x7bRXUg/uE+uZurwmE2NjpjOc64hZ2ILSkNUrHLmo1vHauWUsFJEJLW9GWmRTlMOq8hxjui8TZ8elDatU8azJdGoOPbvq8jtgIhCmGEsuKGlzVjJimGWqNdMmJOWwMyAWdYBMaFkmHVhTnSa8Tia9YE575PtCPz7CcfsN1B3XG/zszU2UslZqPI+YNM9xFdd1tMmp3NwyUkHl2kX6w4BKmnsVPgsFRZVWnz8LAACTC92y7fwW7uVUi/XQG6vIMFd8ZK0bdS56Upui8tgXUWKbbfGYTYq/1wFhrFAoFIrLhJaEVigUCoVCoVAoQP8wVigUCoVCoVAoAGA/SymMkc0VYWcyn0GExhhZ9cs1Yf0cw64yfZfpK82knuFF7i1hNMsoNZnn8veGTn0cAAB6EYadU5GSzQRXTcU8SwRb09yE9UUMm9xkxuNli9B6aWgy/kJh1LJILpAK05qpVmb+LWS1MyPHEJcc16f78P7E5XlXKJRuzF6pMH3ZRrIgxmrSxpm0boOAQ96eT5ITUQ0vpjV2EpKxCBmHMVvatjEdiqqG5fP4duO+M1X9pLHLrKHZvwJYIhBkKGcYa3C4fRCQ9MCk7quxbMKYLItUVNYbomxg26Rp83keLslDTGW+SpX7KmKcm+PxREIjExiSPEg826TgA0dIc1xjQMUxZ0IbMdhBaYRJqVeIjfeMhKRgqYaVUV90lj2X5zEiw2Ih9igKKJ0dncMkEUZPksJkJPcJKfUdAIBD0/DqnBYto0qCrRZey1M+O0ubmwAA4FJVx1QYSgs6c0GfU+S1x/HdvLBMKey2OMXagEyAoUhF59E73+ttAQBA5SCfUYvmPdHFPnZ22LhZpLjm0l6jsgqFQqG4uqCMsUKhUCgUCoVCAfuYMTYFPpJEMLPGhEWXJHOaUSGM3JiFLJ6aYbNsQdoWhuWlrwbSHGeo3ESwWCH1a9JRFbKACDFoZbEJwT7nFrGRsn/zbJqbLQo+WPaLCnaI4h+GLStE2rmU+nKdS1OsGbY5FCm6HCqoYAo4GLMbAKenc4kxj2J+jkfMZ91jE1MvRGOTTSnKZG5zsyaOSH3mkZnRPLMqWPeY1jorC5Xw2hcUNbBz7iv3qUBLSmn0hCGx08AUW/OzcwAAsLSxWbYFCY6r4TBLuEWFR3yH1sbn50Qhrl0imFmvQgVQaFPj4tKzkDv0r1jfOhnALGEiTCPsd2QK2gijmU1suyPOh0lBZ9haz5OFR/C+JEaWdGZ6rmzbJuazAMn4G3cmjnUkWF7DMFdcNtg5dGaMQdRxhNmSDJ79HjK5roj0ZDadwx6zr6HVwyEQAz67wBWIm1RA5MLFC3iP4Gi9Bp7DYMBjjRMqCEIvsS0Mn402GRhtXqfdHj7bJWPk1vpa2XbHbW8EAICnnj8FAHvNh2lsTKDAUMpYoVAoriooY6xQKBQKhUKhUID+YaxQKBQKhUKhUADAPpZSGI1DImQAmY1hzSgjo5K0wRjJBZnq5F/8NoWKM5Gr2AEjG8D/Tj1uq1B4uig4HJzkAT3TjE/IOEgSUFjGECamUSYkFlX6Sr8fGZZktTrL3nOTVGAUFM7PRPU5N6FnGimFCGEnFJa3hMygLG9mZB9C4xEnZFykWTqiLyPpiERFurqPIe+Ki/9mQl5iFaa6n5A/kDHSItlL4QoZgFk7erYrpDDZS7gIPapgR2miwRayjAGZMxfXVnDMQidzeB7lBcsrXNEtN6ZAWm1HPGeyi8au1dWL5bVmfRI/Z55t8Zo0a2gm2yFjnpuIHTTTECZQi6QEVoJrLXNnmzzEspqSkVDUTf7fkHMo+2RWc1wcQxjxu+Mac9weaQ7dT++HZwtdAElgcrEWttk3Gv9o1CvbjKwioxzjHjTKtiZVxRv0+P5Gu0Xjx/uNBAMAoEfGuoRkJmnMcobIqDfEuU1JhtNq4ry7Y52ybXl5FZ8j8m8nEUmYSBpi1VgS8txzJ7GvSdx332XJRnOM9ubcHhcoKBQKheLqgTLGCoVCoVAoFAoF7GPG2KQ8ywS7ZkgirmonGS5rzyXJkpZmOHF7Zpgeus8wkAAAVY+MWcKnVDKsZnzCzAOmEp+5VaRMK9iRx9fM15Ey1Zh4TMlEY5sr2GEzDZmmriBmz3SfyPWi+x1bmrdMdT6qZCfGldIC2zxJ/lyZuo3TfXk1ZNC8Cq2FmIdL1drShJlAq2TXjONRfC8z7CXl9srkepGBzRJGPmMYy02fglUt0/MFhrUWldMi/NkVTN+QGMeShRYT2ekjy+mL/e4RU5rSWnY742VblGFfplpdknCaMHN+67VWeS0hNtQxjL8t1xzHPxww0+qTGc6kBpRrbtLsRRHukZvwmD2zvh6/8iGxtUBMcCZTHJooi3iATdEGw7Q68tzSeFwLx1drCJMmpZHza8yGG1a4MsIxNOq8Ju2xaZoQMfgVnkdIVQkLkSou7COrW6VnOnW+f3MLIwNehZ/dKCvwYR87G1zpMKXzkZ1E419ziscVjsw5UsedQqFQXK1QxlihUCgUCoVCoYB9zBgbBqrYkwPMpCYjBjS9lDn16F+ZUSkzhLEkekztBJMCTabQItbWEsuTE0tk2YahvHSsmWExZfGP3BTzEAwoUb+GAZWFR0wKMJPiSupLbctoYXms5bDpNl+k9hoSe+nsGSv+G4Nhh0W6NlNUxLDQkvk2FUfEmhhtdRpQYQVRIMIhrW2lwkUdwhzZU5sYdrmGRsNs2OFiD1NpXXKtDALQAtiizbORHUxTZE7HWszorq8ig1gXDLAjCoAAACRC823SjuViEVPSYhv9eJyKNaSx+lVijEX6Ndc397NmFkj76xHT6rg8loTOty1SvpnCGZUq3i9T/UGyN22glAx3xycAAGB3l1OmuS5FD2gfq4K1DWmMTs6duDS3yLCqov92CzXFgwGyr4M+M+Xl2RHvq0eFUwwTLyTlEFP6vFFI0QaXP2c00rZ4xSwqsBKNcG3qLT5z7SbOKQhYix0To15QX6lgyhuUKm69h+fE2eXP8e8iZYwVCoXiaoUyxgqFQqFQKBQKBegfxgqFQqFQKBQKBQDsZymFiQOLcLupYJeYJhEBd8jIZSQPMuxuosF7spaZdFTl5/n+hKpdObYwspkKcxRa90QqNyONMOnUpIwDLOeS8RSUiq4wZiZxew4m3ZzpU8zDdJnL+4s9FzMxZmO4ktXtjCnRpzGn4ulmjFZxadU2mwx/ucUyA1MVbETp8zyfj1MQU1jbZxNWQuFzj8ZgKonhQ2m+pvKfCG+bSn/S7GX0Aka6IM2WCY01o3tGMafcMvPIxP02pfqrttsAAFBz2KgFlGJuELMEwSJXpu0WtA6cFs3IaGJKLTg2Nla2bVPlN+GFhAqtf0KmwyJh6YVnZBlNIUcZYGjfVAGsCGOakRnUHd8Mhj9n1uAl3ieXUsTlospbo4JSkFzsQxSjBMGsuSukMxnJJFwjw5HPoXclFKZRzwzEw/u3Vrn6XINMdBktVH2cpTDp+jr1z3MzkqeCJBcbK9xXkuGYpSTJ9XF9epQizhZSmNkjB/B+GldNpM+LhQlSoVAoFFcnlDFWKBQKhUKhUChgHzPGdvHd/2b3KbWVZGbjku0iZlM67XLDIosCFKVp6VJ21BSZKASDllkvMtxIR1u+t60QdJlNNKcsRmIycmWX+vgAXjQu2WpWJBeuKotYNVNcBKSRj5i6VKQmM8UZTCERT5q3ysxyeI9V8PxN/RTfkcw6FewgJtixmcLPUmSDE4/XtUKGtDhA9jIVhkdDwFvEhOaiWIhD7slMDNVKjRmSGHbBbHrUb2yKWQh23yxiLgq0JIblpTFPzR4s2xbPPE9zFew2sfINv0V9SfMkMabEOEbiOT6xu64wjhmDpG0Y/JzX3KYCKFEkmFwyhw0TZEIdUfzC9r0943EESzoiQ1shzwe9R+ZaLs5aRuvrV0RYJsd1jIiFrYgCLcZMF5A50BNuutQwzNJQSWx1XqYP5EVxaY4+raXv8HOSIZnhRNq5GrHbYUDGPDEPr4qmwGzIZsCYDJEVBz938Lr5sm2whAVBpmcxZdyZ5xfLtlHIqQoVCoVCcXVCGWOFQqFQKBQKhQL2MWNcFst4qSICxHLKoguGacyISUtBMMC50a8KxlikjgIoK1Djz/RZyeQ6xEKaEsqJYPY4tVw5av5gZvpkpFSIwegePfGk8j67pDa5zSyGYHmN1rRkb10pvKZUZoJ9N6m5cpOmrpAMotH34v2hoGgLKoaQyhxddM0jCjQXs/TMWAVjakpHJx7ukSfEtjaxlqZ4i0w1lpoUfGKsRt+a0PpITatlIgTEALuCmTZfBUdCy2vyjplUaFGwWTZ1aqgR3gpYR2w0xmbfpYa5ViVNNVHsoq4ERMRgux6fW5vOpmGTK5bQZFPauN5QaFupQxMpkJEM70Xvh9xbE9WQBT5SWp9Sli6LvZBuvMj5PBndt2+K7xRCbx6J9QTW6AIAZMSKu4JhNinTbGKazVkFAEhJ+1sfQ833uNAYby5iKexhKthbYsN9iix4U1wSOtzG4iKpLG9OZ9KlfZxY4DR16+dQB75QR6a51ayVbb3NPbEdhUKhUFyFUMZYoVAoFAqFQqEA/cNYoVAoFAqFQqEAgH0spTBV16yiuKQtpxBzIq9ZZOIhU5yVi1RSJlYsK9KZ9GDGGGTzdwSbfs72pAyjNhOSFsamMhWbSWkm4vrGHGYJeYVjpBM0t0h8PTFV7cy8ZRoyy+Spc4UxrTQBejSEvcnfcHw8DzM3m8LIe8LhZIAyc/MdDqPHRoKRiZC5ZYxyxtDH9xcWhs3lWkQFpc4i+YDlcJjayBKMHCMT5kYjCXAzOTcy3dGS1HzWLESchA8AAEbxsGyr1PCZTQqVAwBExshG89le59Rsk+NzAACwtcspwIrSsGnmLaQwNERzfneHLLPwSf5gTG8AXKVusjMFAACDkE1igx7+PDc1V14zVRL7JK+o1XkNw2FIc0RTWSrkQg6lDUylJ5XG6Jq1FJKTDEw6PFFJMcX+G9UarQPDvKb1BqaWCwOed93H+2NRURBICmMkMVnC72ZiKgTSvpx47oWyLSjTwvG4Qqp45zRxT50Ry14qZAJMREq9yQNotquQ5CQ+t1W2TczjWvd2sPIdCKmKrTSCQqFQXPXQX/UKhUKhUCgUCgXsY8bY/MkuDXO2MYeBc8ntJa9TMo+yAAD1ISgfc81kH7OEoc0qC3Ds4cSAOgYAgMS6NL2bYaEdWTTDdCHMRU5ZXIPMT+IxpeeuJKElG0ksnrhmzFcliyk6MynAbOdS813xkungKC0aMaGZYOvLgiOCVTREvDEr2oLDN0RjLlLZxZRazJgI05xZvIzWzBzIl2K+9xjyzDzotqSQZksqtFKavcR6JSY9GLOpGY3LqlZoXtzX5s4KzU0w2LTP5ow54jzmARkLyWCXJTzo1MdndvxqeS3oI5u92duk+3kNXSJYN7ZWeG40J5vWKxiJ4iXEso8CZJM9l9nkON1r+AQAcOiwRWTCq/hsjjPFPuQ2lKa+sjYHz8MU5EmN4U+cnYiMjnsYV3pmRGetUWHTYfb/t3euMXZV1x3/rXvvPDy2sQ0mUYtRoapFRVDaBBMerVAElYpT16CSD1SgQkGgSgjSqlIUhASCb1WqllZtUqGQAm0EKZAWMKINuJHypUBtWijBIbFLW9siwe/XPO7cubsfztrnrPHMePyce4/z/0mW7z373HPWWeecpT1rr4cf49ChIglvabs61uKVRTLkxMHKs970RL8xT5DMjU4AhnMyZHh2dnszkeFzCg/zWFhtuCgV5eB2f1wcf6xdPaN7dldJmUIIIc5O5DEWQgghhBACTYyFEEIIIYQA+jqUwpfWY63bnDCW1/BDnd2yW11ewo1hAL5b7HzXbHjST14274QOYo3pdWqhCkFoNnI4R0VeUs/L7TYz0qMMawBILn/L1d/tzgzZqMIzYkiIJ841QjJdTtbLf+PEhnw2vTZwPG5ebm7E9W0PW+l6mIGF37W83mzsnNb2znjDOXkrJJW1fFk/67m4spy05iEIIfxh2LvmdT28xFKV5NfsuMwhibD8lCNc0rQLB2DEl+dTiMGYnCiWypsD1fJ5ris85c9AO6y7D+WwmnDuJYuKurfJdTgaurbl2Jy216oeWFSdpztebIt1iVcsKY512JPVYn3ssp52qEOdk+hyx7glS6savKOjo9OufzLUV6a876Husd9Ta+YQmio5LifFtSeqYwxlPXXzsxOS6XLBbu/SF5NGJzzEIddqLn5s02SIYTuLlxYJfMnrGQ+HWsIDfthYx3jp4kIHTT/WeKg5vW/v7mnngSrJsuV6arer69i9v9BhTjbthGTTyfiaCiGEOCuRx1gIIYQQQgj62GOcvbWWgvvVnXa5A1r0IOaPuXRWYqZ7pxH+DsgJYKVfy2Jinie0xTJq2XOYS26FwSxPKj250TOdLyheWyMf9Ki9K09oFic2L8vdzmyWJMJ8gkYs72ZHeZOB5F7RqWbu5DdTT00v09ZOEzN+F73bZYKjH35iFs+0hbJrw60iWas7Uey3N5TDm3KPY74v0bufEzAttg8suw1mL3TltU3mHsDc3S94QodHlrrI1aM/4V7RXJ6uHZ6r7MFtBXk6ft0d9xgPBO/zpHsycxfBRaH13WHvDtcJXvcDyUusjRT7DU1U19FcVHi82+3Ka9nxRMG8qnHkSJWEVnn/8ztQ3ffJslRaKBs4lTsXFp7cFHQ45TK2BitP67KV5wEwdrDQ15GxQ+VYTuoz1107eNEbg14yrT29Ox5AyvsNhi6LXe9sOZzLzlX3b/xAoa+JcKxBLwfXtEI342OhK54/5924guSyjvl+zaEqiXDv3uKa9u/aBcDUZHVum+VdEUIIcXYhj7EQQgghhBD0scc4EyqTlZ7AHB/bCvP63JCgm0tpxRJoZaW1youVG3p0s2czNmkoPXrVQfKnlnt7m6G8W6f0Jjb9fOFYR3umAWvkGNvCG9cJrlDza8vxkmlaWbgcP10dq/SMZ/mD53vYy3V1Qyxv269twMXvhAYfXXdPl01GgsxpaqYnPjcqyXGv54xUnrehRuGFnAhl0UanCm9cZ6LYNt4Onr2US6DlEnYzvXOT4R6V9zT3PAle9BaD8ZDEx7zrHsBYii/HD3dz04lYDs89s+Pjo+W2gQn33Ofygd0Y+5xXOoptkxMhVtr374R49pERj6fNvw8rETmGuRkarQwsHpp2zolOdfwyBt3PMzFR6bdRNmOpnoVc8i4vjUyF56SMPw7v2P49ReOTMn7cKr2Odwovcr4PzXA/cuy2heto5BJ8fp7GQBV/PO5NTgYXFdvGw3U0Z+mykcvUTeYSc2GFID+j3VDCbbLrcdPNQpcDwyEG3cvAZd1HnZjcCEIIcdYjUy+EEEIIIQSaGAshhBBCCAH0cShFThwjJmj5UnrDl3BjQo350nhZ3i0kak16qEJcIs8/zV3oppU5y5XPwtLvoP8NMZV3DEllgx4SMeXJTFNhmT6XcGuFpLgsxpSHSQxMVefptjypLJ8myJA6uatftVRcNtbLJdNsZkmsTijRlbu25dCIacl6KYcG5N+HxMeyc1oMcSh0kkNBQo4UY519hVytSv4hv295+b8xLZnJl6xdObHEWk74iwlwkzmxzkNDuiHMghx+4s/OMg9XADg8WSyjp9j5zrV4wfIiuWznnp+WYysGi2S9Xa0qlKLj3dCWDJ0DQDvcjxySk8MlWqHrYKtVLN0PhmvLIRo5iXBoYOb964Z3IMs9sKgIWxkL4SiT3VGXwXUe7lUWI4UufYNeXq9dliSrZO2MF3qyZuiG5/eh43E4rVCeb6AslTY6Y4zy2ay2TPozucQT36ZCeEnKYSI2cZARAAALqElEQVTjnhwY3oH8HK489xPlpgMH9/vl+ns+UF3j8MhiP2YVEnHIy8B1PIGv2ahK3h30cn6lWQiPaC6RF8Ou0iwhP0IIIeqLPMZCCCGEEELQxx7jpntlpoL3Z8Cme9CawYPYcG9cck/zlIWkp5x404geNPd6+f5jIWFnwMcawduXu3bkLc3oEcte2OxeCglteCJUs1F5vVou9oCPTUWvuLurc7JUOzQYyF5qC16/RnaE+bkboezVbE1CSg+mD7WD5zQ76VsDxbUNhNJhk82ZDUGy9luNQvexScMnzlkJwETw3JfXkhtDhPuRm4PkBg5Tk8G9mE8ZPMw5QTB72EcGq7Jo5rpuuAdx3Kr7sXL5cgD27t9f7e8NHhYvKcY6u3aUY2PtwoM4GBLN2jl50kuZxTJk2ZmYy+B1pkIi2ODRSYHQGS9+mz2uw+E6Orn0WTh+vr8T7ikeDOXUmqk4/uhk4dFeds6ycuzQoSKpzMJSSk4ebE75Ckysh+fvQEzWGxoukjmncom1UEswe+5zST5Coive5GUyJArmhMexw4VcI0sqr23XS+RlnYwsrRp8HN53AICDBw+U21oDxbMwfqTQiXVDo5ms/9jYxO8DnlgXV3jM3/N8H2Oy37Bf/+FwbiGEEGcX8hgLIYQQQgiBJsZCCCGEEEIAYPMlj5jZN4F1wMcppct821eB3wbawDbg91NK+33sAeAuirXU+1NK/zKvENMzus4YJ5o0M9v+edvxJt3Mvr/NvvM0Tuz4xzxSDxKE+kmu+e77ypVF2MfGjRsBWLduXTmWQ0euuOKKctvLL78MwO233w7Aiy++WI6tWbMGgM2bNwNVzW2AXd5NbdGiKjQgd3Xb76EdO3fuLMeuu+46YHo94uUeCpLlGQqd9bJcV155JVCFIkClg+uvv77cdt999wGVTh5//PFybMuWLQDceuut5bYNGzYAcPfddwNwySWXlGNjY0Wy3gsvvADAnXfeWY69/vrrADzyyCMzjvXUU08BcP/995djhz28Iusy3x+APXv2ALBixYpy26pVqwB46623AHj77bepmO05PCPP3eaU0pozceCT4Uzb7YWy2UIIcYaY02Yfj8f4SeCGo7a9BlyWUvo08CPgAQAzuxS4BfiU/+ZrloP2hBBCLBRPIrsthBAnzLzJdyml75vZRUdt+274+gbwRf98I/BsSmkC+NDMtgKfA/7ttEh7ipyoh3K2/U/HMU6nx6pfy0X1k1zzyTI+XiSrXXPNNQA89thj5djwcJFM1mpVr8o999wDwOrVqwF46KGHyrHR0SJZL3st94ckv6effhqAa6+9tty2du1aAB5++GEAbr755nIse1qjF/nee+8FYP369QDs3bu3HHvllVcAuOOOOwB45513yrHzzitK0V1++eUzrj97k88///xy2759+2ac++qrrwbgyJEjQOW9hkqHzz33HACbNm0qx7Zt2wbAsmVVMmD2sh88eBCA2267rRzL9yvr+dFHHy3HbrrppmnyQXXftm/fDkxPEI2l7n6WOJvsthBCLCSnI8b4TuBV/3wBsD2M7fBtMzCze8xsk5ltmm1cCCHEGeOE7bZsthDiZ4F5Y4wB3POwIceqhe0PAmuA30kpJTP7K+CNlNLf+/gTwKsppefnOX7/uBeFEOLE6asYYzizdls2WwhRc+a02Sddx9jM7qBI7rg+VbPrncCFYbdVvk0IIUSPkd0WQohjc1KhFGZ2A/BlYH1KaTQMvQTcYmZDZnYxsBp469TFFEIIcSrIbgshxPzM6zE2s2eAzwMrzWwH8DBFNvMQ8Jon7ryRUvqDlNIPzOwfgPeBDnBvSmlq9iMLIYQ4E8huCyHEyXFcMcZnXAjFqwkh6k3fxRifSWSzhRA155TqGAshhBBCCHHWo4mxEEIIIYQQaGIshBBCCCEEoImxEEIIIYQQgCbGQgghhBBCAJoYCyGEEEIIAWhiLIQQQgghBKCJsRBCCCGEEIAmxkIIIYQQQgCaGAshhBBCCAFoYiyEEEIIIQSgibEQQgghhBAAtHotgLMbOOL/15WVSP5eUWfZod7y11l2OH3y/8JpOEad2A38L/W+/3WWHeotf51lh3rLX2fZYQFstqWUTsPxTx0z25RSWtNrOU4Wyd876iw71Fv+OssO9Ze/19RZf3WWHeotf51lh3rLX2fZYWHkVyiFEEIIIYQQaGIshBBCCCEE0F8T48d7LcApIvl7R51lh3rLX2fZof7y95o666/OskO95a+z7FBv+essOyyA/H0TYyyEEEIIIUQv6SePsRBCCCGEED2jLybGZnaDmX1gZlvN7Cu9ludYmNmFZvY9M3vfzH5gZl/y7eea2Wtm9mP/f0WvZT0WZtY0s/8wsw3+/WIze9PvwbfNbLDXMs6GmS03s+fN7IdmtsXMrq6T7s3sj/y5ec/MnjGz4X7WvZl908w+NrP3wrZZ9W0Ff+nX8a6ZfbZ3ks8p+1f92XnXzP7RzJaHsQdc9g/M7Dd7I3U9qJPNhrPDbtfVZkO97bZs9sLSD3a75xNjM2sCfw2sBS4FftfMLu2tVMekA/xxSulS4CrgXpf3K8DGlNJqYKN/72e+BGwJ3/8E+POU0i8B+4C7eiLV/PwF8M8ppV8GfoXiGmqhezO7ALgfWJNSugxoArfQ37p/ErjhqG1z6XstsNr/3QN8fYFknIsnmSn7a8BlKaVPAz8CHgDwd/gW4FP+m6+5bRJHUUObDWeH3a6rzYaa2m3Z7J7wJD222z2fGAOfA7amlP47pdQGngVu7LFMc5JS+iil9LZ/PkTxgl9AIfNTvttTwE29kXB+zGwV8FvAN/y7AdcBz/sufSm/mS0DrgWeAEgptVNK+6mR7ima6iwysxYwAnxEH+s+pfR9YO9Rm+fS943A06ngDWC5mf3cwkg6k9lkTyl9N6XU8a9vAKv8843AsymliZTSh8BWCtskZlIrmw31t9t1tdlwVtht2ewFpB/sdj9MjC8AtofvO3xb32NmFwGfAd4EPplS+siHfgJ8skdiHQ+PAV8Guv79PGB/ePD69R5cDOwC/taXFL9hZoupie5TSjuBPwX+j8K4HgA2Uw/dR+bSd93e5TuBV/1z3WTvJbXWVU3tdl1tNtTYbstm9yVn3G73w8S4lpjZEuAF4A9TSgfjWCpKffRluQ8zWwd8nFLa3GtZToIW8Fng6ymlz1C0EZ+2/Nbnul9B8RfuxcDPA4uZuWRUK/pZ38fCzB6kWF7/Vq9lEQtHHe12zW021Nhuy2b3Fwtlt/thYrwTuDB8X+Xb+hYzG6Awrt9KKX3HN/80L0H4/x/3Sr55+DVgvZn9D8US6HUU8V/LfakI+vce7AB2pJTe9O/PUxjcuuj+N4APU0q7UkqTwHco7kcddB+ZS9+1eJfN7A5gHXBrqupV1kL2PqGWuqqx3a6zzYZ6223Z7D5hIe12P0yM/x1Y7VmegxSB1C/1WKY58diuJ4AtKaU/C0MvAbf759uBFxdatuMhpfRASmlVSukiCl3/a0rpVuB7wBd9t76UP6X0E2C7mV3im64H3qcmuqdYjrvKzEb8Ocry973uj2Iufb8E/J5nOl8FHAjLd32Bmd1AsSS9PqU0GoZeAm4xsyEzu5giGeWtXshYA2pls6HedrvONhtqb7dls/uABbfbKaWe/wO+QJFpuA14sNfyzCPrr1MsQ7wL/Kf/+wJFzNdG4MfA68C5vZb1OK7l88AG//yL/kBtBZ4Dhnot3xwy/yqwyfX/T8CKOukeeAT4IfAe8HfAUD/rHniGIrZuksLzc9dc+gaMolrBNuC/KDK5+032rRQxafnd/Zuw/4Mu+wfA2l7rvp//1clmu7xnhd2uo812WWtrt2Wz+0L+BbXb6nwnhBBCCCEE/RFKIYQQQgghRM/RxFgIIYQQQgg0MRZCCCGEEALQxFgIIYQQQghAE2MhhBBCCCEATYyFEEIIIYQANDEWQgghhBAC0MRYCCGEEEIIAP4fmJMfAnVsfJwAAAAASUVORK5CYII=\n",
      "text/plain": [
       "<Figure size 864x864 with 2 Axes>"
      ]
     },
     "metadata": {
      "needs_background": "light"
     },
     "output_type": "display_data"
    }
   ],
   "source": [
    "fig, ax = plt.subplots(1, 2)\n",
    "width = 12 # inches\n",
    "aspect_ratio = 1\n",
    "height = width / aspect_ratio\n",
    "fig.set_size_inches(width, height)\n",
    "ax[0].imshow(batch_data[1]['image'].numpy()[0, ..., ::-1])\n",
    "ax[1].imshow(255*np.squeeze(batch_data[1]['annotation'].numpy()[0, ...]), cmap='gray')\n",
    "plt.show()"
   ]
  },
  {
   "cell_type": "code",
   "execution_count": null,
   "metadata": {},
   "outputs": [],
   "source": [
    "# np.unique(np.squeeze(batch_data[0]['annotation'].numpy()[0, ...]))"
   ]
  },
  {
   "cell_type": "code",
   "execution_count": null,
   "metadata": {},
   "outputs": [],
   "source": [
    "class Network:\n",
    "    def __init__(self):\n",
    "        self.model = unet(\"image\", \"annotation\")\n",
    "        self.optimizer = tf.optimizers.Adam(learning_rate=0.0001)\n",
    "        self.loss = tf.losses.BinaryCrossentropy()\n",
    "\n",
    "    def train_op(self, batch):\n",
    "        with tf.GradientTape() as tape:\n",
    "            predictions = self.model(batch[\"image\"])\n",
    "            loss = self.loss(batch[\"annotation\"], predictions)\n",
    "        gradients = tape.gradient(loss, self.model.trainable_variables)\n",
    "        self.optimizer.apply_gradients(zip(gradients, self.model.trainable_variables))\n",
    "        return predictions, loss\n",
    "\n",
    "    def eval_op(self, batch):\n",
    "        predictions = self.model(batch[\"image\"], training=False)\n",
    "        loss = self.loss(batch[\"annotation\"], predictions)\n",
    "        return predictions, loss"
   ]
  },
  {
   "cell_type": "code",
   "execution_count": null,
   "metadata": {},
   "outputs": [],
   "source": [
    "def get_estimator():\n",
    "    traces = [Dice(y_true_key=\"annotation\")]\n",
    "\n",
    "    estimator = Estimator(network=Network(),\n",
    "                          pipeline=pipeline,\n",
    "                          epochs=2000,\n",
    "                          steps_per_epoch=10,\n",
    "                          validation_steps=1,\n",
    "                          log_steps=10,\n",
    "                          traces=traces)\n",
    "    return estimator"
   ]
  },
  {
   "cell_type": "code",
   "execution_count": null,
   "metadata": {},
   "outputs": [],
   "source": [
    "estimator = get_estimator()"
   ]
  },
  {
   "cell_type": "code",
   "execution_count": null,
   "metadata": {
    "scrolled": false
   },
   "outputs": [],
   "source": [
    "estimator.fit(inputs='/data/hsiming/Downloads/cub200/tfrecords/')"
   ]
  },
  {
   "cell_type": "code",
   "execution_count": null,
   "metadata": {},
   "outputs": [],
   "source": []
  }
 ],
 "metadata": {
  "kernelspec": {
   "display_name": "Python 3",
   "language": "python",
   "name": "python3"
  },
  "language_info": {
   "codemirror_mode": {
    "name": "ipython",
    "version": 3
   },
   "file_extension": ".py",
   "mimetype": "text/x-python",
   "name": "python",
   "nbconvert_exporter": "python",
   "pygments_lexer": "ipython3",
   "version": "3.6.7"
  },
  "toc": {
   "base_numbering": 1,
   "nav_menu": {},
   "number_sections": true,
   "sideBar": true,
   "skip_h1_title": false,
   "title_cell": "Table of Contents",
   "title_sidebar": "Contents",
   "toc_cell": false,
   "toc_position": {
    "height": "calc(100% - 180px)",
    "left": "10px",
    "top": "150px",
    "width": "204px"
   },
   "toc_section_display": true,
   "toc_window_display": true
  }
 },
 "nbformat": 4,
 "nbformat_minor": 2
}
